Workbook
Name ИменованныйДиапазон1: 'Матрица поставщиков'!$A$2:$A$100

Sheet Матрица продуктов
A1: Ингредиент | B1: Ед.изм. | C1: Вкусвилл | D1: Рынок-Бухта | E1: turkish-food
A2: Кориандр | B2: г | C2: =IFERROR(__xludf.DUMMYFUNCTION("IFERROR( FILTER( 'Матрица поставщиков'!E:E, 'Матрица поставщиков'!A:A = A2, 'Матрица поставщиков'!B:B = C1 ), 0 ) "),0.0) -> 0 | D2: =IFERROR(__xludf.DUMMYFUNCTION("IFERROR( FILTER( 'Матрица поставщиков'!E:E, 'Матрица поставщиков'!A:A = A2, 'Матрица поставщиков'!B:B = D1 ), 0 ) "),0.0) -> 0 | E2: =IFERROR(__xludf.DUMMYFUNCTION("IFERROR( FILTER( 'Матрица поставщиков'!E:E, 'Матрица поставщиков'!A:A = A2, 'Матрица поставщиков'!B:B = E1 ), 0 ) "),0.0) -> 0
A3: Корица | B3: г | C3: =IFERROR(__xludf.DUMMYFUNCTION("IFERROR( FILTER( 'Матрица поставщиков'!E:E, 'Матрица поставщиков'!A:A = A3, 'Матрица поставщиков'!B:B = C1 ), 0 ) "),0.0) -> 0 | D3: =IFERROR(__xludf.DUMMYFUNCTION("IFERROR( FILTER( 'Матрица поставщиков'!E:E, 'Матрица поставщиков'!A:A = A3, 'Матрица поставщиков'!B:B = D1 ), 0 ) "),0.0) -> 0 | E3: =IFERROR(__xludf.DUMMYFUNCTION("IFERROR( FILTER( 'Матрица поставщиков'!E:E, 'Матрица поставщиков'!A:A = A3, 'Матрица поставщиков'!B:B = E1 ), 0 ) "),0.0) -> 0
A4: Красный молотый перец | B4: г | C4: =IFERROR(__xludf.DUMMYFUNCTION("IFERROR( FILTER( 'Матрица поставщиков'!E:E, 'Матрица поставщиков'!A:A = A4, 'Матрица поставщиков'!B:B = C1 ), 0 ) "),0.0) -> 0 | D4: =IFERROR(__xludf.DUMMYFUNCTION("IFERROR( FILTER( 'Матрица поставщиков'!E:E, 'Матрица поставщиков'!A:A = A4, 'Матрица поставщиков'!B:B = D1 ), 0 ) "),0.0) -> 0 | E4: =IFERROR(__xludf.DUMMYFUNCTION("IFERROR( FILTER( 'Матрица поставщиков'!E:E, 'Матрица поставщиков'!A:A = A4, 'Матрица поставщиков'!B:B = E1 ), 0 ) "),0.0) -> 0
A5: Филе грудки куриное | B5: г | C5: =IFERROR(__xludf.DUMMYFUNCTION("IFERROR( FILTER( 'Матрица поставщиков'!E:E, 'Матрица поставщиков'!A:A = A5, 'Матрица поставщиков'!B:B = C1 ), 0 ) "),0.0) -> 0 | D5: =IFERROR(__xludf.DUMMYFUNCTION("IFERROR( FILTER( 'Матрица поставщиков'!E:E, 'Матрица поставщиков'!A:A = A5, 'Матрица поставщиков'!B:B = D1 ), 0 ) "),0.0) -> 0 | E5: =IFERROR(__xludf.DUMMYFUNCTION("IFERROR( FILTER( 'Матрица поставщиков'!E:E, 'Матрица поставщиков'!A:A = A5, 'Матрица поставщиков'!B:B = E1 ), 0 ) "),0.0) -> 0
A6: Бёдро без кости куриное | B6: г | C6: =IFERROR(__xludf.DUMMYFUNCTION("IFERROR( FILTER( 'Матрица поставщиков'!E:E, 'Матрица поставщиков'!A:A = A6, 'Матрица поставщиков'!B:B = C1 ), 0 ) "),0.0) -> 0 | D6: =IFERROR(__xludf.DUMMYFUNCTION("IFERROR( FILTER( 'Матрица поставщиков'!E:E, 'Матрица поставщиков'!A:A = A6, 'Матрица поставщиков'!B:B = D1 ), 0 ) "),0.0) -> 0 | E6: =IFERROR(__xludf.DUMMYFUNCTION("IFERROR( FILTER( 'Матрица поставщиков'!E:E, 'Матрица поставщиков'!A:A = A6, 'Матрица поставщиков'!B:B = E1 ), 0 ) "),0.0) -> 0
A7: Лимон | B7: г | C7: =IFERROR(__xludf.DUMMYFUNCTION("IFERROR( FILTER( 'Матрица поставщиков'!E:E, 'Матрица поставщиков'!A:A = A7, 'Матрица поставщиков'!B:B = C1 ), 0 ) "),0.0) -> 0 | D7: =IFERROR(__xludf.DUMMYFUNCTION("IFERROR( FILTER( 'Матрица поставщиков'!E:E, 'Матрица поставщиков'!A:A = A7, 'Матрица поставщиков'!B:B = D1 ), 0 ) "),0.0) -> 0 | E7: =IFERROR(__xludf.DUMMYFUNCTION("IFERROR( FILTER( 'Матрица поставщиков'!E:E, 'Матрица поставщиков'!A:A = A7, 'Матрица поставщиков'!B:B = E1 ), 0 ) "),0.0) -> 0
A8: ='Матрица поставщиков'!A9 -> Лук репчатый | B8: мл | C8: =IFERROR(__xludf.DUMMYFUNCTION("IFERROR( FILTER( 'Матрица поставщиков'!E:E, 'Матрица поставщиков'!A:A = A8, 'Матрица поставщиков'!B:B = C1 ), 0 ) "),0.0) -> 0 | D8: =IFERROR(__xludf.DUMMYFUNCTION("IFERROR( FILTER( 'Матрица поставщиков'!E:E, 'Матрица поставщиков'!A:A = A8, 'Матрица поставщиков'!B:B = D1 ), 0 ) "),0.0) -> 0 | E8: =IFERROR(__xludf.DUMMYFUNCTION("IFERROR( FILTER( 'Матрица поставщиков'!E:E, 'Матрица поставщиков'!A:A = A8, 'Матрица поставщиков'!B:B = E1 ), 0 ) "),0.0) -> 0
A9: Масло растительное | B9: мл | C9: =IFERROR(__xludf.DUMMYFUNCTION("IFERROR( FILTER( 'Матрица поставщиков'!E:E, 'Матрица поставщиков'!A:A = A9, 'Матрица поставщиков'!B:B = C1 ), 0 ) "),0.0) -> 0 | D9: =IFERROR(__xludf.DUMMYFUNCTION("IFERROR( FILTER( 'Матрица поставщиков'!E:E, 'Матрица поставщиков'!A:A = A9, 'Матрица поставщиков'!B:B = D1 ), 0 ) "),0.0) -> 0 | E9: =IFERROR(__xludf.DUMMYFUNCTION("IFERROR( FILTER( 'Матрица поставщиков'!E:E, 'Матрица поставщиков'!A:A = A9, 'Матрица поставщиков'!B:B = E1 ), 0 ) "),0.0) -> 0
A10: Оливковое масло | B10: мл | C10: =IFERROR(__xludf.DUMMYFUNCTION("IFERROR( FILTER( 'Матрица поставщиков'!E:E, 'Матрица поставщиков'!A:A = A10, 'Матрица поставщиков'!B:B = C1 ), 0 ) "),0.0) -> 0 | D10: =IFERROR(__xludf.DUMMYFUNCTION("IFERROR( FILTER( 'Матрица поставщиков'!E:E, 'Матрица поставщиков'!A:A = A10, 'Матрица поставщиков'!B:B = D1 ), 0 ) "),0.0) -> 0 | E10: =IFERROR(__xludf.DUMMYFUNCTION("IFERROR( FILTER( 'Матрица поставщиков'!E:E, 'Матрица поставщиков'!A:A = A10, 'Матрица поставщиков'!B:B = E1 ), 0 ) "),0.0) -> 0
A11: Сахар | B11: г | C11: =IFERROR(__xludf.DUMMYFUNCTION("IFERROR( FILTER( 'Матрица поставщиков'!E:E, 'Матрица поставщиков'!A:A = A11, 'Матрица поставщиков'!B:B = C1 ), 0 ) "),0.0) -> 0 | D11: =IFERROR(__xludf.DUMMYFUNCTION("IFERROR( FILTER( 'Матрица поставщиков'!E:E, 'Матрица поставщиков'!A:A = A11, 'Матрица поставщиков'!B:B = D1 ), 0 ) "),0.0) -> 0 | E11: =IFERROR(__xludf.DUMMYFUNCTION("IFERROR( FILTER( 'Матрица поставщиков'!E:E, 'Матрица поставщиков'!A:A = A11, 'Матрица поставщиков'!B:B = E1 ), 0 ) "),0.0) -> 0
A12: Сливочное масло | B12: г | C12: =IFERROR(__xludf.DUMMYFUNCTION("IFERROR( FILTER( 'Матрица поставщиков'!E:E, 'Матрица поставщиков'!A:A = A12, 'Матрица поставщиков'!B:B = C1 ), 0 ) "),0.0) -> 0 | D12: =IFERROR(__xludf.DUMMYFUNCTION("IFERROR( FILTER( 'Матрица поставщиков'!E:E, 'Матрица поставщиков'!A:A = A12, 'Матрица поставщиков'!B:B = D1 ), 0 ) "),0.0) -> 0 | E12: =IFERROR(__xludf.DUMMYFUNCTION("IFERROR( FILTER( 'Матрица поставщиков'!E:E, 'Матрица поставщиков'!A:A = A12, 'Матрица поставщиков'!B:B = E1 ), 0 ) "),0.0) -> 0
A13: Соль | B13: г | C13: =IFERROR(__xludf.DUMMYFUNCTION("IFERROR( FILTER( 'Матрица поставщиков'!E:E, 'Матрица поставщиков'!A:A = A13, 'Матрица поставщиков'!B:B = C1 ), 0 ) "),0.0) -> 0 | D13: =IFERROR(__xludf.DUMMYFUNCTION("IFERROR( FILTER( 'Матрица поставщиков'!E:E, 'Матрица поставщиков'!A:A = A13, 'Матрица поставщиков'!B:B = D1 ), 0 ) "),0.0) -> 0 | E13: =IFERROR(__xludf.DUMMYFUNCTION("IFERROR( FILTER( 'Матрица поставщиков'!E:E, 'Матрица поставщиков'!A:A = A13, 'Матрица поставщиков'!B:B = E1 ), 0 ) "),0.0) -> 0
A14: Сушёная мята | B14: г | C14: =IFERROR(__xludf.DUMMYFUNCTION("IFERROR( FILTER( 'Матрица поставщиков'!E:E, 'Матрица поставщиков'!A:A = A14, 'Матрица поставщиков'!B:B = C1 ), 0 ) "),0.0) -> 0 | D14: =IFERROR(__xludf.DUMMYFUNCTION("IFERROR( FILTER( 'Матрица поставщиков'!E:E, 'Матрица поставщиков'!A:A = A14, 'Матрица поставщиков'!B:B = D1 ), 0 ) "),0.0) -> 0 | E14: =IFERROR(__xludf.DUMMYFUNCTION("IFERROR( FILTER( 'Матрица поставщиков'!E:E, 'Матрица поставщиков'!A:A = A14, 'Матрица поставщиков'!B:B = E1 ), 0 ) "),0.0) -> 0
A15: Тимьян / Чабрец | B15: г | C15: =IFERROR(__xludf.DUMMYFUNCTION("IFERROR( FILTER( 'Матрица поставщиков'!E:E, 'Матрица поставщиков'!A:A = A15, 'Матрица поставщиков'!B:B = C1 ), 0 ) "),0.0) -> 0 | D15: =IFERROR(__xludf.DUMMYFUNCTION("IFERROR( FILTER( 'Матрица поставщиков'!E:E, 'Матрица поставщиков'!A:A = A15, 'Матрица поставщиков'!B:B = D1 ), 0 ) "),0.0) -> 0 | E15: =IFERROR(__xludf.DUMMYFUNCTION("IFERROR( FILTER( 'Матрица поставщиков'!E:E, 'Матрица поставщиков'!A:A = A15, 'Матрица поставщиков'!B:B = E1 ), 0 ) "),0.0) -> 0
A16: Тмин | B16: г | C16: =IFERROR(__xludf.DUMMYFUNCTION("IFERROR( FILTER( 'Матрица поставщиков'!E:E, 'Матрица поставщиков'!A:A = A16, 'Матрица поставщиков'!B:B = C1 ), 0 ) "),0.0) -> 0 | D16: =IFERROR(__xludf.DUMMYFUNCTION("IFERROR( FILTER( 'Матрица поставщиков'!E:E, 'Матрица поставщиков'!A:A = A16, 'Матрица поставщиков'!B:B = D1 ), 0 ) "),0.0) -> 0 | E16: =IFERROR(__xludf.DUMMYFUNCTION("IFERROR( FILTER( 'Матрица поставщиков'!E:E, 'Матрица поставщиков'!A:A = A16, 'Матрица поставщиков'!B:B = E1 ), 0 ) "),0.0) -> 0
A17: Томатная паста | B17: г | C17: =IFERROR(__xludf.DUMMYFUNCTION("IFERROR( FILTER( 'Матрица поставщиков'!E:E, 'Матрица поставщиков'!A:A = A17, 'Матрица поставщиков'!B:B = C1 ), 0 ) "),0.0) -> 0 | D17: =IFERROR(__xludf.DUMMYFUNCTION("IFERROR( FILTER( 'Матрица поставщиков'!E:E, 'Матрица поставщиков'!A:A = A17, 'Матрица поставщиков'!B:B = D1 ), 0 ) "),0.0) -> 0 | E17: =IFERROR(__xludf.DUMMYFUNCTION("IFERROR( FILTER( 'Матрица поставщиков'!E:E, 'Матрица поставщиков'!A:A = A17, 'Матрица поставщиков'!B:B = E1 ), 0 ) "),0.0) -> 0
A18: Чеснок | B18: г | C18: =IFERROR(__xludf.DUMMYFUNCTION("IFERROR( FILTER( 'Матрица поставщиков'!E:E, 'Матрица поставщиков'!A:A = A18, 'Матрица поставщиков'!B:B = C1 ), 0 ) "),0.0) -> 0 | D18: =IFERROR(__xludf.DUMMYFUNCTION("IFERROR( FILTER( 'Матрица поставщиков'!E:E, 'Матрица поставщиков'!A:A = A18, 'Матрица поставщиков'!B:B = D1 ), 0 ) "),0.0) -> 0 | E18: =IFERROR(__xludf.DUMMYFUNCTION("IFERROR( FILTER( 'Матрица поставщиков'!E:E, 'Матрица поставщиков'!A:A = A18, 'Матрица поставщиков'!B:B = E1 ), 0 ) "),0.0) -> 0
A19: Чёрный перец | B19: г | C19: =IFERROR(__xludf.DUMMYFUNCTION("IFERROR( FILTER( 'Матрица поставщиков'!E:E, 'Матрица поставщиков'!A:A = A19, 'Матрица поставщиков'!B:B = C1 ), 0 ) "),0.0) -> 0 | D19: =IFERROR(__xludf.DUMMYFUNCTION("IFERROR( FILTER( 'Матрица поставщиков'!E:E, 'Матрица поставщиков'!A:A = A19, 'Матрица поставщиков'!B:B = D1 ), 0 ) "),0.0) -> 0 | E19: =IFERROR(__xludf.DUMMYFUNCTION("IFERROR( FILTER( 'Матрица поставщиков'!E:E, 'Матрица поставщиков'!A:A = A19, 'Матрица поставщиков'!B:B = E1 ), 0 ) "),0.0) -> 0
A20: Маринованные огурцы (целые) | B20: г | C20: =IFERROR(__xludf.DUMMYFUNCTION("IFERROR( FILTER( 'Матрица поставщиков'!E:E, 'Матрица поставщиков'!A:A = A20, 'Матрица поставщиков'!B:B = C1 ), 0 ) "),0.0) -> 0 | D20: =IFERROR(__xludf.DUMMYFUNCTION("IFERROR( FILTER( 'Матрица поставщиков'!E:E, 'Матрица поставщиков'!A:A = A20, 'Матрица поставщиков'!B:B = D1 ), 0 ) "),0.0) -> 0 | E20: =IFERROR(__xludf.DUMMYFUNCTION("IFERROR( FILTER( 'Матрица поставщиков'!E:E, 'Матрица поставщиков'!A:A = A20, 'Матрица поставщиков'!B:B = E1 ), 0 ) "),0.0) -> 0
A21: Лаваш | B21: шт | C21: =IFERROR(__xludf.DUMMYFUNCTION("IFERROR( FILTER( 'Матрица поставщиков'!E:E, 'Матрица поставщиков'!A:A = A21, 'Матрица поставщиков'!B:B = C1 ), 0 ) "),0.0) -> 0 | D21: =IFERROR(__xludf.DUMMYFUNCTION("IFERROR( FILTER( 'Матрица поставщиков'!E:E, 'Матрица поставщиков'!A:A = A21, 'Матрица поставщиков'!B:B = D1 ), 0 ) "),0.0) -> 0 | E21: =IFERROR(__xludf.DUMMYFUNCTION("IFERROR( FILTER( 'Матрица поставщиков'!E:E, 'Матрица поставщиков'!A:A = A21, 'Матрица поставщиков'!B:B = E1 ), 0 ) "),0.0) -> 0
A22: Манная крупа | B22: г | C22: =IFERROR(__xludf.DUMMYFUNCTION("IFERROR( FILTER( 'Матрица поставщиков'!E:E, 'Матрица поставщиков'!A:A = A22, 'Матрица поставщиков'!B:B = C1 ), 0 ) "),0.0) -> 0 | D22: =IFERROR(__xludf.DUMMYFUNCTION("IFERROR( FILTER( 'Матрица поставщиков'!E:E, 'Матрица поставщиков'!A:A = A22, 'Матрица поставщиков'!B:B = D1 ), 0 ) "),0.0) -> 0 | E22: =IFERROR(__xludf.DUMMYFUNCTION("IFERROR( FILTER( 'Матрица поставщиков'!E:E, 'Матрица поставщиков'!A:A = A22, 'Матрица поставщиков'!B:B = E1 ), 0 ) "),0.0) -> 0
A23: Мука пшеничная (Французская штучка) | B23: г | C23: =IFERROR(__xludf.DUMMYFUNCTION("IFERROR( FILTER( 'Матрица поставщиков'!E:E, 'Матрица поставщиков'!A:A = A23, 'Матрица поставщиков'!B:B = C1 ), 0 ) "),0.0875) -> 0.0875 | D23: =IFERROR(__xludf.DUMMYFUNCTION("IFERROR( FILTER( 'Матрица поставщиков'!E:E, 'Матрица поставщиков'!A:A = A23, 'Матрица поставщиков'!B:B = D1 ), 0 ) "),0.0) -> 0 | E23: =IFERROR(__xludf.DUMMYFUNCTION("IFERROR( FILTER( 'Матрица поставщиков'!E:E, 'Матрица поставщиков'!A:A = A23, 'Матрица поставщиков'!B:B = E1 ), 0 ) "),0.0) -> 0
A24: Пекмез | B24: мл | C24: =IFERROR(__xludf.DUMMYFUNCTION("IFERROR( FILTER( 'Матрица поставщиков'!E:E, 'Матрица поставщиков'!A:A = A24, 'Матрица поставщиков'!B:B = C1 ), 0 ) "),0.0) -> 0 | D24: =IFERROR(__xludf.DUMMYFUNCTION("IFERROR( FILTER( 'Матрица поставщиков'!E:E, 'Матрица поставщиков'!A:A = A24, 'Матрица поставщиков'!B:B = D1 ), 0 ) "),0.0) -> 0 | E24: =IFERROR(__xludf.DUMMYFUNCTION("IFERROR( FILTER( 'Матрица поставщиков'!E:E, 'Матрица поставщиков'!A:A = A24, 'Матрица поставщиков'!B:B = E1 ), 0 ) "),1.0394736842105263) -> 1.0394737
A25: Арахис | B25: г | C25: =IFERROR(__xludf.DUMMYFUNCTION("IFERROR( FILTER( 'Матрица поставщиков'!E:E, 'Матрица поставщиков'!A:A = A25, 'Матрица поставщиков'!B:B = C1 ), 0 ) "),0.0) -> 0 | D25: =IFERROR(__xludf.DUMMYFUNCTION("IFERROR( FILTER( 'Матрица поставщиков'!E:E, 'Матрица поставщиков'!A:A = A25, 'Матрица поставщиков'!B:B = D1 ), 0 ) "),0.0) -> 0 | E25: =IFERROR(__xludf.DUMMYFUNCTION("IFERROR( FILTER( 'Матрица поставщиков'!E:E, 'Матрица поставщиков'!A:A = A25, 'Матрица поставщиков'!B:B = E1 ), 0 ) "),0.0) -> 0
A26: Молоко | B26: мл | C26: =IFERROR(__xludf.DUMMYFUNCTION("IFERROR( FILTER( 'Матрица поставщиков'!E:E, 'Матрица поставщиков'!A:A = A26, 'Матрица поставщиков'!B:B = C1 ), 0 ) "),0.0) -> 0 | D26: =IFERROR(__xludf.DUMMYFUNCTION("IFERROR( FILTER( 'Матрица поставщиков'!E:E, 'Матрица поставщиков'!A:A = A26, 'Матрица поставщиков'!B:B = D1 ), 0 ) "),0.0) -> 0 | E26: =IFERROR(__xludf.DUMMYFUNCTION("IFERROR( FILTER( 'Матрица поставщиков'!E:E, 'Матрица поставщиков'!A:A = A26, 'Матрица поставщиков'!B:B = E1 ), 0 ) "),0.0) -> 0
A27: Мороженое пломбир | B27: г | C27: =IFERROR(__xludf.DUMMYFUNCTION("IFERROR( FILTER( 'Матрица поставщиков'!E:E, 'Матрица поставщиков'!A:A = A27, 'Матрица поставщиков'!B:B = C1 ), 0 ) "),0.0) -> 0 | D27: =IFERROR(__xludf.DUMMYFUNCTION("IFERROR( FILTER( 'Матрица поставщиков'!E:E, 'Матрица поставщиков'!A:A = A27, 'Матрица поставщиков'!B:B = D1 ), 0 ) "),0.0) -> 0 | E27: =IFERROR(__xludf.DUMMYFUNCTION("IFERROR( FILTER( 'Матрица поставщиков'!E:E, 'Матрица поставщиков'!A:A = A27, 'Матрица поставщиков'!B:B = E1 ), 0 ) "),0.0) -> 0
A28: Тахин | B28: мл | C28: =IFERROR(__xludf.DUMMYFUNCTION("IFERROR( FILTER( 'Матрица поставщиков'!E:E, 'Матрица поставщиков'!A:A = A28, 'Матрица поставщиков'!B:B = C2 ), 0 ) "),0.0) -> 0 | D28: =IFERROR(__xludf.DUMMYFUNCTION("IFERROR( FILTER( 'Матрица поставщиков'!E:E, 'Матрица поставщиков'!A:A = A28, 'Матрица поставщиков'!B:B = D1 ), 0 ) "),0.0) -> 0 | E28: =IFERROR(__xludf.DUMMYFUNCTION("IFERROR( FILTER( 'Матрица поставщиков'!E:E, 'Матрица поставщиков'!A:A = A28, 'Матрица поставщиков'!B:B = E1 ), 0 ) "),1.3727272727272728) -> 1.3727273
A29: Йогурт | B29: г

Sheet Матрица поставщиков
A1: Ингредиент | B1: Поставщик | C1: Вес/Объем упаковки | D1: Стоимость упаковки | E1: Стоимость за 1 ед. изм. | F1: Дата проценки
A2: вода | B2: METRO | C2: 5000 | D2: 0 | E2: =D2/C2 -> 0 | F2: 46048 | J2: вход | K2: продукты | L2: цена филе бкбк | M2: цена филе грудки | Q2: вытяжка
A3: кориандр | B3: METRO | C3: 320 | D3: 398 | E3: =D3/C3 -> 1.24375 | F3: 45663 | J3: № тел | K3: https://b2b.lenta.com | L3: 480 | M3: 458 | Q3: https://psk-pro.ru
A4: корица | B4: METRO | C4: 100 | D4: 134 | E4: =D4/C4 -> 1.34 | F4: 45663 | J4: urazovildar@yandex.ru / axel33 | K4: https://napolke.ru | L4: 380 | M4: 369 | Q4: https://www.ventsistema.ru/uslugi/proektirovanie-system-ventilyacii-restoran-kafe
A5: Красный молотый перец | B5: METRO | C5: 365 | D5: 609 | E5: =D5/C5 -> 1.6684932 | F5: 45663 | J5: заявка отправлена | K5: www.ews.ru/ | N5: callcenter@ews.ru | Q5: https://ceds.ru/inzhenernye-sistemy/ventilyatsiya/ventilyatsiya-restoranov-kafe-i-barov
A6: Филе грудки куриное | B6: METRO | C6: 1000 | D6: 339 | E6: =D6/C6 -> 0.339 | F6: 45663 | G6: от 0 до +2С | H6: 10 дн? | J6: заявка отправлена | K6: https://www.abri-kos.ru | L6: 502 | M6: 441 | N6: с/м | Q6: https://psk-pro.ru
A7: Бёдро без кости куриное | B7: METRO | C7: 1000 | D7: 389 | E7: =D7/C7 -> 0.389 | F7: 45663 | G7: от 0 до +2С | H7: 10 дн? | J7: заявка отправлена | K7: https://marr.ru | Q7: https://ventell.ru/ventilyatsiya-pomescheniy/ventilyatsiya-obschepita
A8: Лимон | B8: METRO | C8: 1000 | D8: 259 | E8: =D8/C8 -> 0.259 | F8: 45663 | J8: Axel33 | K8: https://gfc-russia.ru/?version=2 | L8: 459 | M8: 421 | N8: зам | Q8: https://regul-vent.ru/page/montazh-ventilyatsii-dlya-predpriyatiy-obschestvennogo-pitaniya#2
A9: Лук репчатый | B9: METRO | C9: 1000 | D9: 57 | E9: =D9/C9 -> 0.057 | F9: 46051 | J9: заявка отправлена | K9: https://cherri.msk.ru | Q9: https://mosecoclean.ru/montazh-ventilyatsii-v-restorane
A10: Масло растительное | B10: METRO | C10: 5000 | D10: 609 | E10: =D10/C10 -> 0.1218 | F10: 46101 | G10: от 0 до +25С | H10: 365 дн | J10: заявка отправлена | K10: https://beriozkafood.ru | Q10: https://pskaksioma.ru/ventilyacziya-restoranov-kafe-i-barov
A11: Уксус яблочный | B11: METRO | C11: 250 | D11: 58 | E11: =D11/C11 -> 0.232 | F11: 45663 | J11: заявка отправлена | K11: https://fudstori.ru | Q11: https://www.avito.ru/moskva/predlozheniya_uslug/proektirovanie_i_montazh_sistem_ventilyatsii_2244962269?context=H4sIAAAAAAAA_wE_AMD_YToyOntzOjEzOiJsb2NhbFByaW9yaXR5IjtiOjE7czoxOiJ4IjtzOjE2OiJxbVh4cVBqYVhjbjdldnVMIjt9U6a5OT8AAAA
A12: Сахар | B12: METRO | C12: 1000 | D12: 69 | E12: =D12/C12 -> 0.069 | F12: 45663 | J12: заявка отправлена | K12: https://arosa.ru
A13: Сливочное масло | B13: METRO | C13: 450 | D13: 449 | E13: =D13/C13 -> 0.99777778 | F13: 46101 | J13: urazovildar@yandex.ru / Rakwl9rT | K13: https://vkusvill.ru/b2b | L13: 597 | M13: 583
A14: Соль | B14: METRO | C14: 1000 | D14: 42 | E14: =D14/C14 -> 0.042 | F14: 45663 | J14: заявка отправлена | K14: https://rosinterfood.ru
A15: Сушёная мята | B15: METRO | C15: 60 | D15: 113 | E15: =D15/C15 -> 1.8833333 | F15: 45663 | K15: https://azbuka-produktov.ru
A16: Тимьян / Чабрец | B16: озон | C16: 500 | D16: 414 | E16: =D16/C16 -> 0.828 | F16: 45663 | J16: заявка отправлена | K16: https://ice-m.com | L16: 300 | M16: 300 | N16: скорее всего з/м
A17: Тмин | B17: METRO | C17: 490 | D17: 596 | E17: =D17/C17 -> 1.2163265 | F17: 45663 | J17: заявка отправлена | K17: https://swlife.ru | L17: 430 | M17: 410 | N17: охл
A18: Томатная паста | B18: Вагиф | C18: 5000 | D18: 515 | E18: =D18/C18 -> 0.103 | F18: 45663 | G18: 4±2°С. | H18: 3 года | J18: заявка отправлена | K18: https://opttorg-horeca.ru | N18: фудсити
A19: Чеснок | B19: METRO | C19: 1000 | D19: 216 | E19: =D19/C19 -> 0.216 | F19: 45663 | J19: заявка отправлена | K19: https://fydopt.ru | N19: 9091694849 Оксана | O19: мерк чз всё есть
A20: Чёрный перец | B20: METRO | C20: 1000 | D20: 1057 | E20: =D20/C20 -> 1.057 | F20: 45663 | J20: заявка отправлена | K20: https://grossfood.ru
A21: Лаваш | B21: https://moslavash.ru | C21: 1 | D21: 9.5 | E21: 14.5 | F21: 45672 | G21: цена при заказе 100шт доставкой | H21: 5 суток | J21: заявка отправлена | K21: https://food-fresh.ru
A22: Петрушка | B22: METRO | C22: 90 | D22: 280 | E22: =D22/C22 -> 3.1111111 | F22: 45663 | J22: заявка отправлена | K22: https://fk-frutcity.ru
A23: Помидоры - сливовые | B23: METRO | C23: 1000 | D23: 350 | E23: =D23/C23 -> 0.35 | F23: 46101 | G23: от +2 до +8С
A24: Маринованные огурцы (целые) | B24: METRO | C24: 1500 | D24: 547 | E24: =D24/C24 -> 0.36466667 | F24: 46101
A25: копченая паприка 1 | B25: OZON | C25: 1000 | D25: 700 | E25: =D25/C25 -> 0.7 | F25: 45663
A26: Кетчуп Heinz | B26: METRO | C26: 800 | D26: 223 | E26: =D26/C26 -> 0.27875 | F26: 45663
A27: Мука | B27: METRO | C27: 2000 | D27: 76 | E27: =D27/C27 -> 0.038 | F27: 45663
A28: Манная крупа | B28: METRO | C28: 800 | D28: 69 | E28: =D28/C28 -> 0.08625 | F28: 46050
A29: Ванилин | B29: METRO | C29: 200 | D29: 460 | E29: =D29/C29 -> 2.3 | F29: 45663
A30: Тахин | B30: turkish-food | C30: 550 | D30: 755 | E30: =D30/C30 -> 1.3727273
A31: Чеддер плавленный | B31: METRO | C31: 150 | D31: 130 | E31: =D31/C31 -> 0.86666667 | F31: 45663 | G31: Hochland чизбургер | K31: упаковка
A32: Мука пшеничная (Французская штучка) | B32: Вкусвилл | C32: 2000 | D32: 175 | E32: =D32/C32 -> 0.0875 | K32: https://1ea.ru
A33: Пекмез | B33: turkish-food | C33: 380 | D33: 395 | E33: =D33/C33 -> 1.0394737 | K33: https://severupack.ru
A34: Арахис | B34: METRO | C34: 800 | D34: 340 | E34: =D34/C34 -> 0.425 | F34: 45663
A35: Молоко | B35: METRO | C35: 1000 | D35: 60 | E35: =D35/C35 -> 0.06 | F35: 45663
A36: Йогурт турецкий | B36: METRO | C36: 1000 | D36: 289 | E36: =D36/C36 -> 0.289 | F36: 45663 | G36: от 2С до 4С | H36: 3 суток
A37: Паприка | B37: METRO | C37: 1000 | D37: 670 | E37: =D37/C37 -> 0.67 | F37: 45663
A38: Сухой чеснок | B38: METRO | C38: 440 | D38: 590 | E38: =D38/C38 -> 1.3409091 | F38: 45663
A39: Лимонный сок | B39: METRO | C39: 1000 | D39: 284 | E39: =D39/C39 -> 0.284 | F39: 45663
A40: Фарш Primebeef Классик говяжий охлажденный | B40: METRO | C40: 2000 | D40: 1679 | E40: =D40/C40 -> 0.8395 | F40: 46048
A41: Сумах | C41: 500 | D41: 575 | E41: =D41/C41 -> 1.15 | F41: 45663
A42: Кориандр молотый | B42: Ozon | C42: 300 | D42: 204 | E42: =D42/C42 -> 0.68 | F42: 45663
A43: Зира (кумин) | B43: Ozon | C43: 300 | D43: 271 | E43: =D43/C43 -> 0.90333333 | F43: 45663
A44: Майонез 30% | B44: Вагиф | C44: 9500 | D44: 905 | E44: =D44/C44 -> 0.095263158 | F44: 45663
A45: Чеснок (сушёный) | B45: METRO | C45: 1000 | D45: 894 | E45: =D45/C45 -> 0.894
A46: Масло фритюрное | B46: METRO | C46: 5000 | D46: 920 | E46: =D46/C46 -> 0.184 | F46: 45663 | G46: 0 до +25С | H46: 365 дн
A47: Картофель фри | B47: METRO | C47: 2500 | D47: 489 | E47: =D47/C47 -> 0.1956 | F47: 45663 | G47: - 18С. | H47: 18 мес
A48: Упаковка для комбо 1_1 | B48: Мэтро METRO Chef Картофель фри 9х9мм замороженный, 2.5кг | C48: 100 | D48: 1500 | E48: =D48/C48 -> 15
A49: Перец турецкий острый | B49: Ozon | C49: 5000 | D49: 1563 | E49: =D49/C49 -> 0.3126
A50: Айран турецкий 2% | C50: 270 | D50: 42 | E50: =D50/C50 -> 0.15555556
A51: Айран турецкий 2% коктельный | B51: https://turkish-food.ru/tureckie-syry/ajran-tureckij-500ml | C51: 400 | D51: 95 | E51: =D51/C51 -> 0.2375
A52: Сахарный сироп | B52: Ozon | C52: 1000 | D52: 335 | E52: =D52/C52 -> 0.335
A53: Концентрат сока | B53: WB | C53: 1000 | D53: 400 | E53: =D53/C53 -> 0.4
A54: Вода газированная | B54: Ozon | C54: 2000 | D54: 58 | E54: =D54/C54 -> 0.029
A55: Лёд куб | C55: 1 | D55: 0 | E55: =D55/C55 -> 0
A56: Чай чёрный турецкий | C56: 500 | D56: 824 | E56: =D56/C56 -> 1.648
A57: Турецкий кофе KURUKAHVECI MEHMET EFENDI | B57: https://turkish-food.ru/tureckoe-kofe-kurukahveci-mehmet-efendi-500-gr?search=кофе | C57: 100 | D57: 130.4 | E57: =D57/C57 -> 1.304
A58: Турецкий кофе с фундуком nuri toplar | B58: https://www.wildberries.ru/catalog/258223891/detail.aspx | C58: 250 | D58: 1000 | E58: =D58/C58 -> 4
A59: Кардамон молотый | B59: https://www.ozon.ru/product/kardamon-molotyy-100-g-1849597845/?at=OgtEmzDNzuRK9R0RiNxw3nBiWB6KX0Iv7ygvrTqvEPqG | C59: 100 | D59: 450 | E59: =D59/C59 -> 4.5
A60: Сыр сулугуни | B60: https://gurman-llc.ru/catalog/syry/syr_suluguni_starodub_kopchyenyy_45_krug_800_gr/ | C60: 1000 | D60: 574 | E60: =D60/C60 -> 0.574
A61: Айран 2% | C61: 270 | D61: 42 | E61: =D61/C61 -> 0.15555556 | G61: https://vavilon5.github.io/assets/html/ayran.html
B62: https://country-shop.ru/katalog/products/food_beverages/salep-casvaa-250-gr
A64: копченая паприка 2 | B64: METRO | C64: 195 | D64: 511 | E64: =D64/C64 -> 2.6205128 | F64: 46101
A65: Чечевица красная | B65: METRO | C65: 2500 | D65: 559 | E65: =D65/C65 -> 0.2236 | F65: 46101
A66: Морковь | B66: перек | C66: 1000 | D66: 60 | E66: =D66/C66 -> 0.06
A67: Картофель | B67: METRO | C67: 1000 | D67: 49 | E67: =D67/C67 -> 0.049
A68: Чеддер для соуса плавленый | B68: METRO | C68: 1000 | D68: 600 | E68: =D68/C68 -> 0.6 | F68: 46115
A69: Курдюк | B69: METRO | C69: 1000 | D69: 619 | E69: =D69/C69 -> 0.619 | F69: 46051
A70: Фри в панировке | B70: METRO | C70: 2500 | D70: 499 | E70: =D70/C70 -> 0.1996
A71: Сахар порционный | B71: METRO | C71: 500 | D71: 389 | E71: =D71/C71 -> 0.778
A72: Размешиватель для напитков | B72: METRO | C72: 1000 | D72: 203 | E72: =D72/C72 -> 0.203
A73: Сгущенка | B73: Вагиф | C73: 1000 | D73: 130 | E73: =D73/C73 -> 0.13 | F73: 46049
A74: Какао-порошок | B74: METRO | C74: 185 | D74: 209 | E74: =D74/C74 -> 1.1297297 | F74: 46101
A75: Кунжут | B75: METRO | C75: 1000 | D75: 459 | E75: =D75/C75 -> 0.459 | F75: 46101
A76: Лук гранулированный | B76: METRO | C76: 480 | D76: 551 | E76: =D76/C76 -> 1.1479167
A77: Кола Добрый | B77: METRO | C77: 1 | D77: 52 | E77: =D77/C77 -> 52 | F77: 46050
A78: Хмели Сунели | B78: Вагиф | C78: 1000 | D78: 272 | E78: =D78/C78 -> 0.272 | F78: 46051
A79: Сырный соус Heinz | B79: METRO | C79: 1000 | D79: 499 | E79: =D79/C79 -> 0.499 | F79: 46100
A80: Перец Якан | B80: Ozon | C80: 2500 | D80: 1685 | E80: =D80/C80 -> 0.674 | F80: 46101
A81: Сливки 22% | B81: METRO | C81: 1000 | D81: 334 | E81: =D81/C81 -> 0.334
A82: Моцарелла | B82: METRO | C82: 500 | D82: 389 | E82: =D82/C82 -> 0.778
A83: Стейкхаус Фри | B83: METRO | C83: 2500 | D83: 636 | E83: =D83/C83 -> 0.2544
A84: Соус гриль | B84: METRO | C84: 1000 | D84: 900 | E84: =D84/C84 -> 0.9
A85: Айсберг | B85: METRO | C85: 1000 | D85: 239 | E85: =D85/C85 -> 0.239
A86: Петрушка свежая | B86: METRO | C86: 70 | D86: 65 | E86: =D86/C86 -> 0.92857143
A87: Лук красный | B87: METRO | C87: 1000 | D87: 79 | E87: =D87/C87 -> 0.079
A88: Лук сушеный жареный | B88: METRO | C88: 1000 | D88: 338 | E88: =D88/C88 -> 0.338
A89: Цитрат натрия | B89: Ozon | C89: 1000 | D89: 385 | E89: =D89/C89 -> 0.385
A90: Наршараб | B90: Вагиф | C90: 260 | D90: 60 | E90: =D90/C90 -> 0.23076923
A91: сыр Гойя | B91: METRO | C91: 1000 | D91: 1449 | E91: =D91/C91 -> 1.449
A92: Чиабатта | B92: METRO | C92: 30 | D92: 1295 | E92: =D92/C92 -> 43.166667
A93: Суджук | B93: METRO | C93: 300 | D93: 385 | E93: =D93/C93 -> 1.2833333
A94: сыр Российский | B94: 5 | C94: 311 | D94: 215 | E94: =D94/C94 -> 0.69131833
A95: Исот | C95: 500 | D95: 595 | E95: =D95/C95 -> 1.19
A96: Орегано | C96: 200 | D96: 272 | E96: =D96/C96 -> 1.36
A97: Скумбрия | B97: Адмирал | C97: 1000 | D97: 550 | E97: =D97/C97 -> 0.55
A98: Соевый соус | B98: METRO | C98: 1000 | D98: 111 | E98: =D98/C98 -> 0.111
A99: Лук белый | C99: 1000 | D99: 157 | E99: =D99/C99 -> 0.157
A100: Салеп | C100: 200 | D100: 347 | E100: =D100/C100 -> 1.735
A101: Перец красный сладкий | B101: METRO | C101: 1000 | D101: 205 | E101: =D101/C101 -> 0.205
...

Sheet Сводная
A1: Категория | B1: Наименование | C1: цена | D1: цена в доставке | E1: cost финальный | F1: cost продуктов | G1: выход | H1: с/с продуктов | I1: с/с списания | J1: с/с упаковка | K1: с/с общая
A2: Дюрюмы
B3: ='Дюрюм'!B1 -> #REF! | C3: ='Дюрюм'!B33 -> #REF! | D3: ='Дюрюм'!B35 -> #REF! | E3: ='Дюрюм'!B30 -> #REF! | F3: ='Дюрюм'!B32 -> #REF! | G3: ='Дюрюм'!I11 -> #REF! | H3: ='Дюрюм'!C18 -> #REF! | I3: ='Дюрюм'!C19 -> #REF! | J3: ='Дюрюм'!C24 -> #REF! | K3: ='Дюрюм'!C28 -> #REF!
B4: ='Искандер дюрюм Zurna'!B1 -> Iskendy Durum Zurna | C4: ='Искандер дюрюм Zurna'!B30 -> 800 | D4: ='Искандер дюрюм Zurna'!B36 -> 1150 | E4: ='Искандер дюрюм Zurna'!B31 -> 0.22637143 | F4: ='Искандер дюрюм Zurna'!B32 -> 0.20554018 | G4: ='Искандер дюрюм Zurna'!I11 -> 721 | H4: ='Искандер дюрюм Zurna'!C18 -> 164.43214 | I4: ='Искандер дюрюм Zurna'!C19 -> 6.5772858 | J4: ='Искандер дюрюм Zurna'!C20 -> 1.2 | K4: ='Искандер дюрюм Zurna'!C25 -> 172.20943
A5: Напитки
B6: ='Чай чёрный'!B1 -> Чай чёрный | C6: ='Чай чёрный'!C21 -> 150 | E6: ='Чай чёрный'!C22 -> 0.054998222 | F6: ='Чай чёрный'!C23 -> 0.0080111111 | G6: ='Чай чёрный'!I6 -> 4800 | H6: ='Чай чёрный'!D16 -> 1.2016667 | I6: ='Чай чёрный'!D17 -> 0.048066667 | J6: ='Чай чёрный'!D18 -> 7 | K6: ='Чай чёрный'!D19 -> 8.2497333
B7: Айран | C7: ='Айран'!C23 -> 190 | D7: ='Айран'!D23 -> 271.42857 | E7: ='Айран'!C24 -> 0.22105263 | G7: ='Айран'!F5 -> 270
B8: ='Кофе по-турецки'!B1 -> Кофе по-турецки | C8: ='Кофе по-турецки'!C23 -> 250 | E8: ='Кофе по-турецки'!C24 -> 0.1152864 | F8: ='Кофе по-турецки'!C25 -> 0.10316 | G8: ='Кофе по-турецки'!I8 -> 100 | H8: ='Кофе по-турецки'!D18 -> 25.79 | I8: ='Чай чёрный'!D17 -> 0.048066667 | J8: ='Кофе по-турецки'!D20 -> 2 | K8: ='Кофе по-турецки'!D21 -> 28.8216
B9: ='Кофе по-турецки с кардамоном'!B1 -> Кофе по-турецки с кардамоном | C9: ='Кофе по-турецки с кардамоном'!C22 -> 240 | E9: ='Кофе по-турецки с кардамоном'!C23 -> #N/A | F9: ='Кофе по-турецки с кардамоном'!C24 -> #N/A | G9: ='Кофе по-турецки с кардамоном'!I7 -> 100 | H9: ='Кофе по-турецки с кардамоном'!D17 -> #N/A | I9: ='Кофе по-турецки с кардамоном'!D18 -> #N/A | J9: ='Кофе по-турецки с кардамоном'!D19 -> 4 | K9: ='Кофе по-турецки с кардамоном'!D20 -> #N/A
B10: ='Кофе по-турецки с фундуком'!B1 -> Кофе по-турецки с фундуком | C10: ='Кофе по-турецки с фундуком'!C21 -> 350 | E10: ='Кофе по-турецки с фундуком'!C22 -> 0.13028571 | F10: ='Кофе по-турецки с фундуком'!C23 -> 0.11428571 | G10: ='Кофе по-турецки с фундуком'!I6 -> 110 | H10: ='Кофе по-турецки с фундуком'!D16 -> 40 | I10: ='Кофе по-турецки с фундуком'!D17 -> 1.6 | J10: ='Кофе по-турецки с фундуком'!D18 -> 4 | K10: ='Кофе по-турецки с фундуком'!D19 -> 45.6
B11: Лимонад | C11: ='Лимонад'!C28 -> 200 | E11: ='Лимонад'!C29 -> 0.1896075 | F11: ='Лимонад'!C30 -> 0.14525 | G11: ='Лимонад'!I9 -> 365 | H11: ='Лимонад'!D23 -> 29.05 | I11: ='Лимонад'!D24 -> 0.8715 | J11: ='Лимонад'!D25 -> 8 | K11: ='Лимонад'!D26 -> 37.9215
B12: ='Айран коктейль'!B1 -> Айран коктейль | C12: ='Айран коктейль'!C25 -> 290 | E12: ='Айран коктейль'!C26 -> 0.25275862 | F12: ='Айран коктейль'!C27 -> 0.21982759 | G12: ='Айран коктейль'!I9 -> 365 | H12: ='Айран коктейль'!D20 -> 63.75 | I12: ='Айран коктейль'!D21 -> 2.55 | J12: ='Айран коктейль'!D22 -> 7 | K12: ='Айран коктейль'!D23 -> 73.3
A13: Фингерфуд
B14: ='Фри на продажу'!B1 -> Фри | C14: ='Фри на продажу'!C33 -> 230 | D14: ='Фри на продажу'!C39 -> 330 | E14: ='Фри на продажу'!C34 -> 0.19005646 | F14: ='Фри на продажу'!C35 -> 0.14544776 | G14: ='Фри на продажу'!I8 -> 100 | H14: ='Фри на продажу'!D18 -> 33.452985 | I14: ='Фри на продажу'!D19 -> 2 | J14: ='Фри на продажу'!D20 -> 1.2 | K14: ='Фри на продажу'!D26 -> 45.972985
A15: Суп
B16: ='Чечевичный суп'!B1 -> Чечевичный суп | C16: ='Чечевичный суп'!B24 -> 300 | D16: ='Чечевичный суп'!B27 -> 430 | E16: ='Чечевичный суп'!B22 -> 0.14035644
A17: Extra
B18: ='Сырный соус'!B1 -> Сырный соус | C18: ='Сырный соус'!C30 -> 70 | D18: ='Сырный соус'!C36 -> 100 | E18: ='Сырный соус'!C31 -> 0.28898571 | F18: ='Сырный соус'!C32 -> 0.22098571 | G18: ='Сырный соус'!I5 -> 30 | H18: ='Сырный соус'!C10 -> 15.469 | I18: ='Сырный соус'!D16 | J18: ='Сырный соус'!J31 -> 4.76 | K18: ='Сырный соус'!J33 -> 20.229
B19: ='Перец Якан'!B1 -> Перец Якан | C19: ='Перец Якан'!C30 -> 60 | D19: ='Перец Якан'!C36 -> 85 | E19: ='Перец Якан'!C31 -> 0.17246667
B20: ='Кетчуп'!B1 -> Кетчуп | C20: ='Кетчуп'!C30 -> 70 | D20: ='Кетчуп'!C36 -> 100 | E20: ='Кетчуп'!C31 -> 0.19144643 | F20: ='Кетчуп'!C32 -> 0.12344643 | G20: ='Кетчуп'!I5 -> 30 | H20: ='Кетчуп'!G5 -> 8.64125 | J20: ='Кетчуп'!I38 -> 4.76 | K20: ='Кетчуп'!I39 -> 13.40125
A21: Десерты
B22: ='Манная халва'!B1 -> Манная халва | C22: ='Манная халва'!C20 -> 250 | D22: ='Манная халва'!C25 -> 350 | E22: ='Манная халва'!C21 -> 0.20394327 | F22: ='Манная халва'!C22 -> 0.10970327 | G22: ='Манная халва'!B10 -> 150 | H22: ='Манная халва'!C10 -> 27.425819 | I22: ='Манная халва'!G19 -> 2 | J22: ='Манная халва'!D16 -> 23.56 | K22: ='Манная халва'!D17 -> 50.985819
B23: ='Манная халва с шоко'!B1 -> Манная халва с шоколадом | C23: ='Манная халва с шоко'!C21 -> 300 | D23: ='Манная халва с шоко'!C26 -> 430 | E23: ='Манная халва с шоко'!C22 -> 0.1936693 | F23: ='Манная халва с шоко'!C23 -> 0.11513596 | G23: ='Манная халва с шоко'!I6 -> 180 | H23: ='Манная халва с шоко'!D16 -> 34.540789 | I23: ='Манная халва с шоко'!D17 -> 0 | J23: ='Манная халва с шоко'!D18 -> 23.56 | K23: ='Манная халва с шоко'!C11 -> 34.540789
A24: Кмобо
B25: ='Комбо-1_1'!B1 -> Комбо: Дюрюм + фри + соус + напиток | C25: ='Комбо-1_1'!G8 -> 850 | D25: ='Комбо-1_1'!G10 -> 1360 | E25: ='Комбо-1_1'!L8 -> #REF! | G25: ='Комбо-1_1'!B8 -> 480 | H25: ='Комбо-1_1'!D8 -> #REF! | J25: ='Комбо-1_1'!D7 -> 52 | K25: ='Комбо-1_1'!D8 -> #REF!
B26: ='Комбо-1_2'!B1 -> Комбо: Дюрюм + суп +фри + соус + напиток | C26: ='Комбо-1_2'!H9 -> 950 | D26: ='Комбо-1_2'!H11 -> 1360 | E26: ='Комбо-1_2'!L9 -> #REF! | G26: ='Комбо-1_2'!B9 -> 950 | H26: ='Комбо-1_2'!E9 -> #REF! | K26: ='Комбо-1_2'!E9 -> #REF!

Sheet Доставка
A1: Название | B1: % | D1: Коэффициент надбавки
A2: Комиссия яндекса | B2: 30
A3: стоимость доставки в заказе в долях
A4: Итого | B4: =sum(B2:B3) -> 30

Sheet Сырный соус
A1: Наименование ТТК: | B1: Сырный соус
A3: Ингредиент | B3: Брутто | C3: Нетто | D3: Ед.изм. | E3: вес потери | F3: % потери | G3: с/с руб. | H3: с/с % | I3: Выход (мл.)
A4: Сырный соус Heinz | B4: 31 | C4: 30 | D4: г. | E4: =B4-C4 -> 1 | F4: =E4/B4*100 -> 3.2258065 | G4: =VLOOKUP(A4,'Матрица поставщиков'!A1:E530,5,0) * B4 -> 15.469 | H4: =G4/G5 -> 1
A5: Итого | B5: =SUM(B4) -> 31 | C5: =SUM(C4) -> 30 | D5: г. | E5: =B5-C5 -> 1 | F5: =E5/B5*100 -> 3.2258065 | G5: =SUM(G4) -> 15.469 | H5: =SUM(H4) -> 1 | I5: =B5-E5 -> 30
A7: Технология приготовления
A8: Добавить в соусник 30гр соуса
B9: выход | C9: с/с
B10: =I5 -> 30 | C10: =G5/I5*B10 -> 15.469
B11: 1 | C11: =G5/I5*B11 -> 0.51563333
B13: Для расчёта цены продажи
C14: % | D14: руб | E14: цена так
F15: cost (%) | G15: 10 | H15: 15 | I15: 20
F16: price | G16: =D23*100/G15 -> 0 | H16: =D23*100/H15 -> 0 | I16: =D23*100/I15 -> 0
H21: на месте | I21: с собой | J21: доставка
G22: списания | H22: 0 | I22: 0 | J22: 0
G23: салфетки 4 шт. | H23: 0 | I23: 0 | J23: 0
G24: зубочистка | H24: 0 | I24: 0 | J24: 0
G25: пакет | H25: 0 | I25: 0 | J25: 0
G26: наклейка брендированная | H26: 2.5 | I26: 2.5 | J26: 2.5
G27: Соусник | H27: 2.26 | I27: 2.26 | J27: 2.26
G28: Крышка | H28: 0 | I28: 0 | J28: 0
B30: цена | C30: 70 | D30: =C30+J31 -> 74.76
B31: cost общий | C31: =J33/C30 -> 0.28898571 | G31: упаковка | H31: =SUM(H22:H30) -> 4.76 | I31: =SUM(I22:I30) -> 4.76 | J31: =SUM(J22:J30) -> 4.76
B32: cost - продукции | C32: =G5/C30 -> 0.22098571
G33: с/с общий | J33: =G5+J31 -> 20.229
B35: цена | C35: 70
B36: доставка | C36: 100

Sheet Кетчуп
A1: Наименование ТТК: | B1: Кетчуп
A3: Ингредиент | B3: Брутто | C3: Нетто | D3: Ед.изм. | E3: вес потери | F3: % потери | G3: с/с руб. | H3: с/с % | I3: Выход (мл.)
A4: Кетчуп Heinz | B4: 31 | C4: 30 | D4: г. | E4: =B4-C4 -> 1 | F4: =E4/B4*100 -> 3.2258065 | G4: =VLOOKUP(A4,'Матрица поставщиков'!A1:E530,5,0) * B4 -> 8.64125 | H4: =G4/G5 -> 1
A5: Итого | B5: =SUM(B4) -> 31 | C5: =SUM(C4) -> 30 | D5: г. | E5: =B5-C5 -> 1 | F5: =E5/B5*100 -> 3.2258065 | G5: =SUM(G4) -> 8.64125 | H5: =SUM(H4) -> 1 | I5: =B5-E5 -> 30
A7: Технология приготовления
A8: Добавить в соусник 30гр соуса
B9: выход | C9: с/с
B10: =I5 -> 30 | C10: =G5/I5*B10 -> 8.64125
B11: 1 | C11: =G5/I5*B11 -> 0.28804167
B13: Для расчёта цены продажи
C14: % | D14: руб | E14: цена так
F15: cost (%) | G15: 10 | H15: 15 | I15: 20
F16: price | G16: =D23*100/G15 -> 0 | H16: =D23*100/H15 -> 0 | I16: =D23*100/I15 -> 0
B30: цена | C30: 70 | D30: =C30+I38 -> 74.76 | G30: на месте | H30: с собой | I30: доставка
B31: cost общий | C31: =I39/C30 -> 0.19144643 | F31: списания | G31: 0 | H31: 0 | I31: 0
B32: cost - продукции | C32: =G5/C30 -> 0.12344643 | F32: салфетки 4 шт. | G32: 0 | H32: 0 | I32: 0
F33: зубочистка | G33: 0 | H33: 0 | I33: 0
F34: пакет | G34: 0 | H34: 0 | I34: 0
B35: цена | C35: 70 | F35: наклейка брендированная | G35: 2.5 | H35: 2.5 | I35: 2.5
B36: доставка | C36: 100 | F36: Соусник | G36: 2.26 | H36: 2.26 | I36: 2.26
F37: Крышка | G37: 0 | H37: 0 | I37: 0
F38: упаковка | G38: =SUM(G31:G37) -> 4.76 | H38: =SUM(H31:H37) -> 4.76 | I38: =SUM(I31:I37) -> 4.76
F39: с/с общая | I39: =G5+I38 -> 13.40125

Sheet Лимонад
A1: Наименование ТТК: | B1: Чай чёрный
K2: Вкусы
A3: Ингредиент | B3: Брутто | C3: Нетто | D3: Ед.изм. | E3: вес потери | F3: % потери | G3: с/с руб. | H3: с/с % | I3: Выход (мл.) | K3: База | L3: Акцент
A4: Вода газированная | B4: 150 | C4: =B4 -> 150 | D4: мл. | E4: =B4-C4 -> 0 | F4: =E4/B4*100 -> 0 | G4: =VLOOKUP(A4,'Матрица поставщиков'!A1:E60,5,False) * B4 -> 4.35 | H4: =G4/G9 -> 0.14974182 | K4: Арбуз | L4: Айва
A5: Концентрат сока | B5: 25 | C5: =B5 -> 25 | D5: мл. | E5: =B5-C5 -> 0 | F5: =E5/B5*100 -> 0 | G5: =VLOOKUP(A5,'Матрица поставщиков'!A1:E100,5,False) * B5 -> 10 | H5: =G5/$G$9 -> 0.34423408 | K5: Гранат | L5: Яблоко
A6: Концентрат сока | B6: 20 | C6: =B6 -> 20 | D6: мл. | E6: =B6-C6 -> 0 | F6: =E6/B6*100 -> 0 | G6: =VLOOKUP(A6,'Матрица поставщиков'!A2:E101,5,False) * B6 -> 8 | H6: =G6/$G$9 -> 0.27538726 | K6: Кизил | L6: Лимон
A7: Сахарный сироп | B7: 20 | C7: 20 | D7: мл. | E7: =B7-C7 -> 0 | F7: =E7/B7*100 -> 0 | G7: =VLOOKUP(A7,'Матрица поставщиков'!A3:E62,5,False) * B7 -> 6.7 | H7: =G7/$G$9 -> 0.23063683 | K7: Виноград | L7: Розовая вода
A8: Лёд куб | B8: 150 | C8: 150 | D8: мл. | E8: =B8-C8 -> 0 | F8: =E8/B8*100 -> 0 | G8: =VLOOKUP(A8,'Матрица поставщиков'!A4:E62,5,False) * B8 -> 0 | H8: =G8/$G$9 -> 0 | K8: Клубника | L8: Розмарин
A9: Итого | B9: =SUM(B4:B8) -> 365 | C9: =SUM(C3:C8) -> 365 | D9: - | E9: =B9-C9 -> 0 | F9: =E9/B9*100 -> 0 | G9: =SUM(G4:G8) -> 29.05 | H9: =SUM(H4:H8) -> 1 | I9: =B9-E9 -> 365
A11: Технология приготовления
A12: 1. Смешать газированную воду, концентрат сока, сахарный сиор, лёд
B17: Для расчёта цены продажи
B18: выход | C18: с/с | E18: cost (%) | F18: 10 | G18: 15 | H18: 20
B19: =B9 -> 365 | C19: =G9/I9*B19 -> 29.05 | E19: price | F19: =D26*100/F18 -> 379.215 | G19: =D26*100/G18 -> 252.81 | H19: =D26*100/H18 -> 189.6075
B20: 1 | C20: =G9/I9*B20 -> 0.079589041
C22: % | D22: руб
B23: с/с блюда | C23: =D23/D26 -> 0.76605619 | D23: =C19 -> 29.05
B24: списания | C24: 0.03 | D24: =D23*C24 -> 0.8715
B25: упаковка | C25: =D25/D26 -> 0.21096212 | D25: 8
B26: Итого с/с | D26: =SUM(D23:D25) -> 37.9215
B28: цена | C28: 200
B29: cost общий | C29: =D26/C28 -> 0.1896075
B30: cost - продукции | C30: =D23/C28 -> 0.14525

Sheet Айран
A1: Наименование ТТК: | B1: Айран
A3: Ингредиент | B3: Брутто | C3: Ед.изм. | D3: с/с руб. | E3: с/с % | F3: Выход (мл.)
A4: Айран 2% | B4: 270 | C4: г. | D4: =VLOOKUP(A4,'Матрица поставщиков'!A1:E100,5,0) * B4 -> 42 | E4: =D4/D5 -> 1 | F4: =B5 -> 270
A5: Итого | B5: =B4 -> 270 | C5: - | D5: =SUM(D4) -> 42 | E5: =SUM(E4) -> 1 | F5: =SUM(F4) -> 270
B9: выход | C9: с/с
B10: =B5 -> 270 | C10: =D5 -> 42
B11: 1 | C11: =C10/250 -> 0.168
B13: Для расчёта цены продажи
C14: % | D14: руб | E14: цена так
B15: с/с блюда | C15: =D15/D18 -> 1 | D15: =C10 -> 42 | F15: cost (%) | G15: 10 | H15: 15 | I15: 20
B16: списания | C16: 0.04 | D16: 0 | F16: price | G16: =D18*100/G15 -> 420 | H16: =D18*100/H15 -> 280 | I16: =D18*100/I15 -> 210
B17: упаковка | C17: =D17/D18 -> 0 | D17: 0
B18: Итого с/с | D18: =SUM(D15:D17) -> 42
C22: Зал | D22: Доставка
B23: цена | C23: 190 | D23: =(C23/70)*100 -> 271.42857
B24: cost общий | C24: =D18/C23 -> 0.22105263
B25: cost - продукции | C25: =D15/C23 -> 0.22105263

Sheet Айран коктейль
A1: Наименование ТТК: | B1: Айран коктейль
A3: Ингредиент | B3: Брутто | C3: Нетто | D3: Ед.изм. | E3: вес потери | F3: % потери | G3: с/с руб. | H3: с/с % | I3: Выход (мл.)
A4: Айран турецкий 2% коктельный | B4: 200 | C4: =B4 -> 200 | D4: мл | E4: =B4-C4 -> 0 | F4: =E4/B4*100 -> 0 | G4: =VLOOKUP(A4,'Матрица поставщиков'!A1:E52,5,False) * B4 -> 47.5 | H4: =G4/G9 -> 0.74509804
A5: Сахарный сироп | B5: 10 | C5: =B5 -> 10 | D5: мл | E5: =B5-C5 -> 0 | F5: =E5/B5*100 -> 0 | G5: =VLOOKUP(A5,'Матрица поставщиков'!A1:E53,5,False) * B5 -> 3.35 | H5: =G5/G9 -> 0.05254902
A6: Концентрат сока | B6: 25 | C6: =B6 -> 25 | D6: мл | E6: =B6-C6 -> 0 | F6: =E6/B6*100 -> 0 | G6: =VLOOKUP(A6,'Матрица поставщиков'!A1:E57,5,False) * B6 -> 10 | H6: =G6/G9 -> 0.15686275
A7: Вода газированная | B7: 100 | C7: =B7 -> 100 | D7: мл | E7: =B7-C7 -> 0 | F7: =E7/B7*100 -> 0 | G7: =VLOOKUP(A7,'Матрица поставщиков'!A2:E58,5,False) * B7 -> 2.9 | H7: =G7/G9 -> 0.045490196
A8: Лёд куб | B8: 30 | C8: =B8 -> 30 | D8: г | E8: =B8-C8 -> 0 | F8: =E8/B8*100 -> 0 | G8: =VLOOKUP(A8,'Матрица поставщиков'!A3:E59,5,False) * B8 -> 0 | H8: =G8/G9 -> 0
A9: Итого | B9: =sum(B4:B8) -> 365 | C9: =SUM(C4:C8) -> 365 | D9: - | E9: =B9-C9 -> 0 | F9: =E9/B9*100 -> 0 | G9: =SUM(G4:G8) -> 63.75 | H9: =SUM(H4:H6) -> 0.9545098 | I9: =B9-E9 -> 365
A11: Технология приготовления
A12: 1. Смешать сахарный сироп с концентратом 2. Влить смесь в айран и взболтать 3. Добавить газированную воду 4. Добавить кубики льда 5. Смешать (не взбалтывать)
B14: выход | C14: с/с
B15: =I9 -> 365 | C15: =G9/I9*B15 -> 63.75
B16: 1 | C16: =G9/I9*B16 -> 0.17465753
B18: Для расчёта цены продажи
C19: % | D19: руб
B20: с/с блюда | C20: =D20/D23 -> 0.86971351 | D20: =C15 -> 63.75 | F20: cost (%) | G20: 15 | H20: 20 | I20: 22
B21: списания | C21: 0.04 | D21: =D20*C21 -> 2.55 | F21: price | G21: =D23*100/G20 -> 488.66667 | H21: =D23*100/H20 -> 366.5 | I21: =D23*100/I20 -> 333.18182
B22: упаковка | C22: =D22/D23 -> 0.095497954 | D22: 7
B23: Итого с/с | D23: =SUM(D20:D22) -> 73.3
B25: цена | C25: 290
B26: cost общий | C26: =D23/C25 -> 0.25275862
B27: cost - продукции | C27: =D20/C25 -> 0.21982759

Sheet Чай чёрный
A1: Наименование ТТК: | B1: Чай чёрный
A3: Ингредиент | B3: Брутто | C3: Нетто | D3: Ед.изм. | E3: вес потери | F3: % потери | G3: с/с руб. | H3: с/с % | I3: Выход (мл.)
A4: Чай чёрный турецкий | B4: 17.5 | C4: =B4 -> 17.5 | D4: г. | E4: =B4-C4 -> 0 | F4: =E4/B4*100 -> 0 | G4: =VLOOKUP(A4,'Матрица поставщиков'!A1:E60,5,False) * B4 -> 28.84 | H4: =G4/G6 -> 1
A5: вода | B5: 4800 | C5: =B5 -> 4800 | D5: г. | E5: =B5-C5 -> 0 | F5: =E5/B5*100 -> 0 | G5: =(VLOOKUP(A5,'Матрица поставщиков'!A1:E53,5,False) * B5)/10 -> 0 | H5: =G5/G6 -> 0
A6: Итого | B6: =B5 -> 4800 | C6: =B6 -> 4800 | D6: - | E6: =B6-C6 -> 0 | F6: =E6/B6*100 -> 0 | G6: =SUM(G4:G5) -> 28.84 | H6: =SUM(H4:H5) -> 1 | I6: =B6-E6 -> 4800
A8: Технология приготовления
A9: 1. Засыпать чай в чашку 2. Залить кипятком
B10: выход | C10: с/с
B11: 200 | C11: =G6/I6*B11 -> 1.2016667
B12: 1 | C12: =G6/I6*B12 -> 0.0060083333
B14: Для расчёта цены продажи
C15: % | D15: руб | E15: цена так
B16: с/с блюда | C16: =D16/D19 -> 0.14566127 | D16: =C11 -> 1.2016667 | F16: cost (%) | G16: 10 | H16: 15 | I16: 20
B17: списания | C17: 0.04 | D17: =D16*C17 -> 0.048066667 | F17: price | G17: =D19*100/G16 -> 82.497333 | H17: =D19*100/H16 -> 54.998222 | I17: =D19*100/I16 -> 41.248667
B18: упаковка | C18: =D18/D19 -> 0.84851228 | D18: 7
B19: Итого с/с | D19: =SUM(D16:D18) -> 8.2497333
B21: цена | C21: 150
B22: cost общий | C22: =D19/C21 -> 0.054998222
B23: cost - продукции | C23: =D16/C21 -> 0.0080111111

Sheet Манная халва с шоко
A1: Наименование ТТК: | B1: Манная халва с шоколадом
A3: Ингредиент | B3: Брутто | C3: Нетто | D3: Ед.изм. | E3: вес потери | F3: % потери | G3: с/с руб. | H3: с/с % | I3: Выход (мл.)
A4: п/ф Манная халва | B4: 150 | C4: 150 | D4: г. | E4: =B4-C4 -> 0 | F4: =E4/B4*100 -> 0 | G4: =B4*'пф Манная халва'!D23 -> 27.425819 | H4: =G4/G6 -> 0.79401252
A5: п/ф Топинг шоколадный | B5: 30 | C5: 30 | D5: г. | E5: =B5-C5 -> 0 | F5: =E5/B5*100 -> 0 | G5: =B5*'пф Топинг шоколадный'!D23 -> 7.1149701 | H5: =G5/$G$6 -> 0.20598748
A6: Итого | B6: =SUM(B4:B5) -> 180 | C6: =SUM(C4:C5) -> 180 | D6: г. | E6: =B6-C6 -> 0 | F6: =E6/B6*100 -> 0 | G6: =SUM(G4:G5) -> 34.540789 | H6: =SUM(H3:H5) -> 1 | I6: =C6 -> 180
A8: Технология приготовления
A9: Выложить в тару, шоколад сверху, подогреть в СВЧ 1.5 мин на средней мощности. Подать
B10: выход | C10: с/с
B11: 180 | C11: =G6/I6*B11 -> 34.540789
B12: 1 | C12: =G6/I6*B12 -> 0.19189327
B14: Для расчёта цены продажи
C15: % | D15: руб
B16: с/с блюда | C16: =D16/D19 -> 0.59449776 | D16: =C11 -> 34.540789 | F16: cost (%) | G16: 10 | H16: 15 | I16: 20
B17: списания | C17: 0 | D17: =D16*C17 -> 0 | F17: price | G17: =D19*100/G16 -> 581.00789 | H17: =D19*100/H16 -> 387.33859 | I17: =D19*100/I16 -> 290.50394
B18: упаковка | C18: =D18/D19 -> 0.40550224 | D18: =I29 -> 23.56
B19: Итого с/с | D19: =SUM(D16:D18) -> 58.100789 | G19: на месте | H19: с собой | I19: доставка
F20: списания | G20: 2 | H20: 2 | I20: 2
B21: цена | C21: 300 | F21: салфетки 4 шт. | G21: 1.2 | H21: 1.2 | I21: 1.2
B22: cost общий | C22: =I31/C21 -> 0.1936693 | F22: зубочистка | G22: 0.34 | H22: 0.34 | I22: 0.34
B23: cost - продукции | C23: =D16/C21 -> 0.11513596 | F23: пакет | G23: 0 | H23: 2 | I23: 2
F24: наклейка брендированная | G24: 2.5 | H24: 2.5 | I24: 2.5
B25: цена | C25: =C21 -> 300 | F25: Супница | G25: 12.85 | H25: 12.85 | I25: 12.85
B26: доставка | C26: 430 | F26: Ложка с упаковкой | G26: 2.67 | H26: 2.67 | I26: 2.67
G29: =SUM(G20:G28) -> 21.56 | H29: =SUM(H20:H28) -> 23.56 | I29: =SUM(I20:I28) -> 23.56
I31: =D16+I29 -> 58.100789

Sheet Кофе по-турецки
A1: Наименование ТТК: | B1: Кофе по-турецки
A3: Ингредиент | B3: Брутто | C3: Нетто | D3: Ед.изм. | E3: вес потери | F3: % потери | G3: с/с руб. | H3: с/с % | I3: Выход (мл.)
A4: Турецкий кофе KURUKAHVECI MEHMET EFENDI | B4: 10 | C4: 10 | D4: г. | E4: =B4-C4 -> 0 | F4: =E4/B4*100 -> 0 | G4: =VLOOKUP(A4,'Матрица поставщиков'!A1:E60,5,False) * B4 -> 13.04 | H4: =G4/G8 -> 0.50562233
A5: вода | B5: 100 | C5: 100 | D5: мл. | E5: =B5-C5 -> 0 | F5: =E5/B5*100 -> 0 | G5: =VLOOKUP(A5,'Матрица поставщиков'!A1:E53,5,False) * B5 -> 0 | H5: =G5/G8 -> 0
A6: Шоколадные камушки | B6: 5 | C6: 5 | D6: г. | E6: =B6-C6 -> 0 | F6: =E6/B6*100 -> 0 | G6: =VLOOKUP(A6,'Матрица поставщиков'!A2:E549,5,False) * B6 -> 7.5 | H6: =G6/G8 -> 0.29081039
A7: Лукум в шоколадке с мандарином | B7: 7 | C7: 7 | D7: г. | E7: =B7-C7 -> 0 | F7: =E7/B7*100 -> 0 | G7: =VLOOKUP(A7,'Матрица поставщиков'!A3:E559,5,False) * B7 -> 5.25 | H7: =G7/G8 -> 0.20356727
A8: Итого | B8: =B5 -> 100 | C8: =B8 -> 100 | D8: - | E8: =B8-C8 -> 0 | F8: =E8/B8*100 -> 0 | G8: =SUM(G4:G7) -> 25.79 | H8: =SUM(H4:H5) -> 0.50562233 | I8: =B8-E8 -> 100
A10: Технология приготовления
A11: Размешать кофе с холодной водой в турке, погрузить в песок, аккуратно покачивая. Как только начинает закипать, вытаскиваем, погружаем. повторяем 2 раза
B12: выход | C12: с/с
B13: 100 | C13: =G8/I8*B13 -> 25.79
B14: 1 | C14: =G8/I8*B14 -> 0.2579
B16: Для расчёта цены продажи
C17: % | D17: руб | E17: цена так
B18: с/с блюда | C18: =D18/D21 -> 0.894815 | D18: =C13 -> 25.79 | F18: cost (%) | G18: 5 | H18: 7 | I18: 9
B19: списания | C19: 0.04 | D19: =D18*C19 -> 1.0316 | F19: price | G19: =D21*100/G18 -> 576.432 | H19: =D21*100/H18 -> 411.73714 | I19: =D21*100/I18 -> 320.24
B20: упаковка | C20: =D20/D21 -> 0.0693924 | D20: 2
B21: Итого с/с | D21: =SUM(D18:D20) -> 28.8216
B23: цена | C23: 250 | E23: сахер у нас бесплатный
B24: cost общий | C24: =D21/C23 -> 0.1152864
B25: cost - продукции | C25: =D18/C23 -> 0.10316

Sheet Салеп
A1: Наименование ТТК: | B1: Салеп
A3: Ингредиент | B3: Брутто | C3: Нетто | D3: Ед.изм. | E3: вес потери | F3: % потери | G3: с/с руб. | H3: с/с % | I3: Выход (мл.)
A4: Салеп | B4: 20 | C4: =B4 -> 20 | D4: г. | E4: =B4-C4 -> 0 | F4: =E4/B4*100 -> 0 | G4: =VLOOKUP(A4,'Матрица поставщиков'!A1:E600,5,False) * B4 -> 34.7 | H4: =G4/G7 -> 0.74091472
A5: Молоко | B5: 200 | C5: 200 | D5: г. | E5: =B5-C5 -> 0 | F5: =E5/B5*100 -> 0 | G5: =(VLOOKUP(A5,'Матрица поставщиков'!A1:E53,5,FALSE) * B5) -> 12 | H5: =G5/G7 -> 0.25622411
A6: Корица | B6: 1 | C6: 1 | D6: г. | E6: =B6-C6 -> 0 | F6: =E6/B6*100 -> 0 | G6: =(VLOOKUP(A6,'Матрица поставщиков'!A2:E540,5,False) * B6)/10 -> 0.134 | H6: =G6/G7 -> 0.0028611692
A7: Итого | B7: =B5 -> 200 | C7: =B7 -> 200 | D7: - | E7: =B7-C7 -> 0 | F7: =E7/B7*100 -> 0 | G7: =SUM(G4:G6) -> 46.834 | H7: =SUM(H4:H6) -> 1 | I7: =B7-E7 -> 200
A9: Технология приготовления
A10: Смешать в стакане ложкой или размешивателем салеп с молоком до однородной массы. посыпать корицу
A11: выход | B11: с/с
A12: 200 | B12: =G7/I7*A12 -> 46.834
A13: 1 | B13: =G7/I7*A13 -> 0.23417
B15: % | C15: руб
A16: с/с блюда | B16: =C16/C19 -> 0.85608225 | C16: =B12 -> 46.834 | E16: cost (%) | F16: 5 | G16: 7 | H16: 9
A17: списания | B17: 0.04 | C17: =C16*B17 -> 1.87336 | E17: price | F17: =C19*100/F16 -> 1094.1472 | G17: =C19*100/G16 -> 781.53371 | H17: =C19*100/H16 -> 607.85956
A18: упаковка | B18: =C18/C19 -> 0.10967446 | C18: 6
A19: Итого с/с | C19: =SUM(C16:C18) -> 54.70736
A21: цена | B21: 250
A22: cost общий | B22: =C19/B21 -> 0.21882944
A23: cost - продукции | B23: =C16/B21 -> 0.187336

Sheet Чечевичный суп
A1: Наименование блюда: | B1: Чечевичный суп
A3: Ингредиент | B3: Брутто | C3: Нетто | D3: Ед.изм. | E3: Объём потери | F3: % потери | G3: с/с руб. | H3: с/с % | I3: Выход (мл.)
A4: п/ф Чечевичный суп | B4: 300 | C4: =B4 -> 300 | D4: г | E4: =B4-C4 -> 0 | F4: =E4/B4*100 -> 0 | G4: ='пф Чечевичный суп'!D21*B4 -> 17.385798 | H4: =G4/$G$6 -> 0.92202767
A5: п/ф Лимонная заправка | B5: 5 | C5: 5 | D5: г | E5: =B5-C5 -> 0 | F5: =E5/B5*100 -> 0 | G5: ='пф Лимонная заправка'!D11*B5 -> 1.47025 | H5: =G5/$G$6 -> 0.077972331
A6: Итого | B6: =SUM(B4:B5) -> 305 | C6: =SUM(C4:C5) -> 305 | D6: - | E6: =B6-C6 -> 0 | F6: - | G6: =SUM(G4:G5) -> 18.856048 | H6: =SUM(H4:H5) -> 1 | I6: =C6 -> 305
A8: Технология приготовления
A9: Налейте 300мл (3 половника) супа в супницу. Добавьте 5мл лимонно-папричной заправки обязательно предварительно взболтав! при заказе навынос закройте крышкой. Обязательно подайте ложку в пакете.
A11: Для расчёта цены продажи
A12: Состав позиции | B12: доля статьи % | C12: руб
A13: с/с блюда | B13: =C13/C20 -> 0.50212433 | C13: =F22 -> 18.546932 | E13: cost (%) | F13: 25 | G13: 26 | H13: 27 | I13: 27.75 | J13: 29 | K13: 30 | L13: 31
A14: списания | B14: =C14/C20 -> 0.054146348 | C14: 2 | E14: price | F14: =C20*100/F13 -> 147.74773 | G14: =C20*100/G13 -> 142.06512 | H14: =C20*100/H13 -> 136.80345 | I14: =C20*100/I13 -> 133.10606 | J14: =C20*100/J13 -> 127.36873 | K14: =C20*100/K13 -> 123.12311 | L14: =C20*100/L13 -> 119.15139
A15: салфетки 4 шт. | C15: 1.2
A16: зубочистка | B16: =C16/C20 -> 0.0092048792 | C16: 0.34
A17: пакет | B17: =C17/C20 -> 0.054146348 | C17: 2 | E17: 1гр | F17: =G6/I6 -> 0.061823107 | J17: на месте | K17: с собой | L17: доставка
A18: упаковка | B18: =C18/C20 -> 0.34789029 | C18: 12.85 | E18: 100гр | F18: =F17*100 -> 6.1823107 | I18: списания | J18: 2 | K18: 2 | L18: 2
A19: Ложка с упаковкой | B19: =C19/C20 -> 0.072285375 | C19: 2.67 | I19: салфетки 4 шт. | J19: 1.2 | K19: 1.2 | L19: 1.2
A20: Итого с/с | C20: =SUM(C13:C18) -> 36.936932 | E20: 200гр | F20: =F17*200 -> 12.364621 | I20: зубочистка | J20: 0.34 | K20: 0.34 | L20: 0.34
E21: 250гр | F21: =F17*250 -> 15.455777 | I21: пакет | J21: 0 | K21: 2 | L21: 2
A22: cost общий | B22: =L29/B24 -> 0.14035644 | E22: 300гр | F22: =F17*300 -> 18.546932 | I22: наклейка брендированная | J22: 2.5 | K22: 2.5 | L22: 2.5
A23: cost - продукции | B23: =C13/B24 -> 0.061823107 | I23: Супница | J23: 12.85 | K23: 12.85 | L23: 12.85
A24: Цена | B24: 300 | C24: =B24+L27 -> 323.56 | I24: Ложка с упаковкой | J24: 2.67 | K24: 2.67 | L24: 2.67
A26: цена | B26: =B24 -> 300
A27: для доставки | B27: 430 | J27: =SUM(J18:J26) -> 21.56 | K27: =SUM(K18:K26) -> 23.56 | L27: =SUM(L18:L26) -> 23.56
I29: с/с продукции + с/с упаковки | L29: =C13+L27 -> 42.106932

Sheet КОМБО ЛАЙТ - 1
A1: Наименование позиции: | B1: Комбо ЛАЙТ
A3: Ингредиент | B3: Брутто | C3: Нетто | D3: Ед.изм. | E3: с/с руб. | F3: с/с % | G3: Выход (мл.)
A4: ='Дюрюм mini'!B1 -> Дюрюм mini | B4: ='Дюрюм mini'!B11 -> 295 | C4: ='Дюрюм mini'!C11 -> 220 | D4: г | E4: ='Дюрюм mini'!G11 -> 62.066495 | F4: =E4/$E$9 -> 0.56562347
A5: ='Чечевичный суп'!B1 -> Чечевичный суп | B5: 200 | C5: 200 | D5: г | E5: ='Чечевичный суп'!F17*C5 -> 12.364621 | F5: =E5/$E$9 -> 0.11268109
A6: Упаковка для дюрюма | B6: - | C6: - | D6: - | E6: =SUM('Дюрюм mini'!C19:C25)-E8 -> 14.24 | F6: =E6/$E$9 -> 0.12977176
A7: Упаковка для супа | B7: - | C7: - | D7: - | E7: =SUM('Чечевичный суп'!C14:C19)-E8 -> 19.06 | F7: =E7/$E$9 -> 0.17369731
A8: пакет | B8: - | C8: - | D8: - | E8: =2 -> 2 | F8: =E8/$E$9 -> 0.018226371
A9: Итого | B9: =SUM(B4:B5) -> 495 | C9: =SUM(C4:C5) -> 420 | D9: - | E9: =SUM(E4:E8) -> 109.73112 | F9: =SUM(F4:F5) -> 0.67830456 | G9: =C9 -> 420
A14: Наименование | B14: cost % | C14: руб.
A15: TOTAL COST | B15: =B16+B17 -> 0.22394105
A16: PACKAGE COST | B16: =SUM(E6:E8)/C18 -> 0.072040816
A17: FOOD COST | B17: =SUM(E4:E5)/C18 -> 0.15190024
A18: Цена | C18: 490
A19: Цена в доставку (recommend) | C19: =C18/0.7 -> 700

Sheet КОМБО ОБЕД - 1
A1: Наименование позиции: | B1: Комбо ОБЕД
A3: Ингредиент | B3: Брутто | C3: Нетто | D3: Ед.изм. | E3: с/с руб. | F3: с/с % | G3: Выход (мл.)
A4: ='Дюрюм mini'!B1 -> Дюрюм mini | B4: ='Дюрюм mini'!B11 -> 295 | C4: ='Дюрюм mini'!C11 -> 220 | D4: г | E4: ='Дюрюм mini'!G11 -> 62.066495 | F4: =E4/$E$14 -> 0.27142018
A5: ='Чечевичный суп'!B1 -> Чечевичный суп | B5: 200 | C5: 200 | D5: г | E5: ='Чечевичный суп'!F17*C5 -> 12.364621 | F5: =E5/$E$14 -> 0.054071167
A6: Кола | B6: 330 | C6: 330 | D6: мл | E6: 55 | F6: =E6/$E$14 -> 0.24051801
A7: Фри | B7: 100 | C7: 100 | D7: г | E7: ='Фри на продажу'!C14*C7 -> 33.452985 | F7: =E7/$E$14 -> 0.14629174
A8: Соус | B8: ='Сырный соус'!B10 -> 30 | C8: 30 | D8: г | E8: ='Сырный соус'!C10 -> 15.469 | F8: =E8/$E$14 -> 0.067646784
A9: Упаковка для дюрюма | B9: - | C9: - | D9: - | E9: =SUM('Дюрюм mini'!C19:C25)-E13 -> 14.24 | F9: =E9/$E$14 -> 0.0622723
A10: Упаковка для супа | B10: - | C10: - | D10: - | E10: =SUM('Чечевичный суп'!C14:C19)-E13 -> 19.06 | F10: =E10/$E$14 -> 0.083350424
A11: Упаковка для соуса | B11: - | C11: - | D11: - | E11: ='Сырный соус'!J31 -> 4.76 | F11: =E11/$E$14 -> 0.020815741
A12: Упаковка для фри | B12: - | C12: - | D12: - | E12: ='Фри на продажу'!J34 -> 10.26 | F12: =E12/$E$14 -> 0.044867542
A13: пакет | B13: - | C13: - | D13: - | E13: =2 -> 2 | F13: =E13/$E$14 -> 0.0087461096
A14: Итого | B14: =SUM(B4:B13) -> 955 | C14: =SUM(C4:C13) -> 880 | D14: - | E14: =SUM(E4:E13) -> 228.6731 | F14: =SUM(F4:F5) -> 0.32549135 | G14: =C14 -> 880
A19: Наименование | B19: cost % | C19: руб.
A20: TOTAL COST | B20: =B21+B22 -> 0.30489747
A21: PACKAGE COST | B21: =SUM(E9:E13)/C23 -> 0.067093333
A22: FOOD COST | B22: =SUM(E4:E8)/C23 -> 0.23780414
A23: Цена | C23: 750
A24: Цена в доставку (recommend) | C24: =C23/0.7 -> 1071.4286

Sheet КОМБО ЛАЙТ - 2
A1: Наименование позиции: | B1: Комбо ЛАЙТ
A3: Ингредиент | B3: Брутто | C3: Нетто | D3: Ед.изм. | E3: с/с руб. | F3: с/с % | G3: Выход (мл.)
A4: ='Дюрюм'!B1 -> Дюрюм | B4: ='Дюрюм'!B11 -> 435 | C4: ='Дюрюм'!C11 -> 342 | D4: г | E4: ='Дюрюм'!G11 -> 100.31737 | F4: =E4/$E$9 -> 0.67790255
A5: ='Чечевичный суп'!B1 -> Чечевичный суп | B5: 200 | C5: 200 | D5: г | E5: ='Чечевичный суп'!F17*C5 -> 12.364621 | F5: =E5/$E$9 -> 0.083554908
A6: Упаковка для дюрюма | B6: - | C6: - | D6: - | E6: =SUM('Дюрюм'!C19:C25)-E8 -> 14.24 | F6: =E6/$E$9 -> 0.096227927
A7: Упаковка для супа | B7: - | C7: - | D7: - | E7: =SUM('Чечевичный суп'!C14:C19)-E8 -> 19.06 | F7: =E7/$E$9 -> 0.12879946
A8: пакет | B8: - | C8: - | D8: - | E8: =2 -> 2 | F8: =E8/$E$9 -> 0.013515158
A9: Итого | B9: =SUM(B4:B5) -> 635 | C9: =SUM(C4:C5) -> 542 | D9: - | E9: =SUM(E4:E8) -> 147.98199 | F9: =SUM(F4:F5) -> 0.76145746 | G9: =C9 -> 542
A14: Наименование | B14: cost % | C14: руб.
A15: TOTAL COST | B15: =B16+B17 -> 0.25081693
A16: PACAGE COST | B16: =SUM(E6:E8)/C18 -> 0.059830508
A17: FOOD COST | B17: =SUM(E4:E5)/C18 -> 0.19098642
A18: Цена | C18: 590
A19: Цена в доставку (recommend) | C19: =C18/0.7 -> 842.85714

Sheet КОМБО ОБЕД - 2
A1: Наименование позиции: | B1: Комбо ОБЕД
A3: Ингредиент | B3: Брутто | C3: Нетто | D3: Ед.изм. | E3: с/с руб. | F3: с/с % | G3: Выход (мл.)
A4: ='Дюрюм'!B1 -> Дюрюм | B4: ='Дюрюм'!B11 -> 435 | C4: ='Дюрюм'!C11 -> 342 | D4: г | E4: ='Дюрюм'!G11 -> 100.31737 | F4: =E4/E14 -> 0.37582749
A5: ='Чечевичный суп'!B1 -> Чечевичный суп | B5: 200 | C5: 200 | D5: г | E5: ='Чечевичный суп'!F17*C5 -> 12.364621 | F5: =E5/$E$14 -> 0.046322634
A6: Кола | B6: 330 | C6: 330 | D6: мл | E6: 55 | F6: =E6/$E$14 -> 0.20605118
A7: Фри | B7: 100 | C7: 100 | D7: г | E7: ='Фри на продажу'!C14*C7 -> 33.452985 | F7: =E7/$E$14 -> 0.12532777
A8: Соус | B8: ='Сырный соус'!B10 -> 30 | C8: 30 | D8: г | E8: ='Сырный соус'!C10 -> 15.469 | F8: =E8/$E$14 -> 0.057952831
A9: Упаковка для дюрюма | B9: - | C9: - | D9: - | E9: =SUM('Дюрюм mini'!C19:C25)-E13 -> 14.24 | F9: =E9/$E$14 -> 0.053348524
A10: Упаковка для супа | B10: - | C10: - | D10: - | E10: =SUM('Чечевичный суп'!C14:C19)-E13 -> 19.06 | F10: =E10/$E$14 -> 0.0714061
A11: Упаковка для соуса | B11: - | C11: - | D11: - | E11: ='Сырный соус'!J31 -> 4.76 | F11: =E11/$E$14 -> 0.017832793
A12: Упаковка для фри | B12: - | C12: - | D12: - | E12: ='Фри на продажу'!J34 -> 10.26 | F12: =E12/$E$14 -> 0.038437911
A13: пакет | B13: - | C13: - | D13: - | E13: =2 -> 2 | F13: =E13/$E$14 -> 0.0074927702
A14: Итого | B14: =SUM(B4:B5) -> 635 | C14: =SUM(C4:C5) -> 542 | D14: - | E14: =SUM(E4:E13) -> 266.92397 | F14: =SUM(F4:F5) -> 0.42215012 | G14: =C14 -> 542
A19: Наименование | B19: cost % | C19: руб.
A20: TOTAL COST | B20: =B21+B22 -> 0.2809726
A21: PACAGE COST | B21: =SUM(E9:E13)/C23 -> 0.052968421
A22: FOOD COST | B22: =SUM(E4:E8)/C23 -> 0.22800418
A23: Цена | C23: 950
A24: Цена в доставку (recommend) | C24: =C23/0.7 -> 1357.1429

Sheet Искенди кебаб
A1: Наименование блюда: | B1: Кебаб Искенди
A3: Ингредиент | B3: Брутто | C3: Нетто | D3: Ед.изм. | E3: Объём потери | F3: % потери | G3: с/с руб. | H3: с/с % | I3: Выход (мл.)
A4: п/ф Фарш Primebeef Классик жареный | B4: 100 | C4: =B4 -> 100 | D4: г | E4: =B4-C4 -> 0 | F4: =E4/B4*100 -> 0 | G4: ='пф Фарш Primebeef Классик жарен'!D14*B4 -> 145.86927 | H4: =G4/$G$8 -> 0.92332301
A5: п/ф Лаваш Искенди | B5: 0.25 | C5: 0.25 | D5: шт. | E5: =B5-C5 -> 0 | F5: =E5/B5*100 -> 0 | G5: ='пф Лаваш Искенди'!G6*B5 -> 4.70986 | H5: =G5/$G$8 -> 0.029812463
A6: п/ф Соус Кебаб | B6: 40 | C6: 40 | D6: г | E6: =B6-C6 -> 0 | F6: =E6/B6*100 -> 0 | G6: ='пф Соус Кебаб'!D21*B6 -> 3.3493946 | H6: =G6/G8 -> 0.021200992
A7: п/ф Лук маринованный | B7: 30 | C7: 30 | D7: г | E7: =B7-C7 -> 0 | F7: =E7/B7*100 -> 0 | G7: ='пф Лук маринованный'!D18*B7 -> 4.0544 | H7: =G7/G8 -> 0.025663534
A8: Итого | B8: =SUM(B4:B7) -> 170.25 | C8: =SUM(C4:C7) -> 170.25 | D8: - | E8: =B8-C8 -> 0 | F8: - | G8: =SUM(G4:G7) -> 157.98292 | H8: =SUM(H4:H7) -> 1 | I8: =B8-E8 -> 170.25
A10: Технология приготовления
A11: Подача: на половине половины лаваша(П/Ф), соус кебаб 40гр, лук Маринованный пф 30гр
A13: Для расчёта цены продажи
A14: Состав позиции | B14: доля статьи % | C14: руб
A15: с/с блюда | B15: =C15/C21 -> 0.91945196 | C15: =G8 -> 157.98292 | E15: cost (%) | F15: 25 | G15: 26 | H15: 27 | I15: 27.75 | J15: 29 | K15: 30 | L15: 31
A16: списания | B16: =C16/C21 -> 0.011639891 | C16: 2 | E16: price | F16: =C21*100/F15 -> 687.29168 | G16: =C21*100/G15 -> 660.85739 | H16: =C21*100/H15 -> 636.38119 | I16: =C21*100/I15 -> 619.1817 | J16: =C21*100/J15 -> 592.49283 | K16: =C21*100/K15 -> 572.74307 | L16: =C21*100/L15 -> 554.26749
A17: салфетки 4 шт. | B17: =C17/C21 -> 0.023279781 | C17: 4
A18: зубочистка | B18: =C18/C21 -> 0.0019787814 | C18: 0.34
A19: пакет | B19: =C19/C21 -> 0.011639891 | C19: 2
A20: упаковка | B20: =C20/C21 -> 0.032009699 | C20: 5.5
A21: Итого с/с | C21: =SUM(C15:C20) -> 171.82292
F22: на месте | G22: с собой | H22: доставка
A23: cost общий | B23: =H34/B25 -> 0.26397525 | E23: списания | F23: 2 | G23: 2 | H23: 2
A24: cost - продукции | B24: =G8/B25 -> 0.22896075 | E24: салфетки 4 шт. | F24: 1.2 | G24: 1.2 | H24: 1.2
A25: Цена | B25: 690 | C25: =B25+H32 -> 714.16 | E25: зубочистка | F25: 0.34 | G25: 0.34 | H25: 0.34
E26: пакет | F26: 0 | G26: 2 | H26: 2
E27: наклейка брендированная | F27: 0 | G27: 2.5 | H27: 2.5
A28: цена | B28: 575 | E28: Алюм контейнер | F28: 10 | G28: 10 | H28: 10
A29: доставка | B29: 820 | E29: крышка | F29: 0 | G29: 2.32 | H29: 2.32
E30: Соусник | F30: 3.8 | G30: 3.8 | H30: 3.8
F32: =SUM(F23:F31) -> 17.34 | G32: =SUM(G23:G31) -> 24.16 | H32: =SUM(H23:H31) -> 24.16
G34: с/с | H34: =C15+H32 -> 182.14292

Sheet Дюрюм mini
A1: Наименование блюда: | B1: Дюрюм mini
A3: Ингредиент | B3: Брутто | C3: Нетто | D3: Ед.изм. | E3: Объём потери | F3: % потери | G3: с/с руб. | H3: с/с % | I3: Выход (мл.)
A4: п/ф курица жареная | B4: 50 | C4: 50 | D4: г | E4: =B4-C4 -> 0 | F4: =E4/B4*100 -> 0 | G4: ='пф курица готовая'!G6/'пф курица готовая'!I6*B4 -> 25.709425 | H4: =G4/$G$11 -> 0.4142239
A5: п/ф Лаваш Искенди 1/2 | B5: 50 | C5: 50 | D5: г | E5: 0 | F5: =E5/B5*100 -> 0 | G5: ='пф Лаваш Искенди'!G6/2 -> 9.41972 | H5: =G5/$G$11 -> 0.1517682
A6: Помидоры - сливовые | B6: 20 | C6: 20 | D6: г | E6: =B6-C6 -> 0 | F6: =E6/B6*100 -> 0 | G6: =VLOOKUP(A6,'Матрица поставщиков'!A1:E53,5,0) * B6 -> 7 | H6: =G6/G11 -> 0.11278227
A7: п/ф искандер соус | B7: 120 | C7: 45 | D7: мл | E7: =B7-C7 -> 75 | F7: =E7/B7*100 -> 62.5 | G7: =('пф искандер соус'!G11/'пф искандер соус'!I11)*B7 -> 4.33944 | H7: =G7/$G$11 -> 0.069915983
A8: Маринованные огурцы (целые) | B8: 20 | C8: 20 | D8: г | E8: =B8-C8 -> 0 | F8: =E8/B8*100 -> 0 | G8: =VLOOKUP(A8,'Матрица поставщиков'!A1:E507,5,0) * B8 -> 7.2933333 | H8: =G8/$G$11 -> 0.11750838
A9: Йогурт | B9: 20 | C9: =B9 -> 20 | D9: г | E9: =B9-C9 -> 0 | F9: =E9/B9*100 -> 0 | G9: =VLOOKUP(A9,'Матрица поставщиков'!A1:E503,5,0) * B9 -> 3.5266667 | H9: =G9/$G$11 -> 0.05682078
A10: п/ф Фри | B10: 15 | C10: 15 | D10: г | E10: =B10-C10 -> 0 | F10: =E10/B10*100 -> 0 | G10: =('пф Фри'!G7/'пф Фри'!I7) * B10 -> 4.7779095 | H10: =G10/$G$11 -> 0.076980495
A11: Итого | B11: =SUM(B4:B10) -> 295 | C11: =SUM(C4:C10) -> 220 | D11: - | E11: =B11-C11 -> 75 | F11: - | G11: =SUM(G4:G10) -> 62.066495 | H11: =SUM(H4:H10) -> 1 | I11: =B11-E11 -> 220
A13: Технология приготовления
A14: 1. Разогреть гриль до 200 4. Разместить один лаваш поверх другого симметрично 5. Выложить дорожкой по центру маринованные огурцы 6. Выложить дорожкой по центру помидоры нарезанные 7. Выложить дорожкой по центру мясо 8. Разместить по центру белый соус и Искенди 9. Завернуть лаваш 10. полить гриль полоской 20 гр соуса и поджарить 30 секунд до слегка тёмной корочки *в 10-м пункте начинать жарить со стороны открытого лаваша ( нужно запечатать )
A16: Для расчёта цены продажи
A17: Состав позиции | B17: доля статьи % | C17: руб | E17: cost (%) | F17: 25 | G17: 26 | H17: 27 | I17: 27.75 | J17: 29 | K17: 30 | L17: 31
A18: с/с блюда | B18: =C18/C26 -> 0.84551776 | C18: =G11 -> 62.066495 | E18: price | F18: =C26*100/F17 -> 293.62598 | G18: =C26*100/G17 -> 282.33267 | H18: =C26*100/H17 -> 271.87591 | I18: =C26*100/I17 -> 264.52791 | J18: =C26*100/J17 -> 253.12584 | K18: =C26*100/K17 -> 244.68832 | L18: =C26*100/L17 -> 236.79514
A19: списания | B19: =C19/C26 -> 0.027245546 | C19: 2
A20: салфетки 2 шт. | B20: =C20/C26 -> 0.0081736637 | C20: 0.6 | F20: на месте | G20: с собой | H20: доставка
A21: зубочистка | B21: =C21/C26 -> 0.0046317427 | C21: 0.34 | E21: списания | F21: 2 | G21: 2 | H21: 2
A22: пакет | B22: =C22/$C$26 -> 0.027245546 | C22: 2 | E22: салфетки 2 шт. | F22: 0.6 | G22: 0.6 | H22: 0.6
A23: наклейка брендированная | B23: =C23/$C$26 -> 0.021796436 | C23: 1.6 | E23: зубочистка | F23: 0.34 | G23: 0.34 | H23: 0.34
A24: Гриль пакет | B24: =C24/C26 -> 0.092634855 | C24: 6.8 | E24: пакет | F24: 0 | G24: 2 | H24: 2
A25: Фольга | B25: =C25/$C$26 -> 0.039506041 | C25: 2.9 | E25: наклейка брендированная | F25: 1.6 | G25: 1.6 | H25: 1.6
A26: Итого с/с | C26: =C18+F28 -> 73.406495 | E26: Гриль пакет | F26: 6.8 | G26: 6.8 | H26: 6.8
E27: Фольга | F27: 0 | G27: 2.9 | H27: 2.9
E28: Итого | F28: =SUM(F21:F27) -> 11.34 | G28: =SUM(G21:G27) -> 16.24 | H28: =SUM(H21:H27) -> 16.24
A29: Наименование | B29: cost % | C29: руб.
A30: TOTAL COST | B30: =C26/C33 -> 0.20973284
A31: PACKAGE COST | B31: =F28/C33 -> 0.0324
A32: FOOD COST | B32: =C18/C33 -> 0.17733284
A33: Цена | C33: 350
A34: Цена в доставку | C34: =C33/0.7 -> 500

Sheet Дюрюм
A1: Наименование блюда: | B1: Дюрюм
A3: Ингредиент | B3: Брутто | C3: Нетто | D3: Ед.изм. | E3: Объём потери | F3: % потери | G3: с/с руб. | H3: с/с % | I3: Выход (мл.)
A4: п/ф курица жареная | B4: 83 | C4: =B4 -> 83 | D4: г | E4: =B4-C4 -> 0 | F4: =E4/B4*100 -> 0 | G4: ='пф курица готовая'!G6/'пф курица готовая'!I6*B4 -> 42.677646 | H4: =G4/$G$11 -> 0.4254263
A5: п/ф Лаваш Искенди | B5: 100 | C5: 100 | D5: г | E5: 0 | F5: =E5/B5*100 -> 0 | G5: ='пф Лаваш Искенди'!G6 -> 18.83944 | H5: =G5/$G$11 -> 0.18779839
A6: Помидоры - сливовые | B6: 30 | C6: 30 | D6: г | E6: =B6-C6 -> 0 | F6: =E6/B6*100 -> 0 | G6: =VLOOKUP(A6,'Матрица поставщиков'!A1:E53,5,0) * B6 -> 10.5 | H6: =G6/G11 -> 0.10466782
A7: п/ф искандер соус | B7: 140 | C7: 52 | D7: мл | E7: =B7-C7 -> 88 | F7: =E7/B7*100 -> 62.857143 | G7: =('пф искандер соус'!G11/'пф искандер соус'!I11)*B7 -> 5.06268 | H7: =G7/$G$11 -> 0.050466636
A8: Маринованные огурцы (целые) | B8: 30 | C8: 30 | D8: г | E8: =B8-C8 -> 0 | F8: =E8/B8*100 -> 0 | G8: =VLOOKUP(A8,'Матрица поставщиков'!A1:E57,5,0) * B8 -> 10.94 | H8: =G8/$G$11 -> 0.1090539
A9: Йогурт | B9: 30 | C9: 25 | D9: г | E9: =B9-C9 -> 5 | F9: =E9/B9*100 -> 16.666667 | G9: =VLOOKUP(A9,'Матрица поставщиков'!A1:E530,5,0) * B9 -> 5.29 | H9: =G9/$G$11 -> 0.052732644
A10: п/ф Фри | B10: 22 | C10: 22 | D10: г | E10: =B10-C10 -> 0 | F10: =E10/B10*100 -> 0 | G10: =('пф Фри'!G7/'пф Фри'!I7) * B10 -> 7.0076006 | H10: =G10/$G$11 -> 0.069854312
A11: Итого | B11: =SUM(B4:B10) -> 435 | C11: =SUM(C4:C10) -> 342 | D11: - | E11: =B11-C11 -> 93 | F11: - | G11: =SUM(G4:G10) -> 100.31737 | H11: =SUM(H4:H10) -> 1 | I11: =B11-E11 -> 342
A13: Технология приготовления
A14: 1. Разогреть гриль до 200 4. Разместить один лаваш поверх другого симметрично 5. Выложить дорожкой по центру маринованные огурцы 6. Выложить дорожкой по центру помидоры нарезанные 7. Выложить дорожкой по центру мясо 8. Разместить по центру белый соус и Искенди 9. Завернуть лаваш 10. полить гриль полоской 20 гр соуса и поджарить 30 секунд до слегка тёмной корочки *в 10-м пункте начинать жарить со стороны открытого лаваша ( нужно запечатать )
A16: Для расчёта цены продажи
A17: Состав позиции | B17: доля статьи % | C17: руб
A18: с/с блюда | B18: =C18/C26 -> 0.86066947 | C18: =G11 -> 100.31737 | E18: cost (%) | F18: 25 | G18: 26 | H18: 27 | I18: 27.75 | J18: 29 | K18: 30 | L18: 31
A19: списания | B19: =C19/C26 -> 0.017158933 | C19: 2 | E19: price | F19: =C26*100/F18 -> 466.22947 | G19: =C26*100/G18 -> 448.29756 | H19: =C26*100/H18 -> 431.69395 | I19: =C26*100/I18 -> 420.02655 | J19: =C26*100/J18 -> 401.92195 | K19: =C26*100/K18 -> 388.52456 | L19: =C26*100/L18 -> 375.99151
A20: салфетки 2 шт. | B20: =C20/C26 -> 0.0051476798 | C20: 0.6
A21: зубочистка | B21: =C21/C26 -> 0.0029170185 | C21: 0.34
A22: пакет | B22: =C22/$C$26 -> 0.017158933 | C22: 2 | F22: на месте | G22: с собой | H22: доставка
A23: наклейка брендированная | B23: =C23/$C$26 -> 0.013727146 | C23: 1.6 | E23: списания | F23: 2 | G23: 2 | H23: 2
A24: Гриль пакет | B24: =C24/C26 -> 0.058340371 | C24: 6.8 | E24: салфетки 2 шт. | F24: 0.6 | G24: 0.6 | H24: 0.6
A25: Фольга | B25: =C25/$C$26 -> 0.024880452 | C25: 2.9 | E25: зубочистка | F25: 0.34 | G25: 0.34 | H25: 0.34
A26: Итого с/с | C26: =C18+G30 -> 116.55737 | E26: пакет | F26: 0 | G26: 2 | H26: 2
E27: наклейка брендированная | F27: 1.6 | G27: 1.6 | H27: 1.6
E28: Гриль пакет | F28: 6.8 | G28: 6.8 | H28: 6.8
A29: Наименование | B29: cost % | C29: руб. | E29: Фольга | F29: 0 | G29: 2.9 | H29: 2.9
A30: TOTAL COST | B30: =C26/C33 -> 0.25901637 | E30: Итого | F30: =SUM(F23:F29) -> 11.34 | G30: =SUM(G23:G29) -> 16.24 | H30: =SUM(H23:H29) -> 16.24
A31: PACKAGE COST | B31: =F30/C33 -> 0.0252
A32: FOOD COST | B32: =C18/C33 -> 0.22292748
A33: Цена | C33: 450
A34: Цена в доставку (recommend) | C34: =C33/0.7 -> 642.85714

Sheet Комбо-1_1
A1: Наименование ТТК: | B1: Комбо: Дюрюм + фри + соус + напиток | K1: cost (%) | L1: 25 | M1: 26 | N1: 27 | O1: 27.75 | P1: 29 | Q1: 30 | R1: 31
K2: price | L2: =D8*100/L1 -> #REF! | M2: =D8*100/M1 -> #REF! | N2: =D8*100/N1 -> #REF! | O2: =D8*100/O1 -> #REF! | P2: =D8*100/P1 -> #REF! | Q2: =D8*100/Q1 -> #REF! | R2: =D8*100/R1 -> #REF!
A3: Ингредиент | B3: Выход | C3: Ед.изм. | D3: с/с руб. | E3: с/с % | F3: цена по отдельности | G3: цена комбо | H3: выгода гостя % | I3: cost
A4: Iskanderun Durum Tavuk | B4: 350 | C4: г | D4: ='Дюрюм'!C18 -> #REF! | E4: =D4/$D$8 -> #REF! | F4: ='Дюрюм'!B33 -> #REF!
A5: Фри на продажу | B5: 100 | C5: г | D5: ='Фри на продажу'!D18 -> 33.452985 | E5: =D5/$D$8 -> #REF! | F5: 230
A6: Соус сырный/кетчуп | B6: 30 | C6: г | D6: ='Сырный соус'!D15 | E6: =D6/$D$8 -> #REF! | F6: 70
A7: Напиток на выбор | D7: =VLOOKUP(F13,'Матрица поставщиков'!A1:E530,5,0) -> 52 | E7: =D7/$D$8 -> #REF! | F7: 190
A8: Итого | B8: =SUM(B4:B7) -> 480 | C8: - | D8: =SUM(D4:D7) -> #REF! | E8: =SUM(E4:E7) -> #REF! | F8: =SUM(F4:F7) -> #REF! | G8: 850 | H8: =F8/G8-100% -> #REF! | I8: =D8/G8 -> #REF! | J8: =D8/G8 -> #REF! | K8: =J25/G8 -> 0.046564706 | L8: =(D8+J25)/G8 -> #REF!
F10: доставка | G10: 1360
F13: Кола Добрый | H13: на месте | I13: с собой | J13: доставка
G14: списания | H14: 2 | I14: 2 | J14: 2
G15: салфетки 4 шт. | H15: 1.2 | I15: 1.2 | J15: 1.2
G16: зубочистка | H16: 0.34 | I16: 0.34 | J16: 0.34
G17: пакет | H17: 0 | I17: 2 | J17: 2
G18: наклейка брендированная | H18: 7.5 | I18: 7.5 | J18: 7.5
G19: Гриль пакет | H19: 6.8 | I19: 6.1 | J19: 6.1
G20: Фольга | H20: 0 | I20: 2.9 | J20: 2.9
G21: Соусник | H21: 4.52 | I21: 4.52 | J21: 4.52
G22: Стакан | H22: 2.7 | I22: 2.7 | J22: 2.7
G23: Крышка | H23: 0 | I23: 1.52 | J23: 1.52
G24: Перец якан турецкий | H24: 8.8 | I24: 8.8 | J24: 8.8
H25: =SUM(H14:H24) -> 33.86 | I25: =SUM(I14:I24) -> 39.58 | J25: =SUM(J14:J24) -> 39.58
J27: =D8+J25 -> #REF!

Sheet Дюрюм Нарсоган
A1: Наименование блюда: | B1: Дюрюм
A3: Ингредиент | B3: Брутто | C3: Нетто | D3: Ед.изм. | E3: Объём потери | F3: % потери | G3: с/с руб. | H3: с/с % | I3: Выход (мл.)
A4: п/ф курица жареная | B4: 83 | C4: =B4 -> 83 | D4: г | E4: =B4-C4 -> 0 | F4: =E4/B4*100 -> 0 | G4: ='пф курица готовая'!G6/'пф курица готовая'!I6*B4 -> 42.677646 | H4: =G4/$G$12 -> 0.37464262
A5: п/ф Лаваш Искенди | B5: 100 | C5: 100 | D5: г | E5: 0 | F5: =E5/B5*100 -> 0 | G5: ='пф Лаваш Искенди'!G6 -> 18.83944 | H5: =G5/$G$12 -> 0.16538066
A6: Помидоры - сливовые | B6: 30 | C6: 30 | D6: г | E6: =B6-C6 -> 0 | F6: =E6/B6*100 -> 0 | G6: =VLOOKUP(A6,'Матрица поставщиков'!A1:E53,5,0) * B6 -> 10.5 | H6: =G6/G12 -> 0.092173489
A7: п/ф искандер соус | B7: 140 | C7: 52 | D7: мл | E7: =B7-C7 -> 88 | F7: =E7/B7*100 -> 62.857143 | G7: =('пф искандер соус'!G11/'пф искандер соус'!I11)*B7 -> 5.06268 | H7: =G7/$G$12 -> 0.044442369
A8: Маринованные огурцы (целые) | B8: 30 | C8: 30 | D8: г | E8: =B8-C8 -> 0 | F8: =E8/B8*100 -> 0 | G8: =VLOOKUP(A8,'Матрица поставщиков'!A1:E57,5,0) * B8 -> 10.94 | H8: =G8/$G$12 -> 0.096035997
A9: Лук сушеный жареный | B9: 30 | C9: =B9 -> 30 | D9: г | E9: =B9-C9 -> 0 | F9: =E9/B9*100 -> 0 | G9: =VLOOKUP(A9,'Матрица поставщиков'!A1:E553,5,0) * B9 -> 10.14 | H9: =G9/$G$12 -> 0.089013255
A10: п/ф соус Нар | B10: 30 | C10: =B10 -> 30 | D10: г | E10: =B10-C10 -> 0 | F10: =E10/B10*100 -> 0 | G10: =('пф соус Нар'!L5)*B10 -> 8.7482517 | H10: =G10/$G$12 -> 0.076795894
A11: п/ф Фри | B11: 22 | C11: 22 | D11: г | E11: =B11-C11 -> 0 | F11: =E11/B11*100 -> 0 | G11: =('пф Фри'!G7/'пф Фри'!I7) * B11 -> 7.0076006 | H11: =G11/$G$12 -> 0.061515714
A12: Итого | B12: =SUM(B4:B11) -> 465 | C12: =SUM(C4:C11) -> 377 | D12: - | E12: =B12-C12 -> 88 | F12: - | G12: =SUM(G4:G11) -> 113.91562 | H12: =SUM(H4:H11) -> 1 | I12: =B12-E12 -> 377
A14: Технология приготовления
A15: 1. Разогреть гриль до 200 4. Разместить один лаваш поверх другого симметрично 5. Выложить дорожкой по центру маринованные огурцы 6. Выложить дорожкой по центру помидоры нарезанные 7. Выложить дорожкой по центру мясо 8. Разместить по центру соус нар, жареный лук и соус Искенди 9. Завернуть лаваш 10. полить гриль полоской 20 гр соуса и поджарить 30 секунд до слегка тёмной корочки *в 10-м пункте начинать жарить со стороны открытого лаваша ( нужно запечатать )
A17: Для расчёта цены продажи
A18: Состав позиции | B18: доля статьи % | C18: руб
A19: с/с блюда | B19: =C19/C29 -> 0.87724828 | C19: =G12 -> 113.91562 | E19: cost (%) | F19: 25 | G19: 26 | H19: 27 | I19: 27.75 | J19: 29 | K19: 30 | L19: 31
A20: списания | B20: =C20/C29 -> 0.015401721 | C20: 2 | E20: price | F20: =C29*100/F19 -> 519.42247 | G20: =C29*100/G19 -> 499.44469 | H20: =C29*100/H19 -> 480.94674 | I20: =C29*100/I19 -> 467.94817 | J20: =C29*100/J19 -> 447.77799 | K20: =C29*100/K19 -> 432.85206 | L20: =C29*100/L19 -> 418.88909
A21: салфетки 4 шт. | B21: =C21/C29 -> 0.0092410326 | C21: 1.2
A22: зубочистка | B22: =C22/C29 -> 0.0026182926 | C22: 0.34
A23: пакет | B23: =C23/$C$29 -> 0.015401721 | C23: 2 | F23: на месте | G23: с собой | H23: доставка
A24: наклейка брендированная | B24: =C24/$C$29 -> 0.019252151 | C24: 2.5 | E24: списания | F24: 2 | G24: 2 | H24: 2
A25: Гриль пакет | B25: =C25/C29 -> 0.052365851 | C25: 6.8 | E25: салфетки 4 шт. | F25: 1.2 | G25: 1.2 | H25: 0
A26: Фольга | B26: =C26/$C$29 -> 0.022332495 | C26: 2.9 | E26: зубочистка | F26: 0.34 | G26: 0.34 | H26: 0.34
A27: Соусник | B27: =C27/C29 -> 0.017403945 | C27: 2.26 | E27: пакет | F27: 0 | G27: 2 | H27: 2
A28: Перец якан турецкий | E28: наклейка брендированная | F28: 2.5 | G28: 2.5 | H28: 2.6
A29: Итого с/с | C29: =C19+H33 -> 129.85562 | E29: Гриль пакет | F29: 6.8 | G29: 6.1 | H29: 6.1
E30: Фольга | F30: 0 | G30: 2.9 | H30: 2.9
A31: cost общий | B31: =H35/B34 -> 0.26501147 | E31: Соусник | F31: 2.26 | G31: 2.26 | H31: 0
A32: cost упаковки | B32: =H33/B34 -> 0.032530612 | E32: Перец якан турецкий | F32: 8.8 | G32: 8.8 | H32: 0
A33: cost - продукции | B33: =C19/B34 -> 0.23248085 | F33: =SUM(F24:F32) -> 23.9 | G33: =SUM(G24:G32) -> 28.1 | H33: =SUM(H24:H32) -> 15.94
A34: Цена | B34: 490 | C34: =B34+H33 -> 505.94
H35: =C19+H33 -> 129.85562
A36: доставка | B36: =B34/70*100 -> 700
A38: =B34-(H33+C19) -> 360.14438 | B38: =A38/B34 -> 0.73498853

Sheet Балык Дюрюм
A1: Наименование блюда: | B1: Балык Дюрюм
A3: Ингредиент | B3: Брутто | C3: Нетто | D3: Ед.изм. | E3: Объём потери | F3: % потери | G3: с/с руб. | H3: с/с % | I3: Выход (мл.)
A4: п/ф Скумбрия | B4: 126 | C4: 70 | D4: г | E4: =B4-C4 -> 56 | F4: =E4/B4*100 -> 44.444444 | G4: =('пф скумбрия'!L5)*B4 -> 127.39516 | H4: =G4/$G$15 -> 0.679477
A5: Лаваш | B5: 0.5 | C5: 50 | D5: г | E5: 0 | F5: =E5/B5*100 -> 0 | G5: =VLOOKUP(A5,'Матрица поставщиков'!A2:E540,5,0) * B5 -> 7.25 | H5: =G5/$G$15 -> 0.038668723
A6: Помидоры - сливовые | B6: 30 | C6: 30 | D6: г | E6: =B6-C6 -> 0 | F6: =E6/B6*100 -> 0 | G6: =VLOOKUP(A6,'Матрица поставщиков'!A1:E53,5,0) * B6 -> 10.5 | H6: =G6/G15 -> 0.056002978
A7: п/ф айсберг | B7: 30 | C7: 30 | D7: г | E7: =B7-C7 -> 0 | F7: =E7/B7*100 -> 0 | G7: ='пф айсберг'!C12*B7 -> 8.9081818 | H7: =G7/$G$15 -> 0.047512829
A8: Лимон | B8: 30 | C8: 25 | D8: г | E8: =B8-C8 -> 5 | F8: =E8/B8*100 -> 16.666667 | G8: =VLOOKUP(A8,'Матрица поставщиков'!A1:E553,5,0) * B8 -> 7.77 | H8: =G8/$G$15 -> 0.041442203
A9: п/ф соус Нар | B9: 20 | C9: =B9 -> 20 | D9: г | E9: =B9-C9 -> 0 | F9: =E9/B9*100 -> 0 | G9: =('пф соус Нар'!L5)*B9 -> 5.8321678 | H9: =G9/$G$15 -> 0.031106549
A10: п/ф специи балык | B10: 5 | C10: 5 | D10: г | E10: =B10-C10 -> 0 | F10: =E10/B10*100 -> 0 | G10: =('пф специи балык'!D16) * B10 -> 5.6165116 | H10: =G10/$G$15 -> 0.029956321
A11: Масло фритюрное | B11: 15 | C11: =B11 -> 15 | D11: г | E11: =B11-C11 -> 0 | F11: =E11/B11*100 -> 0 | G11: =VLOOKUP(A11,'Матрица поставщиков'!A4:E556,5,0) * B11 -> 2.76 | H11: =G11/$G$15 -> 0.014720783
A12: п/ф перец сладкий | B12: 25 | C12: 20 | D12: г | E12: =B12-C12 -> 5 | F12: =E12/B12*100 -> 20 | G12: ='пф перец сладкий'!C12*B12 -> 5.8238636 | H12: =G12/$G$15 -> 0.031062258
A13: п/ф обмазка балыка | B13: 15 | C13: 5 | D13: г | E13: =B13-C13 -> 10 | F13: =E13/B13*100 -> 66.666667 | G13: ='пф обмазка балыка'!C15*B13 -> 2.8976757 | H13: =G13/$G$15 -> 0.015455092
A14: п/ф Лук - сумах | B14: 20 | C14: 20 | D14: г | E14: =B14-C14 -> 0 | F14: =E14/B14*100 -> 0 | G14: ='пф Лук - сумах'!D17*B14 -> 2.7364667 | H14: =G14/$G$15 -> 0.014595265
A15: Итого | B15: =SUM(B4:B14) -> 316.5 | C15: =SUM(C4:C14) -> 290 | D15: - | E15: =B15-C15 -> 26.5 | F15: - | G15: =SUM(G4:G14) -> 187.49003 | H15: =SUM(H4:H14) -> 1 | I15: =B15-E15 -> 290
A17: Технология приготовления
A18: Пожарить скумбрию по 3 мин с каждой стороны на жарочном масле на 200 градусов. Выложить на лаваш Положить айсберг с морковью на рыбу. Положить черпак помидоров вдоль рыбы Посыпать специями Полить соусом нар Завернуть Обжарить с двух сторон по 30 сек на 200 градусов на жарочном масле Посыпать обжаренный специями с двух сторон Добавить дольку лимона сверху
A20: Для расчёта цены продажи
A21: Состав позиции | B21: доля статьи % | C21: руб
A22: с/с блюда | B22: =C22/C32 -> 0.92164382 | C22: =G15 -> 187.49003 | E22: cost (%) | F22: 25 | G22: 26 | H22: 27 | I22: 27.75 | J22: 29 | K22: 30 | L22: 31
A23: списания | B23: =C23/C32 -> 0.0098313901 | C23: 2 | E23: price | F23: =C32*100/F22 -> 813.72012 | G23: =C32*100/G22 -> 782.4232 | H23: =C32*100/H22 -> 753.44456 | I23: =C32*100/I22 -> 733.08119 | J23: =C32*100/J22 -> 701.48287 | K23: =C32*100/K22 -> 678.1001 | L23: =C32*100/L22 -> 656.22591
A24: салфетки 4 шт. | B24: =C24/C32 -> 0.0058988341 | C24: 1.2
A25: зубочистка | B25: =C25/C32 -> 0.0016713363 | C25: 0.34
A26: пакет | B26: =C26/$C$32 -> 0.0098313901 | C26: 2 | F26: на месте | G26: с собой | H26: доставка
A27: наклейка брендированная | B27: =C27/$C$32 -> 0.012289238 | C27: 2.5 | E27: списания | F27: 2 | G27: 2 | H27: 2
A28: Гриль пакет | B28: =C28/C32 -> 0.033426726 | C28: 6.8 | E28: салфетки 4 шт. | F28: 1.2 | G28: 1.2 | H28: 0
A29: Фольга | B29: =C29/$C$32 -> 0.014255516 | C29: 2.9 | E29: зубочистка | F29: 0.34 | G29: 0.34 | H29: 0.34
A30: Соусник | B30: =C30/C32 -> 0.011109471 | C30: 2.26 | E30: пакет | F30: 0 | G30: 2 | H30: 2
A31: Перец якан турецкий | E31: наклейка брендированная | F31: 2.5 | G31: 2.5 | H31: 2.6
A32: Итого с/с | C32: =C22+H36 -> 203.43003 | E32: Гриль пакет | F32: 6.8 | G32: 6.1 | H32: 6.1
E33: Фольга | F33: 0 | G33: 2.9 | H33: 2.9
A34: cost общий | B34: =H38/B37 -> 0.34479666 | E34: Соусник | F34: 2.26 | G34: 2.26 | H34: 0
A35: cost упаковки | B35: =H36/B37 -> 0.027016949 | E35: Перец якан турецкий | F35: 8.8 | G35: 8.8 | H35: 0
A36: cost - продукции | B36: =C22/B37 -> 0.31777971 | F36: =SUM(F27:F35) -> 23.9 | G36: =SUM(G27:G35) -> 28.1 | H36: =SUM(H27:H35) -> 15.94
A37: Цена | B37: 590 | C37: =B37+H36 -> 605.94
H38: =C22+H36 -> 203.43003
A39: доставка | B39: =B37/70*100*1.15 -> 969.28571
A41: =B37-(H36+C22) -> 386.56997 | B41: =A41/B37 -> 0.65520334

Sheet Суджук сендвич
A1: Наименование блюда: | B1: Дюрюм
A3: Ингредиент | B3: Брутто | C3: Нетто | D3: Ед.изм. | E3: Объём потери | F3: % потери | G3: с/с руб. | H3: с/с % | I3: Выход (мл.)
A4: Суджук | B4: 26 | C4: =B4 -> 26 | D4: г | E4: =B4-C4 -> 0 | F4: =E4/B4*100 -> 0 | G4: =VLOOKUP(A4,'Матрица поставщиков'!A1:E530,5,0) * B4 -> 33.366667 | H4: =G4/$G$9 -> 0.34236174 | J4: 5 кружков
A5: Чиабатта | B5: 0.5 | C5: 75 | D5: г | E5: 0 | F5: =E5/B5*100 -> 0 | G5: =VLOOKUP(A5,'Матрица поставщиков'!A2:E531,5,0) * B5 -> 21.583333 | H5: =G5/$G$9 -> 0.22145777
A6: Помидоры - сливовые | B6: 30 | C6: 30 | D6: г | E6: =B6-C6 -> 0 | F6: =E6/B6*100 -> 0 | G6: =VLOOKUP(A6,'Матрица поставщиков'!A1:E53,5,0) * B6 -> 10.5 | H6: =G6/G9 -> 0.10773621
A7: сыр Российский | B7: 40 | C7: 40 | D7: г | E7: =B7-C7 -> 0 | F7: =E7/B7*100 -> 0 | G7: =VLOOKUP(A7,'Матрица поставщиков'!A3:E550,5,0) * B7 -> 27.652733 | H7: =G7/$G$9 -> 0.2837334
A8: п/ф соус для суджука | B8: 30 | C8: =B8 -> 30 | D8: г | E8: =B8-C8 -> 0 | F8: =E8/B8*100 -> 0 | G8: =('пф соус для суджука'!C21)*B8 -> 4.3575341 | H8: =G8/$G$9 -> 0.044710878
A9: Итого | B9: =SUM(B4:B8) -> 126.5 | C9: =SUM(C4:C8) -> 201 | D9: - | E9: =B9-C9 -> -74.5 | F9: - | G9: =SUM(G4:G8) -> 97.460267 | H9: =SUM(H4:H8) -> 1 | I9: =B9-E9 -> 201
A11: Технология приготовления
A14: Для расчёта цены продажи
A15: Состав позиции | B15: доля статьи % | C15: руб
A16: с/с блюда | B16: =C16/C26 -> 0.85943596 | C16: =G9 -> 97.460267 | E16: cost (%) | F16: 25 | G16: 26 | H16: 27 | I16: 27.75 | J16: 29 | K16: 30 | L16: 31
A17: списания | B17: =C17/C26 -> 0.017636643 | C17: 2 | E17: price | F17: =C26*100/F16 -> 453.60107 | G17: =C26*100/G16 -> 436.15487 | H17: =C26*100/H16 -> 420.00099 | I17: =C26*100/I16 -> 408.64961 | J17: =C26*100/J16 -> 391.0354 | K17: =C26*100/K16 -> 378.00089 | L17: =C26*100/L16 -> 365.80731
A18: салфетки 4 шт. | B18: =C18/C26 -> 0.010581986 | C18: 1.2
A19: зубочистка | B19: =C19/C26 -> 0.0029982293 | C19: 0.34
A20: пакет | B20: =C20/$C$26 -> 0.017636643 | C20: 2 | F20: на месте | G20: с собой | H20: доставка
A21: наклейка брендированная | B21: =C21/$C$26 -> 0.022045803 | C21: 2.5 | E21: списания | F21: 2 | G21: 2 | H21: 2
A22: Гриль пакет | B22: =C22/C26 -> 0.059964585 | C22: 6.8 | E22: салфетки 4 шт. | F22: 1.2 | G22: 1.2 | H22: 0
A23: Фольга | B23: =C23/$C$26 -> 0.025573132 | C23: 2.9 | E23: зубочистка | F23: 0.34 | G23: 0.34 | H23: 0.34
A24: Соусник | B24: =C24/C26 -> 0.019929406 | C24: 2.26 | E24: пакет | F24: 0 | G24: 2 | H24: 2
A25: Перец якан турецкий | E25: наклейка брендированная | F25: 2.5 | G25: 2.5 | H25: 2.6
A26: Итого с/с | C26: =C16+H30 -> 113.40027 | E26: Гриль пакет | F26: 6.8 | G26: 6.1 | H26: 6.1
E27: Фольга | F27: 0 | G27: 2.9 | H27: 2.9
A28: cost общий | B28: =H32/B31 -> 0.25200059 | E28: Соусник | F28: 2.26 | G28: 2.26 | H28: 0
A29: cost упаковки | B29: =H30/B31 -> 0.035422222 | E29: Перец якан турецкий | F29: 8.8 | G29: 8.8 | H29: 0
A30: cost - продукции | B30: =C16/B31 -> 0.21657837 | F30: =SUM(F21:F29) -> 23.9 | G30: =SUM(G21:G29) -> 28.1 | H30: =SUM(H21:H29) -> 15.94
A31: Цена | B31: 450 | C31: =B31+H30 -> 465.94
H32: =C16+H30 -> 113.40027
A33: доставка | B33: =B31/70*100 -> 642.85714
A35: =B31-(H30+C16) -> 336.59973 | B35: =A35/B31 -> 0.74799941

Sheet Кебаб дюрюм
A1: Наименование блюда: | B1: Дюрюм
A3: Ингредиент | B3: Брутто | C3: Нетто | D3: Ед.изм. | E3: Объём потери | F3: % потери | G3: с/с руб. | H3: с/с % | I3: Выход (мл.)
A4: Фарш Primebeef Классик говяжий охлажденный | B4: 150 | C4: 150 | D4: г | E4: =B4-C4 -> 0 | F4: =E4/B4*100 -> 0 | G4: =VLOOKUP(A4,'Матрица поставщиков'!A1:E530,5,0) * B4 -> 125.925 | H4: =G4/$G$12 -> 0.65542277
A5: Курдюк | B5: 15 | C5: 15 | D5: г | E5: =B5-C5 -> 0 | F5: =E5/B5*100 -> 0 | G5: =VLOOKUP(A5,'Матрица поставщиков'!A2:E531,5,0) * B5 -> 9.285 | H5: =G5/$G$12 -> 0.048327183
A6: Лаваш | B6: 100 | C6: 100 | D6: шт. | E6: =B6-C6 -> 0 | F6: =E6/B6*100 -> 0 | G6: =VLOOKUP(A6,'Матрица поставщиков'!A1:E56,5,0) -> 14.5 | H6: =G6/$G$12 -> 0.07547056
A7: Помидоры - сливовые | B7: 30 | C7: 30 | D7: г | E7: =B7-C7 -> 0 | F7: =E7/B7*100 -> 0 | G7: =VLOOKUP(A7,'Матрица поставщиков'!A1:E53,5,0) * B7 -> 10.5 | H7: =G7/G12 -> 0.054651095
A8: п/ф искандер соус | B8: 250 | C8: 80 | D8: мл | E8: =B8-C8 -> 170 | F8: =E8/B8*100 -> 68 | G8: =('пф искандер соус'!G11/'пф искандер соус'!I11)*B8 -> 9.0405 | H8: =G8/$G$12 -> 0.047054593 | K8: збс
A9: Маринованные огурцы (целые) | B9: 30 | C9: 30 | D9: г | E9: =B9-C9 -> 0 | F9: =E9/B9*100 -> 0 | G9: =VLOOKUP(A9,'Матрица поставщиков'!A1:E57,5,0) * B9 -> 10.94 | H9: =G9/$G$12 -> 0.056941236
A10: Майонез 30% | B10: 25 | C10: =B10 -> 25 | D10: г | E10: =B10-C10 -> 0 | F10: =E10/B10*100 -> 0 | G10: =VLOOKUP(A10,'Матрица поставщиков'!A1:E53,5,0) * B10 -> 2.3815789 | H10: =G10/$G$12 -> 0.0123958
A11: Фри | B11: 30 | C11: 30 | D11: г | E11: =B11-C11 -> 0 | F11: =E11/B11*100 -> 0 | G11: =('пф Фри'!G7/'пф Фри'!I7) * B11 -> 9.555819 | H11: =G11/$G$12 -> 0.049736759
A12: Итого | B12: =SUM(B4:B11) -> 630 | C12: =SUM(C4:C11) -> 460 | D12: - | E12: =B12-C12 -> 170 | F12: - | G12: =SUM(G4:G11) -> 192.1279 | H12: =SUM(H4:H11) -> 1 | I12: =B12-E12 -> 460
A14: Технология приготовления
A15: 1. Разогреть гриль до среднего жара 2. Промазать 2 лаваша с одной стороны соусом п/ф искандер соус 3. Поджарить каждый лаваш с двух сторон по 30 секунд на гриле 4. Разместить один лаваш поверх другого симметрично 5. Выложить дорожкой по центру маринованные огурцы 6. Выложить дорожкой по центру помидоры нарезанные 7. Выложить дорожкой по центру мясо 8. Разместить по центру белый соус 9. Завернуть лаваш 10. Смазать соусом искандер каждую сторону лаваша и поджарить 30 секунд до слегка тёмной корочки *в 10-м пункте начинать жарить со стороны открытого лаваша ( нужно запечатать )
A17: Для расчёта цены продажи
A18: Состав позиции | B18: доля статьи % | C18: руб
A19: с/с блюда | B19: =C19/C27 -> 0.91547064 | C19: =G12 -> 192.1279 | E19: cost (%) | F19: 25 | G19: 26 | H19: 27 | I19: 27.75 | J19: 29 | K19: 30 | L19: 31
A20: списания | B20: =C20/C27 -> 0.0095298043 | C20: 2 | E20: price | F20: =C27*100/F19 -> 839.47159 | G20: =C27*100/G19 -> 807.18422 | H20: =C27*100/H19 -> 777.28851 | I20: =C27*100/I19 -> 756.28071 | J20: =C27*100/J19 -> 723.68241 | K20: =C27*100/K19 -> 699.55966 | L20: =C27*100/L19 -> 676.99322
A21: салфетки 4 шт. | B21: =C21/C27 -> 0.0057178826 | C21: 1.2
A22: зубочистка | B22: =C22/C27 -> 0.0016200667 | C22: 0.34
A23: пакет | B23: =C23/$C$26 -> 0.68965517 | C23: 2
A24: наклейка брендированная | B24: =C24/$C$26 -> 0.86206897 | C24: 2.5
A25: Гриль пакет | B25: =C25/C27 -> 0.032401335 | C25: 6.8
A26: Фольга | B26: =C26/C27 -> 0.013818216 | C26: 2.9
A27: Итого с/с | C27: =SUM(C19:C26) -> 209.8679
A29: cost общий | B29: =C27/B31 -> 0.29981128
A30: cost - продукции | B30: =C19/B31 -> 0.27446843
A31: Цена | B31: 700

Sheet Искандер дюрюм + сыр
A1: Наименование блюда: | B1: Дюрюм
A3: Ингредиент | B3: Брутто | C3: Нетто | D3: Ед.изм. | E3: Объём потери | F3: % потери | G3: с/с руб. | H3: с/с % | I3: Выход (мл.)
A4: п/ф курица жареная | B4: 80 | C4: =B4 -> 80 | D4: г | E4: =B4-C4 -> 0 | F4: =E4/B4*100 -> 0 | G4: ='пф курица готовая'!G6/'пф курица готовая'!I6*B4 -> 41.135081 | H4: =G4/$G$12 -> 0.31508343
A5: Лаваш | B5: 100 | C5: 100 | D5: шт. | E5: =B5-C5 -> 0 | F5: =E5/B5*100 -> 0 | G5: =VLOOKUP(A5,'Матрица поставщиков'!A1:E56,5,0) -> 14.5 | H5: =G5/$G$12 -> 0.11106602
A6: Помидоры - сливовые | B6: 30 | C6: 30 | D6: г | E6: =B6-C6 -> 0 | F6: =E6/B6*100 -> 0 | G6: =VLOOKUP(A6,'Матрица поставщиков'!A1:E53,5,0) * B6 -> 10.5 | H6: =G6/G12 -> 0.080427119
A7: п/ф искандер соус | B7: 250 | C7: 80 | D7: мл | E7: =B7-C7 -> 170 | F7: =E7/B7*100 -> 68 | G7: =('пф искандер соус'!G11/'пф искандер соус'!I11)*B7 -> 9.0405 | H7: =G7/$G$12 -> 0.06924775
A8: Чеддер плавленный | B8: 37.5 | C8: =B8 -> 37.5 | D8: г | E8: =B8-C8 -> 0 | F8: =E8/B8*100 -> 0 | G8: =VLOOKUP(A8,'Матрица поставщиков'!A1:E52,5,0) * B8 -> 32.5 | H8: =G8/G12 -> 0.24894108 | K8: посчитан Hochland чизбургер
A9: Маринованные огурцы (целые) | B9: 30 | C9: 30 | D9: г | E9: =B9-C9 -> 0 | F9: =E9/B9*100 -> 0 | G9: =VLOOKUP(A9,'Матрица поставщиков'!A1:E57,5,0) * B9 -> 10.94 | H9: =G9/$G$12 -> 0.083797399
A10: Майонез 30% | B10: 25 | C10: =B10 -> 25 | D10: г | E10: =B10-C10 -> 0 | F10: =E10/B10*100 -> 0 | G10: =VLOOKUP(A10,'Матрица поставщиков'!A1:E53,5,0) * B10 -> 2.3815789 | H10: =G10/$G$12 -> 0.018242241
A11: Фри | B11: 30 | C11: 30 | D11: г | E11: =B11-C11 -> 0 | F11: =E11/B11*100 -> 0 | G11: =('пф Фри'!G7/'пф Фри'!I7) * B11 -> 9.555819 | H11: =G11/$G$12 -> 0.073194952
A12: Итого | B12: =SUM(B4:B11) -> 582.5 | C12: =SUM(C4:C11) -> 412.5 | D12: - | E12: =B12-C12 -> 170 | F12: - | G12: =SUM(G4:G11) -> 130.55298 | H12: =SUM(H4:H11) -> 1 | I12: =B12-E12 -> 412.5
A14: Технология приготовления
A15: 1. Разогреть гриль до среднего жара 2. Промазать 2 лаваша с одной стороны соусом п/ф искандер соус 3. Поджарить каждый лаваш с двух сторон по 30 секунд на гриле 4. Разместить один лаваш поверх другого симметрично 5. Выложить дорожкой по центру маринованные огурцы 6. Выложить дорожкой по центру помидоры нарезанные 7. Выложить дорожкой по центру мясо 8. Разместить по центру белый соус 9. Завернуть лаваш 10. Смазать соусом искандер каждую сторону лаваша и поджарить 30 секунд до слегка тёмной корочки *в 10-м пункте начинать жарить со стороны открытого лаваша ( нужно запечатать )
A17: Для расчёта цены продажи
A18: Состав позиции | B18: доля статьи % | C18: руб
A19: с/с блюда | B19: =C19/C27 -> 0.88037195 | C19: =G12 -> 130.55298 | E19: cost (%) | F19: 25 | G19: 26 | H19: 27 | I19: 27.75 | J19: 29 | K19: 30 | L19: 31
A20: списания | B20: =C20/C27 -> 0.013486815 | C20: 2 | E20: price | F20: =C27*100/F19 -> 593.17191 | G20: =C27*100/G19 -> 570.35761 | H20: =C27*100/H19 -> 549.23325 | I20: =C27*100/I19 -> 534.38911 | J20: =C27*100/J19 -> 511.3551 | K20: =C27*100/K19 -> 494.30993 | L20: =C27*100/L19 -> 478.36445
A21: салфетки 4 шт. | B21: =C21/C27 -> 0.0080920891 | C21: 1.2
A22: зубочистка | B22: =C22/C27 -> 0.0022927586 | C22: 0.34
A23: пакет | B23: =C23/$C$26 -> 0.68965517 | C23: 2
A24: наклейка брендированная | B24: =C24/$C$26 -> 0.86206897 | C24: 2.5
A25: Гриль пакет | B25: =C25/C27 -> 0.045855172 | C25: 6.8
A26: Фольга | B26: =C26/C27 -> 0.019555882 | C26: 2.9
A27: Итого с/с | C27: =SUM(C19:C26) -> 148.29298
A29: cost общий | B29: =C27/B31 -> 0.2696236
A30: cost - продукции | B30: =C19/B31 -> 0.23736905
A31: Цена | B31: 550

Sheet Искандер дюрюм - mini (не согла
A1: Наименование ТТК: | B1: Iskendy Durum - mini | K1: cost (%) | L1: 25 | M1: 26 | N1: 27 | O1: 28 | P1: 29 | Q1: 30 | R1: 31
K2: price | L2: =G12*100/L1 -> 397.31787 | M2: =G12*100/M1 -> 382.03641 | N2: =G12*100/N1 -> 367.88692 | O2: =G12*100/O1 -> 354.7481 | P2: =G12*100/P1 -> 342.5154 | Q2: =G12*100/Q1 -> 331.09822 | R2: =G12*100/R1 -> 320.41764
A3: Ингредиент | B3: Брутто | C3: Нетто | D3: Ед.изм. | E3: Объём потери | F3: % потери | G3: с/с руб. | H3: с/с % | I3: Выход (мл.)
A4: п/ф мясо жареннное | B4: 90 | C4: =B4 -> 90 | D4: г | E4: =B4-C4 -> 0 | F4: =E4/B4*100 -> 0 | G4: ='пф курица готовая'!G6/'пф курица готовая'!I6*B4 -> 46.276966 | H4: =G4/$G$12 -> 0.46589363
A5: Лаваш | B5: 100 | C5: =B5 -> 100 | D5: г | E5: =B5-C5 -> 0 | F5: =E5/B5*100 -> 0 | G5: =VLOOKUP(A5,'Матрица поставщиков'!A1:E56,5,0) -> 14.5 | H5: =G5/$G$12 -> 0.14597884
A6: Помидоры - сливовые | B6: 20 | C6: =B6 -> 20 | D6: г | E6: =B6-C6 -> 0 | F6: =E6/B6*100 -> 0 | G6: =VLOOKUP(A6,'Матрица поставщиков'!A1:E53,5,0) * B6 -> 7 | H6: =G6/G12 -> 0.070472541
A7: п/ф искандер соус | B7: 100 | C7: 70 | D7: мл | E7: =B7-C7 -> 30 | F7: =E7/B7*100 -> 30 | G7: =('пф искандер соус'!G11/'пф искандер соус'!I11)*B7 -> 3.6162 | H7: =G7/$G$12 -> 0.036406115
A8: Петрушка | B8: 2 | C8: =B8 -> 2 | D8: г | E8: =B8-C8 -> 0 | F8: =E8/B8*100 -> 0 | G8: =VLOOKUP(A8,'Матрица поставщиков'!A1:E52,5,0) * B8 -> 6.2222222 | H8: =G8/G12 -> 0.062642259
A9: Маринованные огурцы (целые) | B9: 15 | C9: =B9 -> 15 | D9: г | E9: =B9-C9 -> 0 | F9: =E9/B9*100 -> 0 | G9: =VLOOKUP(A9,'Матрица поставщиков'!A1:E57,5,0) * B9 -> 5.47 | H9: =G9/$G$12 -> 0.055069257
A10: п/ф майонез турецкий | B10: 15 | C10: =B10 -> 15 | D10: мл | E10: =B10-C10 -> 0 | F10: =E10/B10*100 -> 0 | G10: =('пф Сырный дип'!G13/'пф Сырный дип'!I13)*B10 -> 9.8735333 | H10: =G10/$G$12 -> 0.099401855
A11: Фри | B11: 20 | C11: =B11 -> 20 | D11: г | E11: =B11-C11 -> 0 | F11: =E11/B11*100 -> 0 | G11: =('пф Фри'!G7/'пф Фри'!I7) * B11 -> 6.370546 | H11: =G11/$G$12 -> 0.06413551
A12: Итого | B12: =SUM(B4:B11) -> 362 | C12: =SUM(C4:C11) -> 332 | D12: - | E12: =B12-C12 -> 30 | F12: - | G12: =SUM(G4:G11) -> 99.329467 | H12: =SUM(H4:H11) -> 1 | I12: =B12-E12 -> 332
A14: Технология приготовления
A15: 1. Разогреть гриль до среднего жара 2. Промазать 2 лаваша с одной стороны соусом п/ф искандер соус 3. Поджарить каждый лаваш с двух сторон по 30 секунд на гриле 4. Разместить один лаваш поверх другого симметрично 5. Выложить дорожкой по центру маринованные огурцы 6. Выложить дорожкой по центру помидоры нарезанные 7. Выложить дорожкой по центру мясо 8. Разместить по центру белый соус 9. Завернуть лаваш 10. Смазать соусом искандер каждую сторону лаваша и поджарить 30 секунд до слегка тёмной корочки *в 10-м пункте начинать жарить со стороны открытого лаваша ( нужно запечатать )
A17: Для расчёта цены продажи
B18: % | C18: руб
A19: с/с блюда | B19: =C19/C22 -> 0.9477157 | C19: =G12 -> 99.329467 | E19: cost (%) | F19: 25 | G19: 26 | H19: 27 | I19: 27.75 | J19: 29 | K19: 30 | L19: 31
A20: списания | B20: 0.03 | C20: =C19*B20 -> 2.979884 | E20: price | F20: =C22*100/F19 -> 419.23741 | G20: =C22*100/G19 -> 403.11289 | H20: =C22*100/H19 -> 388.18278 | I20: =C22*100/I19 -> 377.69136 | J20: =C22*100/J19 -> 361.41156 | K20: =C22*100/K19 -> 349.3645 | L20: =C22*100/L19 -> 338.09468
A21: упаковка | B21: =C21/C22 -> 0.023852833 | C21: 2.5
A22: Итого с/с | C22: =SUM(C19:C21) -> 104.80935
A24: цена | B24: 360
A25: cost общий | B25: =C22/B24 -> 0.29113709
A26: cost - продукции | B26: =C19/B24 -> 0.27591519

Sheet Кофе по-турецки с кардамоном
A1: Наименование ТТК: | B1: Кофе по-турецки с кардамоном
A3: Ингредиент | B3: Брутто | C3: Нетто | D3: Ед.изм. | E3: вес потери | F3: % потери | G3: с/с руб. | H3: с/с % | I3: Выход (мл.)
A4: Турецкий кофе KURUKAHVECI MEHMET EFENDI | B4: 10 | C4: =B4 -> 10 | D4: г. | E4: =B4-C4 -> 0 | F4: =E4/B4*100 -> 0 | G4: =VLOOKUP(A4,'Матрица поставщиков'!A1:E100,5,False) * B4 -> 13.04 | H4: =G4/G7 -> #N/A
A5: вода | B5: 100 | C5: =B5 -> 100 | D5: г. | E5: =B5-C5 -> 0 | F5: =E5/B5*100 -> 0 | G5: =(VLOOKUP(A5,'Матрица поставщиков'!A1:E100,5,False) * B5)/10 -> 0 | H5: =G5/$G$7 -> #N/A
A6: Кардамон молотый зелёный | B6: 0.1 | C6: 0.1 | D6: г. | E6: =B6-C6 -> 0 | F6: =E6/B6*100 -> 0 | G6: =(VLOOKUP(A6,'Матрица поставщиков'!A2:E100,5,False) * B6)/10 -> #N/A | H6: =G6/$G$7 -> #N/A
A7: Итого | B7: =B5 -> 100 | C7: =B7 -> 100 | D7: - | E7: =B7-C7 -> 0 | F7: =E7/B7*100 -> 0 | G7: =SUM(G4:G6) -> #N/A | H7: =SUM(H4:H5) -> #N/A | I7: =B7-E7 -> 100
A9: Технология приготовления
A10: 1. Засыпать чай в чашку 2. Залить кипятком
B11: выход | C11: с/с
B12: 100 | C12: =G7/I7*B12 -> #N/A
B13: 1 | C13: =G7/I7*B13 -> #N/A
B15: Для расчёта цены продажи
C16: % | D16: руб | E16: цена так
B17: с/с блюда | C17: =D17/D20 -> #N/A | D17: =C12 -> #N/A | F17: cost (%) | G17: 10 | H17: 15 | I17: 20
B18: списания | C18: 0.04 | D18: =D17*C18 -> #N/A | F18: price | G18: =D20*100/G17 -> #N/A | H18: =D20*100/H17 -> #N/A | I18: =D20*100/I17 -> #N/A
B19: упаковка | C19: =D19/D20 -> #N/A | D19: 4
B20: Итого с/с | D20: =SUM(D17:D19) -> #N/A
B22: цена | C22: 240
B23: cost общий | C23: =D20/C22 -> #N/A
B24: cost - продукции | C24: =D17/C22 -> #N/A

Sheet Кофе по-турецки с фундуком
A1: Наименование ТТК: | B1: Кофе по-турецки с фундуком
A3: Ингредиент | B3: Брутто | C3: Нетто | D3: Ед.изм. | E3: вес потери | F3: % потери | G3: с/с руб. | H3: с/с % | I3: Выход (мл.)
A4: Турецкий кофе с фундуком nuri toplar | B4: 10 | C4: =B4 -> 10 | D4: г. | E4: =B4-C4 -> 0 | F4: =E4/B4*100 -> 0 | G4: =VLOOKUP(A4,'Матрица поставщиков'!A1:E60,5,False) * B4 -> 40 | H4: =G4/G6 -> 1
A5: вода | B5: 100 | C5: 100 | D5: г. | E5: =B5-C5 -> 0 | F5: =E5/B5*100 -> 0 | G5: =(VLOOKUP(A5,'Матрица поставщиков'!A1:E53,5,False) * B5)/10 -> 0 | H5: =G5/G6 -> 0
A6: Итого | B6: =sum(B4:B5) -> 110 | C6: =B6 -> 110 | D6: - | E6: =B6-C6 -> 0 | F6: =E6/B6*100 -> 0 | G6: =SUM(G4:G5) -> 40 | H6: =SUM(H4:H5) -> 1 | I6: =B6-E6 -> 110
A8: Технология приготовления
A9: 1. Засыпать чай в чашку 2. Залить кипятком
B10: выход | C10: с/с
B11: 110 | C11: =G6/I6*B11 -> 40
B12: 1 | C12: =G6/I6*B12 -> 0.36363636
B14: Для расчёта цены продажи
C15: % | D15: руб | E15: цена так
B16: с/с блюда | C16: =D16/D19 -> 0.87719298 | D16: =C11 -> 40 | F16: cost (%) | G16: 5 | H16: 7 | I16: 9
B17: списания | C17: 0.04 | D17: =D16*C17 -> 1.6 | F17: price | G17: =D19*100/G16 -> 912 | H17: =D19*100/H16 -> 651.42857 | I17: =D19*100/I16 -> 506.66667
B18: упаковка | C18: =D18/D19 -> 0.087719298 | D18: 4
B19: Итого с/с | D19: =SUM(D16:D18) -> 45.6
B21: цена | C21: 350
B22: cost общий | C22: =D19/C21 -> 0.13028571
B23: cost - продукции | C23: =D16/C21 -> 0.11428571

Sheet Искандер дюрюм Zurna
A1: Наименование ТТК: | B1: Iskendy Durum Zurna | K1: cost (%) | L1: 25 | M1: 26 | N1: 27 | O1: 28 | P1: 29 | Q1: 30 | R1: 31
K2: price | L2: =G11*100/L1 -> 657.72858 | M2: =G11*100/M1 -> 632.43133 | N2: =G11*100/N1 -> 609.00794 | O2: =G11*100/O1 -> 587.25766 | P2: =G11*100/P1 -> 567.0074 | Q2: =G11*100/Q1 -> 548.10715 | R2: =G11*100/R1 -> 530.42627
A3: Ингредиент | B3: Брутто | C3: Нетто | D3: Ед.изм. | E3: Объём потери | F3: % потери | G3: с/с руб. | H3: с/с % | I3: Выход (мл.)
A4: п/ф мясо жареннное | B4: 120 | C4: =B4 -> 120 | D4: г | E4: =B4-C4 -> 0 | F4: =E4/B4*100 -> 0 | G4: ='пф курица готовая'!G6/'пф курица готовая'!I6*B4 -> 61.702621 | H4: =G4/$G$11 -> 0.37524671
A5: п/ф Лаваш Искенди | B5: ='пф Лаваш Искенди'!B5*2 -> 240 | C5: =B5 -> 240 | D5: шт | E5: =B5-C5 -> 0 | F5: =E5/B5*100 -> 0 | G5: ='пф Лаваш Искенди'!G6*2 -> 37.67888 | H5: =G5/$G$11 -> 0.22914546
A6: Помидоры - сливовые | B6: 60 | C6: =B6 -> 60 | D6: г | E6: =B6-C6 -> 0 | F6: =E6/B6*100 -> 0 | G6: =VLOOKUP(A6,'Матрица поставщиков'!A1:E53,5,0) * B6 -> 21 | H6: =G6/G11 -> 0.12771225
A7: п/ф искандер соус | B7: 190 | C7: 160 | D7: мл | E7: =B7-C7 -> 30 | F7: =E7/B7*100 -> 15.789474 | G7: =('пф искандер соус'!G11/'пф искандер соус'!I11)*B7 -> 6.87078 | H7: =G7/$G$11 -> 0.041784896
A8: Маринованные огурцы (целые) | B8: 55 | C8: =B8 -> 55 | D8: г | E8: =B8-C8 -> 0 | F8: =E8/B8*100 -> 0 | G8: =VLOOKUP(A8,'Матрица поставщиков'!A1:E57,5,0) * B8 -> 20.056667 | H8: =G8/$G$11 -> 0.12197534
A9: Майонез 30% | B9: 46 | C9: =B9 -> 46 | D9: мл | E9: =B9-C9 -> 0 | F9: =E9/B9*100 -> 0 | G9: =VLOOKUP(A9,'Матрица поставщиков'!A1:E53,5,0) * B9 -> 4.3821053 | H9: =G9/$G$11 -> 0.026649931
A10: Фри | B10: 40 | C10: 40 | D10: г | E10: =B10-C10 -> 0 | F10: =E10/B10*100 -> 0 | G10: =('пф Фри'!G7/'пф Фри'!I7) * B10 -> 12.741092 | H10: =G10/$G$11 -> 0.077485409
A11: Итого | B11: =SUM(B4:B10) -> 751 | C11: =SUM(C4:C10) -> 721 | D11: - | E11: =B11-C11 -> 30 | F11: - | G11: =SUM(G4:G10) -> 164.43214 | H11: =SUM(H4:H10) -> 1 | I11: =C11 -> 721
A13: Технология приготовления
A14: 1. Разогреть гриль до 200 4. Разместить один лаваш поверх другого симметрично 5. Выложить дорожкой по центру маринованные огурцы 6. Выложить дорожкой по центру помидоры нарезанные 7. Выложить дорожкой по центру мясо 8. Разместить по центру белый соус 9. Завернуть лаваш 10. Смазать соусом искандер каждую сторону лаваша и поджарить 30 секунд до слегка тёмной корочки *в 10-м пункте начинать жарить со стороны открытого лаваша ( нужно запечатать )
A16: Для расчёта цены продажи
B17: % | C17: руб
A18: с/с блюда | B18: =C18/C25 -> 0.95483821 | C18: =G11 -> 164.43214 | E18: cost (%) | F18: 25 | G18: 26 | H18: 27 | I18: 27.75 | J18: 29 | K18: 30 | L18: 31
A19: списания | B19: 0.04 | C19: =C18*B19 -> 6.5772858 | E19: price | F19: =C25*100/F18 -> 688.83772 | G19: =C25*100/G18 -> 662.34396 | H19: =C25*100/H18 -> 637.81271 | I19: =C25*100/I18 -> 620.57453 | J19: =C25*100/J18 -> 593.82562 | K19: =C25*100/K18 -> 574.03144 | L19: =C25*100/L18 -> 555.51429
A20: салфетки 4 шт. | B20: =C20/C25 -> 0.0069682595 | C20: 1.2
A21: зубочистка | B21: =C21/C25 -> 0.0019743402 | C21: 0.34
A22: пакет | B22: =C22/C25 -> 0.011613766 | C22: 2
A23: наклейка брендированная | B23: =C23/C25 -> 0.014517207 | C23: 2.5 | G23: на месте | H23: с собой | I23: доставка
A24: Фольга | B24: =C24/C25 -> 0.050519881 | C24: 8.7 | F24: списания | G24: 2 | H24: 2 | I24: 2
A25: Итого с/с | C25: =SUM(C18:C20) -> 172.20943 | F25: салфетки 4 шт. | G25: 1.2 | H25: 1.2 | I25: 1.2
F26: зубочистка | G26: 0.34 | H26: 0.34 | I26: 0.34
F27: пакет | G27: 0 | H27: 2 | I27: 2
F28: наклейка брендированная | G28: 0 | H28: 2.5 | I28: 2.5
A30: цена | B30: =B35 -> 800 | F30: Фольга | G30: 5.75 | H30: 8.625 | I30: 8.625
A31: cost общий | B31: =I35/B30 -> 0.22637143 | F31: Соусник | G31: 2.26 | H31: 2.26 | I31: 0
A32: cost - продукции | B32: =G11/B30 -> 0.20554018 | F32: Перец якан турецкий | G32: 8.8 | H32: 8.8 | I32: 0
D33: =B30+I33 -> 816.665 | F33: Итого | G33: =SUM(G24:G32) -> 20.35 | H33: =SUM(H24:H32) -> 27.725 | I33: =SUM(I24:I32) -> 16.665
A35: цена | B35: 800 | F35: с/с продкции + с/с упаковки | I35: =G11+I33 -> 181.09714
A36: доставка | B36: 1150

Sheet Комбо-1_2
A1: Наименование ТТК: | B1: Комбо: Дюрюм + суп +фри + соус + напиток | L1: cost (%) | M1: 25 | N1: 26 | O1: 27 | P1: 27.75 | Q1: 29 | R1: 30 | S1: 31
L2: price | M2: =E9*100/M1 -> #REF! | N2: =E9*100/N1 -> #REF! | O2: =E9*100/O1 -> #REF! | P2: =E9*100/P1 -> #REF! | Q2: =E9*100/Q1 -> #REF! | R2: =E9*100/R1 -> #REF! | S2: =E9*100/S1 -> #REF!
A3: Ингредиент | B3: Выход комбо | C3: Выход соло | D3: Ед.изм. | E3: с/с руб. | F3: с/с % | G3: цена по отдельности | H3: цена комбо | I3: выгода гостя % | J3: cost
A4: Чечевичный суп | B4: 200 | C4: 300 | D4: г | E4: ='Чечевичный суп'!F17 * B4 -> 12.364621 | F4: =E4/$E$9 -> #REF! | G4: ='Чечевичный суп'!B24 -> 300
A5: Iskanderun Durum Tavuk | B5: 350 | C5: 350 | D5: г | E5: ='Дюрюм'!C18 -> #REF! | F5: =E5/$E$9 -> #REF! | G5: ='Дюрюм'!B33 -> #REF!
A6: Фри | B6: 100 | C6: 100 | D6: г | E6: ='Фри на продажу'!C14*B6 -> 33.452985 | F6: =E6/$E$9 -> #REF! | G6: ='Фри на продажу'!C38 -> 230
A7: Соус сырный/кетчуп | B7: 30 | C7: 30 | D7: г | E7: ='Сырный соус'!D15 | F7: =E7/$E$9 -> #REF! | G7: ='Сырный соус'!C35 -> 70
A8: Напиток на выбор | B8: 270 | C8: 270 | E8: =VLOOKUP(G14,'Матрица поставщиков'!A1:E530,5,0) -> 52 | F8: =E8/$E$9 -> #REF! | G8: 190
A9: Итого | B9: =SUM(B4:B8) -> 950 | C9: =SUM(C4:C8) -> 1050 | D9: - | E9: =SUM(E4:E8) -> #REF! | F9: =SUM(F4:F8) -> #REF! | G9: =SUM(G4:G8) -> #REF! | H9: 950 | I9: =G9/H9-100% -> #REF! | J9: =E9/H9 -> #REF! | K9: =K28/H9 -> 0.052736842 | L9: =(E9+K28)/H9 -> #REF! | M9: =E9/H9 -> #REF!
G11: доставка | H11: 1360
G14: Кола Добрый | I14: на месте | J14: с собой | K14: доставка
H15: списания | I15: 2 | J15: 2 | K15: 2
H16: салфетки 4 шт. | I16: 1.2 | J16: 1.2 | K16: 1.2
H17: зубочистка | I17: 0.34 | J17: 0.34 | K17: 0.34
H18: пакет | I18: 0 | J18: 2 | K18: 2
H19: наклейка брендированная | I19: 7.5 | J19: 7.5 | K19: 2.5
H20: Гриль пакет | I20: 6.8 | J20: 6.1 | K20: 6.1
H21: Фольга | I21: 0 | J21: 2.9 | K21: 2.9
H22: Соусник | I22: 4.52 | J22: 4.52 | K22: 4.52
H23: Супница | I23: 12.85 | J23: 12.85 | K23: 12.85
H24: Ложка+конверт | I24: 2.67 | J24: 2.67 | K24: 2.67
H25: Стакан | I25: 2.7 | J25: 2.7 | K25: 2.7
H26: Крышка | I26: 0 | J26: 1.52 | K26: 1.52
H27: Перец якан турецкий | I27: 8.8 | J27: 8.8 | K27: 8.8
I28: =SUM(I15:I27) -> 49.38 | J28: =SUM(J15:J27) -> 55.1 | K28: =SUM(K15:K27) -> 50.1
K30: =E9+K28 -> #REF!

Sheet Фри на продажу
A1: Наименование ТТК: | B1: Фри
A3: Ингредиент | B3: Брутто | C3: Нетто | D3: Ед.изм. | E3: вес потери | F3: % потери | G3: с/с руб. | H3: с/с % | I3: Выход (мл.)
A4: п/ф Фри | B4: 100 | C4: 100 | D4: г. | E4: =B4-C4 -> 0 | F4: =E4/B4*100 -> 0 | G4: ='пф Фри в панировке'!L5*B4 -> 30.078472 | H4: =G4/G8 -> 0.89912671
A5: Паприка | B5: 1 | C5: 1 | D5: г. | E5: =B5-C5 -> 0 | F5: =E5/B5*100 -> 0 | G5: =VLOOKUP(A5,'Матрица поставщиков'!A1:E53,5,0) * B5 -> 0.67 | H5: =G5/G8 -> 0.020028108
A6: копченая паприка 2 | B6: 1 | C6: 1 | D6: г. | E6: =B6-C6 -> 0 | F6: =E6/B6*100 -> 0 | G6: =VLOOKUP(A6,'Матрица поставщиков'!A2:E540,5,0) * B6 -> 2.6205128 | H6: =G6/G8 -> 0.0783342
A7: Соль | B7: 2 | C7: 2 | D7: г. | E7: =B7-C7 -> 0 | F7: =E7/B7*100 -> 0 | G7: =VLOOKUP(A7,'Матрица поставщиков'!A1:E54,5,0) * B7 -> 0.084 | H7: =G7/G8 -> 0.0025109867
A8: Итого | B8: =SUM(B4) -> 100 | C8: =SUM(C4) -> 100 | D8: г. | E8: =B8-C8 -> 0 | F8: =E8/B8*100 -> 0 | G8: =SUM(G4:G7) -> 33.452985 | H8: =SUM(H4:H7) -> 1 | I8: =B8-E8 -> 100
A10: Технология приготовления
A11: Жарить во фритюре 3мин 15 сек. Добавить смесь соли и паприки двумя быстрыми кивками. Подать в стакане
B12: выход | C12: с/с
B13: =I8 -> 100 | C13: =G8/I8*B13 -> 33.452985
B14: 1 | C14: =G8/I8*B14 -> 0.33452985
B16: Для расчёта цены продажи
C17: % | D17: руб | E17: цена так
B18: с/с блюда | C18: =D18/D26 -> 0.72766615 | D18: =C13 -> 33.452985 | F18: cost (%) | G18: 10 | H18: 15 | I18: 20
B19: списания | C19: =D19/D26 -> 0.04350381 | D19: 2 | F19: price | G19: =D26*100/G18 -> 459.72985 | H19: =D26*100/H18 -> 306.48657 | I19: =D26*100/I18 -> 229.86492
B20: салфетки 4 шт. | C20: =D20/D26 -> 0.026102286 | D20: 1.2
B21: зубочистка | C21: =D21/D26 -> 0.0073956477 | D21: 0.34
B22: Стакан | C22: =D22/D26 -> 0.058730143 | D22: 2.7
B23: наклейка брендированная | C23: =D23/D26 -> 0.054379762 | D23: 2.5
B24: Соусник | C24: =D24/D26 -> 0.049159305 | D24: 2.26 | H24: на месте | I24: с собой | J24: доставка
B25: крышка | C25: =D25/D26 -> 0.033062896 | D25: 1.52 | G25: списания | H25: 2 | I25: 2 | J25: 2
B26: Итого с/с | D26: =SUM(D18:D25) -> 45.972985 | G26: салфетки 4 шт. | H26: 1.2 | I26: 1.2 | J26: 1.2
G27: зубочистка | H27: 0.34 | I27: 0.34 | J27: 0.34
G28: пакет | H28: 0 | I28: 0
G29: наклейка брендированная | H29: 2.5 | I29: 2.5 | J29: 2.5
G30: Стакан | H30: 2.7 | I30: 2.7 | J30: 2.7
G31: Крышка | H31: 0 | I31: 1.52 | J31: 1.52
B33: цена | C33: 230
B34: cost общий | C34: =J36/C33 -> 0.19005646 | H34: =SUM(H25:H33) -> 8.74 | I34: =SUM(I25:I33) -> 10.26 | J34: =SUM(J25:J33) -> 10.26
B35: cost - продукции | C35: =D18/C33 -> 0.14544776
J36: =D18+J34 -> 43.712985
B38: цена | C38: 230
B39: доставка | C39: 330

Sheet Перец Якан
A1: Наименование ТТК: | B1: Перец Якан
A3: Ингредиент | B3: Брутто | C3: Нетто | D3: Ед.изм. | E3: вес потери | F3: % потери | G3: с/с руб. | H3: с/с % | I3: Выход (мл.)
A4: Перец Якан | B4: 12 | C4: 12 | D4: г. | E4: =B4-C4 -> 0 | F4: =E4/B4*100 -> 0 | G4: =VLOOKUP(A4,'Матрица поставщиков'!A1:E530,5,0) * B4 -> 8.088 | H4: =G4/G5 -> 1
A5: Итого | B5: =SUM(B4) -> 12 | C5: =SUM(C4) -> 12 | D5: г. | E5: =B5-C5 -> 0 | F5: =E5/B5*100 -> 0 | G5: =SUM(G4) -> 8.088 | H5: =SUM(H4) -> 1 | I5: =B5-E5 -> 12
A7: Технология приготовления
A8: Наложить 10гр щипцами в соусник
B9: выход | C9: с/с
B10: =I5 -> 12 | C10: =G5/I5*B10 -> 8.088
B11: 1 | C11: =G5/I5*B11 -> 0.674
B13: Для расчёта цены продажи
C14: % | D14: руб | E14: цена так
B15: с/с блюда | C15: =D15/D23 -> 0.39246894 | D15: =C10 -> 8.088 | F15: cost (%) | G15: 10 | H15: 15 | I15: 20
B16: списания | C16: =D16/D23 -> 0.097049689 | D16: 2 | F16: price | G16: =D23*100/G15 -> 206.08 | H16: =D23*100/H15 -> 137.38667 | I16: =D23*100/I15 -> 103.04
B17: салфетки 4 шт. | C17: =D17/D23 -> 0.058229814 | D17: 1.2
B18: зубочистка | C18: =D18/D23 -> 0.016498447 | D18: 0.34
B19: Стакан | C19: =D19/D23 -> 0.13101708 | D19: 2.7
B20: наклейка брендированная | C20: =D20/D23 -> 0.12131211 | D20: 2.5
B21: Соусник | C21: =D21/D23 -> 0.10966615 | D21: 2.26 | H21: на месте | I21: с собой | J21: доставка
B22: крышка | C22: =D22/D23 -> 0.073757764 | D22: 1.52 | G22: списания | H22: 0 | I22: 0 | J22: 0
B23: Итого с/с | D23: =SUM(D15:D22) -> 20.608 | G23: салфетки 4 шт. | H23: 0 | I23: 0 | J23: 0
G24: зубочистка | H24: 0 | I24: 0 | J24: 0
G25: пакет | H25: 0 | I25: 0 | J25: 0
G26: наклейка брендированная | H26: 0 | I26: 0 | J26: 0
G27: Соусник | H27: 2.26 | I27: 2.26 | J27: 2.26
G28: Крышка | H28: 0 | I28: 0 | J28: 0
B30: цена | C30: 60 | D30: =C30+J31 -> 62.26
B31: cost общий | C31: =J33/C30 -> 0.17246667 | H31: =SUM(H22:H30) -> 2.26 | I31: =SUM(I22:I30) -> 2.26 | J31: =SUM(J22:J30) -> 2.26
B32: cost - продукции | C32: =D15/C30 -> 0.1348
J33: =D15+J31 -> 10.348
B35: цена | C35: 60
B36: доставка | C36: 85

Sheet Искандер соус
A1: Наименование ТТК: | B1: Искандер соус
A3: Ингредиент | B3: Брутто | C3: Нетто | D3: Ед.изм. | E3: вес потери | F3: % потери | G3: с/с руб. | H3: с/с % | I3: Выход (мл.)
A4: Масло растительное | B4: 40 | C4: =B4 -> 40 | D4: г | E4: =B4-C4 -> 0 | F4: =E4/B4*100 -> 0 | G4: =VLOOKUP(A4,'Матрица поставщиков'!A1:E52,5,False) * B4 -> 4.872 | H4: =G4/G11 -> 0.16910736
A5: Сливочное масло | B5: 0.0001 | C5: =B5 -> 0.0001 | D5: г | E5: =B5-C5 -> 0 | F5: =E5/B5*100 -> 0 | G5: =VLOOKUP(A5,'Матрица поставщиков'!A2:E53,5,False) * B5 -> 9.9777778e-05 | H5: =G5/G11 -> 3.4632916e-06
A6: Томатная паста | B6: 160 | C6: =B6 -> 160 | D6: г | E6: =B6-C6 -> 0 | F6: =E6/B6*100 -> 0 | G6: =VLOOKUP(A6,'Матрица поставщиков'!A1:E53,5,False) * B6 -> 16.48 | H6: =G6/G11 -> 0.57202162
A7: Тимьян / Чабрец | B7: 6 | C7: =B7 -> 6 | D7: г | E7: =B7-C7 -> 0 | F7: =E7/B7*100 -> 0 | G7: =VLOOKUP(A7,'Матрица поставщиков'!A1:E57,5,False) * B7 -> 4.968 | H7: =G7/G11 -> 0.17243953
A8: Сахар | B8: 30 | C8: =B8 -> 30 | D8: г | E8: =B8-C8 -> 0 | F8: =E8/B8*100 -> 0 | G8: =VLOOKUP(A8,'Матрица поставщиков'!A1:E56,5,False) * B8 -> 2.07 | H8: =G8/G11 -> 0.071849803
A9: Соль | B9: 10 | C9: =B9 -> 10 | D9: г | E9: =B9-C9 -> 0 | F9: =E9/B9*100 -> 0 | G9: =VLOOKUP(A9,'Матрица поставщиков'!A1:E55,5,False) * B9 -> 0.42 | H9: =G9/G11 -> 0.014578221
A10: Вода | B10: 750 | C10: 700 | D10: мл | E10: =B10-C10 -> 50 | F10: =E10/B10*100 -> 6.6666667 | G10: 0 | H10: =G10/G11 -> 0
A11: Итого | B11: =SUM(B4:B10) -> 996.0001 | C11: =SUM(C4:C10) -> 946.0001 | D11: - | E11: =B11-C11 -> 50 | F11: =E11/B11*100 -> 5.0200798 | G11: =SUM(G4:G10) -> 28.8101 | H11: =SUM(H4:H10) -> 1 | I11: =B11-E11 -> 946.0001
A13: Технология приготовления
B15: выход | C15: с/с | D15: цена | E15: cost
B16: 50 | C16: =G11/I11*B16 -> 1.5227324 | D16: 50 | E16: =C16/D16 -> 0.030454648
B17: 1 | C17: =G11/I11*B17 -> 0.030454648 | D17: 1 | E17: =C17/D17 -> 0.030454648
B19: Для расчёта цены продажи
C20: % | D20: руб
B21: с/с блюда | C21: =D21/D24 -> 0.42491201 | D21: =C16 -> 1.5227324 | F21: cost (%) | G21: 15 | H21: 20 | I21: 25
B22: списания | C22: 0.04 | D22: =D21*C22 -> 0.060909295 | F22: price | G22: =D24*100/G21 -> 23.890945 | H22: =D24*100/H21 -> 17.918208 | I22: =D24*100/I21 -> 14.334567
B23: упаковка | C23: =D23/D24 -> 0.55809151 | D23: 2
B24: Итого с/с | D24: =SUM(D21:D23) -> 3.5836417
B26: цена | C26: 80
B27: cost общий | C27: =D24/C26 -> 0.044795521
B28: cost - продукции | C28: =D21/C26 -> 0.019034155

Sheet Манная халва
A1: Наименование ТТК: | B1: Манная халва
A3: Ингредиент | B3: Брутто | C3: Нетто | D3: Ед.изм. | E3: вес потери | F3: % потери | G3: с/с руб. | H3: с/с % | I3: Выход (мл.)
A4: п/ф Манная халва | B4: 150 | C4: 150 | D4: г. | E4: =B4-C4 -> 0 | F4: =E4/B4*100 -> 0 | G4: =B4*'пф Манная халва'!D23 -> 27.425819 | H4: =G4/G5 -> 1
A5: Итого | B5: =SUM(B4) -> 150 | C5: =SUM(C4) -> 150 | D5: г. | E5: =B5-C5 -> 0 | F5: =E5/B5*100 -> 0 | G5: =SUM(G4) -> 27.425819 | H5: =SUM(H4) -> 1 | I5: =C5 -> 150
A7: Технология приготовления
A8: Выложить в тару, подогреть в СВЧ. Подать
B9: выход | C9: с/с
B10: 150 | C10: =G5/I5*B10 -> 27.425819
B11: 1 | C11: =G5/I5*B11 -> 0.18283879
B13: Для расчёта цены продажи
C14: % | D14: руб
B15: с/с блюда | C15: =D15/D17 -> 0.53791072 | D15: =C10 -> 27.425819 | F15: cost (%) | G15: 10 | H15: 15 | I15: 20
B16: упаковка | C16: =D16/D17 -> 0.46208928 | D16: =I28 -> 23.56 | F16: price | G16: =D17*100/G15 -> 509.85819 | H16: =D17*100/H15 -> 339.90546 | I16: =D17*100/I15 -> 254.92909
B17: Итого с/с | D17: =sum(D15,D16) -> 50.985819
G18: на месте | H18: с собой | I18: доставка
F19: списания | G19: 2 | H19: 2 | I19: 2
B20: цена | C20: 250 | D20: =C20+I28 -> 273.56 | F20: салфетки 4 шт. | G20: 1.2 | H20: 1.2 | I20: 1.2
B21: cost общий | C21: =I30/C20 -> 0.20394327 | F21: зубочистка | G21: 0.34 | H21: 0.34 | I21: 0.34
B22: cost - продукции | C22: =D15/C20 -> 0.10970327 | F22: пакет | G22: 0 | H22: 2 | I22: 2
F23: наклейка брендированная | G23: 2.5 | H23: 2.5 | I23: 2.5
B24: цена | C24: 250 | F24: Супница | G24: 12.85 | H24: 12.85 | I24: 12.85
B25: доставка | C25: 350 | F25: Ложка с упаковкой | G25: 2.67 | H25: 2.67 | I25: 2.67
B26: маржа | C26: =C24-D17 -> 199.01418
G28: =SUM(G19:G27) -> 21.56 | H28: =SUM(H19:H27) -> 23.56 | I28: =SUM(I19:I27) -> 23.56
I30: =D15+I28 -> 50.985819

Sheet Сырный Дип
A1: Наименование ТТК: | B1: Сырный дип
A3: Ингредиент | B3: Брутто | C3: Нетто | D3: Ед.изм. | E3: вес потери | F3: % потери | G3: с/с руб. | H3: с/с % | I3: Выход (мл.)
A4: п/ф Сырный дип | B4: 50 | C4: 50 | D4: г. | E4: =B4-C4 -> 0 | F4: =E4/B4*100 -> 0 | G4: =B4*'пф Сырный дип'!C20 -> 32.911778 | H4: =G4/G5 -> 1
A5: Итого | B5: =SUM(B4) -> 50 | C5: =SUM(C4) -> 50 | D5: г. | E5: =B5-C5 -> 0 | F5: =E5/B5*100 -> 0 | G5: =SUM(G4) -> 32.911778 | H5: =SUM(H4) -> 1 | I5: =C5 -> 50
A7: Технология приготовления
A8: Расфасовать в соусники 80мл по 50 гр. , подогреть в СВЧ до 45 градусов. Подать
B9: выход | C9: с/с
B10: 50 | C10: =G5/I5*B10 -> 32.911778
B11: 1 | C11: =G5/I5*B11 -> 0.65823556
B13: Для расчёта цены продажи
C14: % | D14: руб
B15: с/с блюда | C15: =D15/D17 -> 0.87179412 | D15: =C10 -> 32.911778 | F15: cost (%) | G15: 10 | H15: 15 | I15: 20
B16: упаковка | C16: =D16/D17 -> 0.12820588 | D16: =I28 -> 4.84 | F16: price | G16: =D17*100/G15 -> 377.51778 | H16: =D17*100/H15 -> 251.67852 | I16: =D17*100/I15 -> 188.75889
B17: Итого с/с | D17: =sum(D15,D16) -> 37.751778
G18: на месте | H18: с собой | I18: доставка
F19: списания
B20: цена | C20: 130 | D20: =C20+I28 -> 134.84 | F20: салфетки 4 шт.
B21: cost общий | C21: =I30/C20 -> 0.29039829 | F21: зубочистка
B22: cost - продукции | C22: =D15/C20 -> 0.25316752 | F22: пакет
F23: наклейка брендированная | I23: 2.6
B24: цена | C24: =C20 -> 130 | G24: ка
B25: доставка | C25: =C24/70*100 -> 185.71429 | F25: Соусник | I25: 2.24
B26: маржа | C26: =C24-D17 -> 92.248222
G28: =SUM(G19:G27) -> 0 | H28: =SUM(H19:H27) -> 0 | I28: =SUM(I19:I27) -> 4.84
I30: =D15+I28 -> 37.751778

Sheet Шоколад Искенди
A1: Наименование ТТК: | B1: Шоколад Искенди
A3: Ингредиент | B3: Брутто | C3: Нетто | D3: Ед.изм. | E3: вес потери | F3: % потери | G3: с/с руб. | H3: с/с % | I3: Выход (мл.)
A4: п/ф Топинг шоколадный | B4: 100 | C4: 100 | D4: г. | E4: =B4-C4 -> 0 | F4: =E4/B4*100 -> 0 | G4: =B4*'пф Топинг шоколадный'!D23 -> 23.716567 | H4: =G4/$G$5 -> 1
A5: Итого | B5: =SUM(B4) -> 100 | C5: =SUM(C4) -> 100 | D5: г. | E5: =B5-C5 -> 0 | F5: =E5/B5*100 -> 0 | G5: =SUM(G4) -> 23.716567 | H5: =G5/$G$5 -> 1 | I5: 50
A7: Технология приготовления
B9: выход | C9: с/с
B10: 50 | C10: =C11*B10 -> 23.716567
B11: 1 | C11: =G5/I5*B11 -> 0.47433134
B13: Для расчёта цены продажи
C14: % | D14: руб
B15: с/с блюда | C15: =D15/D18 -> 0.79947357 | D15: =C10 -> 23.716567 | F15: cost (%) | G15: 10 | H15: 15 | I15: 20
B16: списания | C16: 0.04 | D16: =D15*C16 -> 0.94866269 | F16: price | G16: =D18*100/G15 -> 296.6523 | H16: =D18*100/H15 -> 197.7682 | I16: =D18*100/I15 -> 148.32615
B17: упаковка | C17: =D17/D18 -> 0.16854749 | D17: 5
B18: Итого с/с | D18: =SUM(D15:D17) -> 29.66523 | G18: на месте | H18: с собой | I18: доставка
F19: списания | G19: 2 | H19: 2 | I19: 2
B20: цена | C20: 85 | D20: =C20+I28 -> 97.61 | F20: салфетки 4 шт. | G20: 1.2 | H20: 1.2 | I20: 1.2
B21: cost общий | C21: =I30/C20 -> 0.42737138 | F21: зубочистка | G21: 0.34 | H21: 0.34 | I21: 0.34
B22: cost - продукции | C22: =D15/C20 -> 0.27901844 | F22: пакет | G22: 0 | H22: 2 | I22: 2
F23: наклейка брендированная | G23: 2.5 | H23: 2.5 | I23: 2.5
B24: цена | C24: 100 | F24: Соусник | G24: 1.9 | H24: 1.9 | I24: 1.9
B25: доставка | C25: 145 | F25: Ложка с упаковкой | G25: 2.67 | H25: 2.67 | I25: 2.67
G28: =SUM(G19:G27) -> 10.61 | H28: =SUM(H19:H27) -> 12.61 | I28: =SUM(I19:I27) -> 12.61
I30: =D15+I28 -> 36.326567

Sheet пф Топинг шоколадный
A1: Наименование ТТК: | B1: п/ф Топинг шоколадный
A3: Ингредиент | B3: Брутто | C3: Нетто | D3: Ед.изм. | E3: Объём потери | F3: % потери | G3: с/с руб. | H3: с/с % | I3: Выход (г.)
A4: Сгущенка | B4: 1000 | C4: 1000 | D4: г | E4: =B4-C4 -> 0 | F4: =E4/B4*100 -> 0 | G4: =VLOOKUP(A4,'Матрица поставщиков'!A1:E520,5,0) * B4 -> 130 | H4: =G4/$G$11 -> 0.32530566
A5: Какао-порошок | B5: 80 | C5: 80 | D5: г | E5: =B5-C5 -> 0 | F5: =E5/B5*100 -> 0 | G5: =VLOOKUP(A5,'Матрица поставщиков'!A2:E530,5,0) * B5 -> 90.378378 | H5: =G5/$G$11 -> 0.22615845
A6: Сливочное масло | B6: 100 | C6: 67 | D6: г | E6: =B6-C6 -> 33 | F6: =E6/B6*100 -> 33 | G6: =VLOOKUP(A6,'Матрица поставщиков'!A3:E54,5,0) * B6 -> 99.777778 | H6: =G6/$G$11 -> 0.24967905
A7: Ванилин | B7: 1 | C7: 1 | D7: г | E7: =B7-C7 -> 0 | F7: =E7/B7*100 -> 0 | G7: =VLOOKUP(A7,'Матрица поставщиков'!A4:E55,5,0) * B7 -> 2.3 | H7: =G7/$G$11 -> 0.0057554078
A8: корица | B8: 1 | C8: 1 | D8: г | E8: =B8-C8 -> 0 | F8: =E8/B8*100 -> 0 | G8: =VLOOKUP(A8,'Матрица поставщиков'!A1:E560,5,0) * B8 -> 1.34 | H8: =G8/$G$11 -> 0.0033531507
A9: Кардамон молотый | B9: 1 | C9: 1 | D9: г | E9: =B9-C9 -> 0 | F9: =E9/B9*100 -> 0 | G9: =VLOOKUP(A9,'Матрица поставщиков'!A1:E5780,5,0) * B9 -> 4.5 | H9: =G9/$G$11 -> 0.011260581
A10: п/ф тахини' | B10: 170 | C10: 170 | D10: г | E10: =B10-C10 -> 0 | F10: =E10/B10*100 -> 0 | G10: ='пф тахини'!M5*B10 -> 71.328 | H10: =G10/$G$11 -> 0.17848771
A11: Итого | B11: =SUM(B3:B10) -> 1353 | C11: =SUM(C3:C10) -> 1320 | D11: - | E11: =SUM(E4:E10) -> 33 | F11: =SUM(F4:F10) -> 33 | G11: =SUM(G4:G10) -> 399.62416 | H11: =SUM(H4:H10) -> 1 | I11: 1685
A13: Технология приготовления
A14: Приготовление: Смешать сухие ингредиенты. Постепенно добавляем в какао сгущённое молоко, постоянно помешивая. Используем миксер на низкой скорости. Добавляем тахини, мешаем дальше. Добавляем масло. Заранее растапливаем сливочное масло в микроволновке и вливаем в смесь. Перемешиваем до однородности. Охлаждаем и храним в холодильнике. Хранится в холодильнике до 1 месяца☝️
C16: выход | D16: с/с
C17: 100 | D17: =G11/I11*C17 -> 23.716567 | G17: 90гр | H17: 38.7
C18: 1000 | D18: =G11/I11*C18 -> 237.16567 | G18: прайс | H18: 150 | I18: ?
C21: выход | D21: с/с
C22: 100 | D22: =G11/I11*C22 -> 23.716567
C23: 1 | D23: =G11/I11*C23 -> 0.23716567

Sheet пф Манная халва
A1: Наименование ТТК: | B1: п/ф Манная халва
A3: Ингредиент | B3: Брутто | C3: Нетто | D3: Ед.изм. | E3: Объём потери | F3: % потери | G3: с/с руб. | H3: с/с % | I3: Выход (г.)
A4: Сливочное масло | B4: 200 | C4: 200 | D4: г | E4: =B4-C4 -> 0 | F4: =E4/B4*100 -> 0 | G4: =VLOOKUP(A4,'Матрица поставщиков'!A1:E520,5,0) * B4 -> 199.55556 | H4: =G4/$G$11 -> 0.64581597
A5: Манная крупа | B5: 400 | C5: 400 | D5: г | E5: =B5-C5 -> 0 | F5: =E5/B5*100 -> 0 | G5: =VLOOKUP(A5,'Матрица поставщиков'!A3:E54,5,0) * B5 -> 34.5 | H5: =G5/$G$11 -> 0.11165137
A6: Сахар | B6: 400 | C6: 400 | D6: г | E6: =B6-C6 -> 0 | F6: =E6/B6*100 -> 0 | G6: =VLOOKUP(A6,'Матрица поставщиков'!A4:E55,5,0) * B6 -> 27.6 | H6: =G6/$G$11 -> 0.089321095
A7: Вода | B7: 800 | C7: 600 | D7: г | E7: =B7-C7 -> 200 | F7: =E7/B7*100 -> 25 | G7: =VLOOKUP(A7,'Матрица поставщиков'!A1:E5780,5,0) * B7 -> 0 | H7: =G7/$G$11 -> 0
A8: Ванилин | B8: 1 | C8: 1 | D8: г | E8: =B8-C8 -> 0 | F8: =E8/B8*100 -> 0 | G8: =VLOOKUP(A8,'Матрица поставщиков'!A2:E5781,5,0) * B8 -> 2.3 | H8: =G8/$G$11 -> 0.0074434246
A9: Соль | B9: 1 | C9: 1 | D9: г | E9: =B9-C9 -> 0 | F9: =E9/B9*100 -> 0 | G9: =VLOOKUP(A9,'Матрица поставщиков'!A3:E5782,5,0) * B9 -> 0.042 | H9: =G9/$G$11 -> 0.00013592341
A10: Кардамон молотый | B10: 10 | C10: 10 | D10: г | E10: =B10-C10 -> 0 | F10: =E10/B10*100 -> 0 | G10: =VLOOKUP(A10,'Матрица поставщиков'!A4:E5783,5,0) * B10 -> 45 | H10: =G10/$G$11 -> 0.14563222
A11: Итого | B11: =SUM(B3:B8) -> 1801 | C11: =SUM(C3:C8) -> 1601 | D11: - | E11: =SUM(E4:E8) -> 200 | F11: =SUM(F4:F8) -> 25 | G11: =SUM(G4:G10) -> 308.99756 | H11: =SUM(H4:H8) -> 0.85423186 | I11: 1690
A13: Технология приготовления
A14: 1. Приготовьте сироп: Доведите до кипения воду на 2000вт. Добавьте сахар, воду, соль, ваниль кардамон (порошок). и варите 2 минуты на 500вт. Отставьте в сторону. 2. Обжарьте манку: В отдельной сковороде или кастрюле с толстым дном налейте растительное масло, затем в него добавьте сливочное масло и растопите. Добавьте манную крупу и обжаривайте на 1000вт, постоянно помешивая! пока она не станет золотисто-коричневой (примерно 8–10 минут) на 500-1000вт. Будьте внимательны — манка легко пригорает! 3.Соедините сироп и манку: Медленно, тонкой струйкой влейте горячий сироп в обжаренную манку, постоянно помешивая (будьте осторожны — смесь начинает бурлить и брызгать! Продолжайте варить около 3-4 минут 500вт, пока масса не загустеет и не начнёт отставать от стенок. Готово👌 Переложить в гастроемкость, пока не остыла!
C16: выход | D16: с/с
C17: 100 | D17: =G11/I11*C17 -> 18.283879
C18: 1000 | D18: =G11/I11*C18 -> 182.83879
C21: выход | D21: с/с
C22: 100 | D22: =G11/I11*C22 -> 18.283879
C23: 1 | D23: =G11/I11*C23 -> 0.18283879

Sheet пф Чечевичный суп
A1: Наименование блюда: | B1: Чечевичный суп
A3: Ингредиент | B3: Брутто | C3: Нетто | D3: Ед.изм. | E3: Объём потери | F3: % потери | G3: с/с руб. | H3: с/с % | I3: Выход (мл.)
A4: Чечевица красная | B4: 450 | C4: =B4 -> 450 | D4: г | E4: =B4-C4 -> 0 | F4: =E4/B4*100 -> 0 | G4: =VLOOKUP(A4,'Матрица поставщиков'!A1:E500,5,0) * B4 -> 100.62 | H4: =G4/$G$16 -> 0.43406119
A5: Лук репчатый | B5: 350 | C5: 350 | D5: г | E5: =B5-C5 -> 0 | F5: =E5/B5*100 -> 0 | G5: =VLOOKUP(A5,'Матрица поставщиков'!A2:E501,5,0) * B5 -> 19.95 | H5: =G5/$G$16 -> 0.086061625
A6: Морковь | B6: 350 | C6: 350 | D6: г | E6: =B6-C6 -> 0 | F6: =E6/B6*100 -> 0 | G6: =VLOOKUP(A6,'Матрица поставщиков'!A3:E502,5,0) * B6 -> 21 | H6: =G6/G16 -> 0.090591184
A7: Картофель | B7: 350 | C7: 350 | D7: г | E7: =B7-C7 -> 0 | F7: =E7/B7*100 -> 0 | G7: =VLOOKUP(A7,'Матрица поставщиков'!A4:E503,5,0) * B7 -> 17.15 | H7: =G7/$G$16 -> 0.0739828
A8: Томатная паста | B8: 50 | C8: =B8 -> 50 | D8: г | E8: =B8-C8 -> 0 | F8: =E8/B8*100 -> 0 | G8: =VLOOKUP(A8,'Матрица поставщиков'!A5:E504,5,0) * B8 -> 5.15 | H8: =G8/G16 -> 0.022216409
A9: п/ф специи для супа | B9: 50 | C9: 15 | D9: г | E9: =B9-C9 -> 35 | F9: =E9/B9*100 -> 70 | G9: =B9*'пф специи для супа'!D13 -> 47.363636 | H9: =G9/$G$16 -> 0.20432038
A10: Масло растительное | B10: 50 | C10: =B10 -> 50 | D10: г | E10: =B10-C10 -> 0 | F10: =E10/B10*100 -> 0 | G10: =VLOOKUP(A10,'Матрица поставщиков'!A7:E506,5,0) * B10 -> 6.09 | H10: =G10/$G$16 -> 0.026271443
A11: Соль | B11: 50 | C11: 50 | D11: г | E11: =B11-C11 -> 0 | F11: =E11/B11*100 -> 0 | G11: =VLOOKUP(A11,'Матрица поставщиков'!A1:E507,5,0) * B11 -> 2.1 | H11: =G11/$G$16 -> 0.0090591184
A12: Чёрный перец | B12: 1 | C12: 1 | D12: г | E12: =B12-C12 -> 0 | F12: =E12/B12*100 -> 0 | G12: =VLOOKUP(A12,'Матрица поставщиков'!A2:E508,5,0) * B12 -> 1.057 | H12: =G12/$G$16 -> 0.0045597563
A13: Сушёная мята | B13: 3 | C13: 3 | D13: г | E13: =B13-C13 -> 0 | F13: =E13/B13*100 -> 0 | G13: =VLOOKUP(A13,'Матрица поставщиков'!A1:E511,5,0) * B13 -> 5.65 | H13: =G13/$G$16 -> 0.024373342
A14: Лимонный сок | B14: 20 | C14: 10 | D14: г | E14: =B14-C14 -> 10 | F14: =E14/B14*100 -> 50 | G14: =VLOOKUP(A14,'Матрица поставщиков'!A7:E513,5,0) * B14 -> 5.68 | H14: =G14/$G$16 -> 0.024502758
A15: Вода | B15: 3000 | C15: 3000 | D15: г | E15: =B15-C15 -> 0 | F15: =E15/B15*100 -> 0 | G15: =VLOOKUP(A15,'Матрица поставщиков'!A1:E507,5,0) * B15 -> 0 | H15: =G15/$G$16 -> 0
A16: Итого | B16: =SUM(B4:B15) -> 4724 | C16: 4200 | D16: - | E16: =B16-C16 -> 524 | F16: - | G16: =SUM(G4:G15) -> 231.81064 | H16: =SUM(H4:H15) -> 1 | I16: 4000
C19: выход | D19: с/с
C20: 100 | D20: =G16/I16*C20 -> 5.7952659
C21: 1 | D21: =G16/I16*C21 -> 0.057952659
A23: Технология приготовления
A24: 1. Промойте чечевицу под холодной водой, пока вода не станет прозрачной. 2. Обжарьте овощи: В кастрюле разогрейте масло на 500вт. Нарежьте овощи на овощерезке кубиком или ножом произвольно. Добавьте лук и обжаривайте до прозрачности на 800-1000вт, чтобы не пригорал. Добавьте все овощи, кроме чечевицы, готовьте ещё 3–4 минуты, следите, чтобы не пригорало. Затем добавьте томатную пасту и тушите 2–3 минуты, чтобы ушла кислинка. 3. Добавьте чечевицу, специи и воду: Добавьте промытую чечевицу в кастрюлю, соль, сок лимона, все специи. Перемешайте. Залейте водой. Перемешайте. Доведите до кипения на 2000вт, далее снижаем до 500-800вт 4. Варите суп: Уменьшите огонь до 500-800вт, накройте кастрюлю крышкой и варите 30 минут, пока чечевица не станет мягкой и не начнёт развариваться. 5. Измельчите суп: Для более гладкой консистенции — взбейте суп блендером до однородности. Затем снова довести до кипения!

Sheet пф специи для супа
A1: Наименование блюда: | B1: п/ф специи для супа
A3: Ингредиент | B3: Брутто | C3: Нетто | D3: Ед.изм. | E3: Объём потери | F3: % потери | G3: с/с руб. | H3: с/с % | I3: Выход (мл.)
A4: Сухой чеснок | B4: 15 | C4: 15 | D4: г | E4: =B4-C4 -> 0 | F4: =E4/B4*100 -> 0 | G4: =VLOOKUP(A4,'Матрица поставщиков'!A6:E505,5,0) * B4 -> 20.113636 | H4: =G4/$G$8 -> 0.42466411
A5: Паприка | B5: 10 | C5: 10 | D5: г | E5: =B5-C5 -> 0 | F5: =E5/B5*100 -> 0 | G5: =VLOOKUP(A5,'Матрица поставщиков'!A3:E509,5,0) * B5 -> 6.7 | H5: =G5/$G$8 -> 0.14145873
A6: копченая паприка 1 | B6: 10 | C6: 10 | D6: г | E6: =B6-C6 -> 0 | F6: =E6/B6*100 -> 0 | G6: =VLOOKUP(A6,'Матрица поставщиков'!A4:E510,5,0) * B6 -> 7 | H6: =G6/$G$8 -> 0.14779271
A7: Зира (кумин) | B7: 15 | C7: 15 | D7: г | E7: =B7-C7 -> 0 | F7: =E7/B7*100 -> 0 | G7: =VLOOKUP(A7,'Матрица поставщиков'!A6:E512,5,0) * B7 -> 13.55 | H7: =G7/$G$8 -> 0.28608445
A8: Итого | B8: =SUM(B4:B7) -> 50 | C8: =SUM(C4:C7) -> 50 | D8: - | E8: =B8-C8 -> 0 | F8: - | G8: =SUM(G4:G7) -> 47.363636 | H8: =SUM(H4:H7) -> 1 | I8: =C8 -> 50
C11: выход | D11: с/с
C12: 100 | D12: =G8/I8*C12 -> 94.727273
C13: 1 | D13: =G8/I8*C13 -> 0.94727273
A15: Технология приготовления

Sheet пф Лимонная заправка
A1: Наименование блюда: | B1: Чечевичный суп
A3: Ингредиент | B3: Брутто | C3: Нетто | D3: Ед.изм. | E3: Объём потери | F3: % потери | G3: с/с руб. | H3: с/с % | I3: Выход (мл.)
A4: Лимонный сок | B4: 1000 | C4: =B4 -> 1000 | D4: г | E4: =B4-C4 -> 0 | F4: =E4/B4*100 -> 0 | G4: =VLOOKUP(A4,'Матрица поставщиков'!A1:E500,5,0) * B4 -> 284 | H4: =G4/$G$6 -> 0.96582214
A5: Паприка | B5: 15 | C5: 0 | D5: г | E5: =B5-C5 -> 15 | F5: =E5/B5*100 -> 100 | G5: =VLOOKUP(A5,'Матрица поставщиков'!A2:E501,5,0) * B5 -> 10.05 | H5: =G5/$G$6 -> 0.034177861
A6: Итого | B6: =SUM(B4:B5) -> 1015 | C6: =SUM(C4:C5) -> 1000 | D6: - | E6: =B6-C6 -> 15 | F6: - | G6: =SUM(G4:G5) -> 294.05 | H6: =SUM(H4:H5) -> 1 | I6: =C6 -> 1000
C9: выход | D9: с/с
C10: 100 | D10: =G6/I6*C10 -> 29.405
C11: 1 | D11: =G6/I6*C11 -> 0.29405
A13: Технология приготовления
A14: Перелейте 1 литр лимонного сока в соусник, добавьте 15гр паприки. Тщательно взболтайте.

Sheet пф Лаваш Искенди
A1: Наименование ТТК: | B1: п/ф Топинг шоколадный
A3: Ингредиент | B3: Брутто | C3: Нетто | D3: Ед.изм. | E3: Объём потери | F3: % потери | G3: с/с руб. | H3: с/с % | I3: Выход (шт)
A4: Лаваш | B4: 1 | C4: 1 | D4: шт | E4: =B4-C4 -> 0 | F4: =E4/B4*100 -> 0 | G4: =VLOOKUP(A4,'Матрица поставщиков'!A1:E520,5,0) * B4 -> 14.5 | H4: =G4/$G$6 -> 0.76966194
A5: п/ф искандер соус | B5: 120 | C5: 0 | D5: г | E5: =B5-C5 -> 120 | F5: =E5/B5*100 -> 100 | G5: ='пф искандер соус'!L11*B5 -> 4.33944 | H5: =G5/$G$6 -> 0.23033806
A6: Итого | B6: =SUM(B3:B5) -> 121 | C6: =SUM(C3:C5) -> 1 | D6: - | E6: =SUM(E4:E5) -> 120 | F6: =SUM(F4:F5) -> 100 | G6: =SUM(G4:G5) -> 18.83944 | H6: =SUM(H4:H5) -> 1 | I6: =B6-E6 -> 1
A8: Технология приготовления
A9: Приготовление: Смазать каждую сторону 60мл п/ф искандер соус 3. Поджарить каждый лаваш с двух сторон по 30 секунд на гриле при 225гр. Жареный лаваш сложить на пополам прямо на гриле и переложить в контейнер, не забыв его закрыть!
C11: выход | D11: с/с
C12: 100 | D12: =G6/I6*C12 -> 1883.944 | G12: 90гр | H12: 38.7
C13: 1000 | D13: =G6/I6*C13 -> 18839.44 | G13: прайс | H13: 150 | I13: ?
C16: выход | D16: с/с
C17: 100 | D17: =G6/I6*C17 -> 1883.944
C18: 1 | D18: =G6/I6*C18 -> 18.83944

Sheet пф тахини
A1: Наименование ТТК: | B1: п/ф Тахини
A3: Ингредиент | B3: Брутто | C3: Нетто | D3: Ед.изм. | E3: Объём потери | F3: % потери | G3: с/с руб. | H3: с/с % | I3: Выход (г.) | L3: выход | M3: с/с
A4: Кунжут | B4: 150 | C4: 150 | D4: г | E4: =B4-C4 -> 0 | F4: =E4/B4*100 -> 0 | G4: =VLOOKUP(A4,'Матрица поставщиков'!A1:E525,5,0) * B4 -> 68.85 | H4: =G4/$G$7 -> 0.96525908 | L4: 100 | M4: =G7/I7*L4 -> 41.957647
A5: Масло растительное | B5: 20 | C5: 20 | D5: г | E5: =B5-C5 -> 0 | F5: =E5/B5*100 -> 0 | G5: =VLOOKUP(A5,'Матрица поставщиков'!A2:E53,5,0) * B5 -> 2.436 | H5: =G5/$G$7 -> 0.034152086 | L5: 1 | M5: =G7/I7*L5 -> 0.41957647
A6: соль | B6: 1 | C6: 0 | D6: г | E6: =B6-C6 -> 1 | F6: =E6/B6*100 -> 100 | G6: =VLOOKUP(A6,'Матрица поставщиков'!A3:E54,5,0) * B6 -> 0.042 | H6: =G6/$G$7 -> 0.00058882907
A7: Итого | B7: =SUM(B3:B6) -> 171 | C7: =SUM(C3:C6) -> 170 | D7: - | E7: =SUM(E4:E6) -> 1 | F7: =SUM(F4:F6) -> 100 | G7: =SUM(G4:G6) -> 71.328 | H7: =SUM(H4:H6) -> 1 | I7: =B7-E7 -> 170
A9: Технология приготовления
A10: Приготовление: Подсушить кунжут (обязательно!): На сковороде на 500-800вт, слегка обжарить 3–5 минут, постоянно помешивая, пока он не станет ароматным и чуть золотистым. Это усилит вкус и поможет лучше измельчиться!!! Остудить кунжут градусов до 40 (горячий кунжут может выделить слишком много масла и стать горьким). Измельчаем в блендере: Засыпать кунжут в чашу. Включаем на максимум и мелим 1–2 минуты — сначала будет крошкой, потом начнёт комковаться☝️ Добавляем масло понемногу☝️ Продолжая взбивать, вливаем понемногу, пока масса не станет гладкой и кремовой. Добавляем соль. Продолжаем взбивать, пока паста не станет однородной и блестящей — это может занять 3–5 минут.
C12: выход | D12: с/с
C13: 100 | D13: =G7/I7*C13 -> 41.957647 | G13: 90гр | H13: 38.7
C14: 1000 | D14: =G7/I7*C14 -> 419.57647 | G14: прайс | H14: 150 | I14: ?

Sheet пф курица маринованная
A1: Наименование ТТК: | B1: п/ф курица маринованная
A3: Ингредиент | B3: Брутто | C3: Нетто | D3: Ед.изм. | E3: Объём потери | F3: % потери | G3: с/с руб. | H3: с/с % | I3: Выход (г.)
A4: Филе грудки куриное | B4: 1000 | C4: 950 | D4: г | E4: =B4-C4 -> 50 | F4: =E4/B4*100 -> 5 | G4: =VLOOKUP(A4,'Матрица поставщиков'!A1:E52,5,0) * B4 -> 339 | H4: =G4/$G$10 -> 0.92825287
A5: Масло растительное | B5: 40 | C5: 0 | D5: г | E5: =B5-C5 -> 40 | F5: =E5/B5*100 -> 100 | G5: =VLOOKUP(A5,'Матрица поставщиков'!A3:E54,5,0) * B5 -> 4.872 | H5: =G5/$G$10 -> 0.013340554
A6: п/ф специи для курицы | B6: 19 | C6: 0 | D6: г | E6: =B6-C6 -> 19 | F6: =E6/B6*100 -> 100 | G6: =B6*'пф специи для курицы'!D15 -> 17.475212 | H6: =G6/$G$10 -> 0.047850784
A7: Томатная паста | B7: 30 | C7: 0 | D7: г | E7: =B7-C7 -> 30 | F7: =E7/B7*100 -> 100 | G7: =VLOOKUP(A7,'Матрица поставщиков'!A8:E59,5,0) * B7 -> 3.09 | H7: =G7/$G$10 -> 0.0084610659
A8: Сахар | B8: 5 | C8: 0 | D8: г | E8: =B8-C8 -> 5 | F8: =E8/B8*100 -> 100 | G8: =VLOOKUP(A8,'Матрица поставщиков'!A10:E61,5,0) * B8 -> 0.345 | H8: =G8/$G$10 -> 0.00094468212
A9: Соль | B9: 10 | C9: 0 | D9: г | E9: =B9-C9 -> 10 | F9: =E9/B9*100 -> 100 | G9: =VLOOKUP(A9,'Матрица поставщиков'!A10:E61,5,0) * B9 -> 0.42 | H9: =G9/$G$10 -> 0.0011500478
A10: Итого | B10: =SUM(B3:B9) -> 1104 | C10: =SUM(C3:C9) -> 950 | D10: - | E10: =SUM(E4:E9) -> 154 | F10: =SUM(F4:F9) -> 505 | G10: =SUM(G4:G9) -> 365.20221 | H10: =SUM(H4:H9) -> 1 | I10: =B10-E10 -> 950
A12: Технология приготовления
A13: 1. Нарезать курицу 2. Добавить масло и томатную пасту 3. Добавить смесь специй, сахар и соль 4. Тщательно перемешать до однородного цвета. 5. Накрыть крышкой и оставь в холодильнике минимум на 1 час, лучше — на ночь (8–12 ч)
C15: выход | D15: с/с
C16: 100 | D16: =G10/I10*C16 -> 38.442338 | G16: 90гр | H16: 38.7
C17: 1000 | D17: =G10/I10*C17 -> 384.42338 | G17: прайс | H17: 150 | I17: ?

Sheet пф специи для курицы
A1: Наименование ТТК: | B1: п/ф специи для курицы
A3: Ингредиент | B3: Брутто | C3: Нетто | D3: Ед.изм. | E3: Объём потери | F3: % потери | G3: с/с руб. | H3: с/с % | I3: Выход (г.)
A4: Зира (кумин) | B4: 2 | C4: 2 | D4: г | E4: =B4-C4 -> 0 | F4: =E4/B4*100 -> 0 | G4: =VLOOKUP(A4,'Матрица поставщиков'!A4:E55,5,0) * B4 -> 1.8066667 | H4: =G4/$G$9 -> 0.10338453
A5: Паприка | B5: 5 | C5: 5 | D5: г | E5: =B5-C5 -> 0 | F5: =E5/B5*100 -> 0 | G5: =VLOOKUP(A5,'Матрица поставщиков'!A6:E57,5,0) * B5 -> 3.35 | H5: =G5/$G$9 -> 0.19170011
A6: Сухой чеснок | B6: 5 | C6: 5 | D6: г | E6: =B6-C6 -> 0 | F6: =E6/B6*100 -> 0 | G6: =VLOOKUP(A6,'Матрица поставщиков'!A7:E58,5,0) * B6 -> 6.7045455 | H6: =G6/$G$9 -> 0.38366032
A7: Чёрный перец | B7: 2 | C7: 2 | D7: г | E7: =B7-C7 -> 0 | F7: =E7/B7*100 -> 0 | G7: =VLOOKUP(A7,'Матрица поставщиков'!A9:E60,5,0) * B7 -> 2.114 | H7: =G7/$G$9 -> 0.12097135
A8: копченая паприка 1 | B8: 5 | C8: 5 | D8: г | E8: =B8-C8 -> 0 | F8: =E8/B8*100 -> 0 | G8: =VLOOKUP(A8,'Матрица поставщиков'!A11:E62,5,0) * B8 -> 3.5 | H8: =G8/$G$9 -> 0.20028369
A9: Итого | B9: =SUM(B3:B8) -> 19 | C9: =SUM(C3:C8) -> 19 | D9: - | E9: =SUM(E4:E8) -> 0 | F9: =SUM(F4:F8) -> 0 | G9: =SUM(G4:G8) -> 17.475212 | H9: =SUM(H4:H8) -> 1 | I9: =B9-E9 -> 19
A11: Технология приготовления
A12: Добавлять в курицу в расчете 19гр смеси специй на 1 кг курицы
C14: выход | D14: с/с
C15: 1 | D15: =G9/I9*C15 -> 0.91974801 | G15: 90гр | H15: 38.7
C16: 100 | D16: =G9/I9*C16 -> 91.974801 | G16: прайс | H16: 150 | I16: ?

Sheet пф специи балык
A1: Наименование ТТК: | B1: п/ф специи балык
A3: Ингредиент | B3: Брутто | C3: Нетто | D3: Ед.изм. | E3: Объём потери | F3: % потери | G3: с/с руб. | H3: с/с % | I3: Выход (г.)
A4: Зира (кумин) | B4: 60 | C4: 60 | D4: г | E4: =B4-C4 -> 0 | F4: =E4/B4*100 -> 0 | G4: =VLOOKUP(A4,'Матрица поставщиков'!A4:E55,5,0) * B4 -> 54.2 | H4: =G4/$G$10 -> 0.22442135
A5: копченая паприка 1 | B5: 60 | C5: 60 | D5: г | E5: =B5-C5 -> 0 | F5: =E5/B5*100 -> 0 | G5: =VLOOKUP(A5,'Матрица поставщиков'!A6:E57,5,0) * B5 -> 42 | H5: =G5/$G$10 -> 0.17390584
A6: Сумах | B6: 50 | C6: 50 | D6: г | E6: =B6-C6 -> 0 | F6: =E6/B6*100 -> 0 | G6: =VLOOKUP(A6,'Матрица поставщиков'!A7:E58,5,0) * B6 -> 57.5 | H6: =G6/$G$10 -> 0.23808538
A7: Чёрный перец | B7: 30 | C7: 30 | D7: г | E7: =B7-C7 -> 0 | F7: =E7/B7*100 -> 0 | G7: =VLOOKUP(A7,'Матрица поставщиков'!A9:E600,5,0) * B7 -> 31.71 | H7: =G7/$G$10 -> 0.13129891
A8: Орегано | B8: 15 | C8: 15 | D8: г | E8: =B8-C8 -> 0 | F8: =E8/B8*100 -> 0 | G8: =VLOOKUP(A8,'Матрица поставщиков'!A11:E620,5,0) * B8 -> 20.4 | H8: =G8/$G$10 -> 0.084468552
A9: Исот | B9: 30 | C9: 30 | D9: г | E9: =B9-C9 -> 0 | F9: =E9/B9*100 -> 0 | G9: =VLOOKUP(A9,'Матрица поставщиков'!A12:E621,5,0) * B9 -> 35.7 | H9: =G9/$G$10 -> 0.14781997
A10: Итого | B10: =SUM(B3:B8) -> 215 | C10: =SUM(C3:C8) -> 215 | D10: - | E10: =SUM(E4:E8) -> 0 | F10: =SUM(F4:F8) -> 0 | G10: =SUM(G4:G9) -> 241.51 | H10: =SUM(H4:H9) -> 1 | I10: =B10-E10 -> 215
A12: Технология приготовления
A13: Смешать
C15: выход | D15: с/с
C16: 1 | D16: =G10/I10*C16 -> 1.1233023 | G16: 90гр | H16: 38.7
C17: 100 | D17: =G10/I10*C17 -> 112.33023 | G17: прайс | H17: 150 | I17: ?

Sheet пф Соус Кебаб
A1: Наименование ТТК: | B1: п/ф Соус Кебаб
A3: Ингредиент | B3: Брутто | C3: Нетто | D3: Ед.изм. | E3: Объём потери | F3: % потери | G3: с/с руб. | H3: с/с % | I3: Выход (г.)
A4: Томатная паста | B4: 400 | C4: 400 | D4: г | E4: =B4-C4 -> 0 | F4: =E4/B4*100 -> 0 | G4: =VLOOKUP(A4,'Матрица поставщиков'!A1:E52,5,0) * B4 -> 41.2 | H4: =G4/$G$13 -> 0.76580422
A5: Вода | B5: 200 | C5: 200 | D5: г | E5: =B5-C5 -> 0 | F5: =E5/B5*100 -> 0 | G5: =VLOOKUP(A5,'Матрица поставщиков'!A2:E53,5,0) * B5 -> 0 | H5: =G5/$G$13 -> 0
A6: Лимонный сок | B6: 10 | C6: 10 | D6: г | E6: =B6-C6 -> 0 | F6: =E6/B6*100 -> 0 | G6: =VLOOKUP(A6,'Матрица поставщиков'!A3:E54,5,0) * B6 -> 2.84 | H6: =G6/$G$13 -> 0.052788446
A7: Хмели Сунели | B7: 10 | C7: 10 | D7: г | E7: =B7-C7 -> 0 | F7: =E7/B7*100 -> 0 | G7: =VLOOKUP(A7,'Матрица поставщиков'!A4:E550,5,0) * B7 -> 2.72 | H7: =G7/$G$13 -> 0.050557948
A8: Сухой чеснок | B8: 2 | C8: 2 | D8: г | E8: =B8-C8 -> 0 | F8: =E8/B8*100 -> 0 | G8: =VLOOKUP(A8,'Матрица поставщиков'!A7:E58,5,0) * B8 -> 2.6818182 | H8: =G8/$G$13 -> 0.049848244
A9: Чёрный перец | B9: 1 | C9: 1 | D9: г | E9: =B9-C9 -> 0 | F9: =E9/B9*100 -> 0 | G9: =VLOOKUP(A9,'Матрица поставщиков'!A9:E60,5,0) * B9 -> 1.057 | H9: =G9/$G$13 -> 0.019646967
A10: Сахар | B10: 10 | C10: 10 | D10: г | E10: =B10-C10 -> 0 | F10: =E10/B10*100 -> 0 | G10: =VLOOKUP(A10,'Матрица поставщиков'!A10:E61,5,0) * B10 -> 0.69 | H10: =G10/$G$13 -> 0.012825362
A11: Соль | B11: 7.5 | C11: 7.5 | D11: г | E11: =B11-C11 -> 0 | F11: =E11/B11*100 -> 0 | G11: =VLOOKUP(A11,'Матрица поставщиков'!A10:E61,5,0) * B11 -> 0.315 | H11: =G11/$G$13 -> 0.0058550565
A12: Лук гранулированный | B12: 2 | C12: 2 | D12: г | E12: =B12-C12 -> 0 | F12: =E12/B12*100 -> 0 | G12: =VLOOKUP(A12,'Матрица поставщиков'!A11:E620,5,0) * B12 -> 2.2958333 | H12: =G12/$G$13 -> 0.042673758
A13: Итого | B13: =SUM(B3:B12) -> 642.5 | C13: =SUM(C3:C12) -> 642.5 | D13: - | E13: =SUM(E4:E12) -> 0 | F13: =SUM(F4:F12) -> 0 | G13: =SUM(G4:G12) -> 53.799652 | H13: =SUM(H4:H12) -> 1 | I13: =B13-E13 -> 642.5
A15: Технология приготовления
A16: В небольшую гастроемкость выложить томатную пасту. Постепенно влить воду, постоянно помешивая, чтобы не было комочков. Добавить все специи, соль, сахар и лимонный сок. Хорошо всё перемешать ложкой или миксером с венчиком. Дать настояться в холодильнике не менее 30 минут❗️
C18: выход | D18: с/с
C19: 100 | D19: =G13/I13*C19 -> 8.3734866
C20: 1000 | D20: =G13/I13*C20 -> 83.734866
C21: 1 | D21: =G13/I13*C21 -> 0.083734866

Sheet пф Лук маринованный
A1: Наименование ТТК: | B1: п/ф Лук маринованный
A3: Ингредиент | B3: Брутто | C3: Нетто | D3: Ед.изм. | E3: Объём потери | F3: % потери | G3: с/с руб. | H3: с/с % | I3: Выход (г.)
A4: Лук репчатый | B4: 350 | C4: 300 | D4: г | E4: =B4-C4 -> 50 | F4: =E4/B4*100 -> 14.285714 | G4: =VLOOKUP(A4,'Матрица поставщиков'!A1:E52,5,0) * B4 -> 19.95 | H4: =G4/$G$10 -> 0.49205801
A5: Уксус яблочный | B5: 30 | C5: 0 | D5: г | E5: =B5-C5 -> 30 | F5: =E5/B5*100 -> 100 | G5: =VLOOKUP(A5,'Матрица поставщиков'!A2:E53,5,0) * B5 -> 6.96 | H5: =G5/$G$10 -> 0.17166535
A6: Сумах | B6: 10 | C6: 0 | D6: г | E6: =B6-C6 -> 10 | F6: =E6/B6*100 -> 100 | G6: =VLOOKUP(A6,'Матрица поставщиков'!A7:E58,5,0) * B6 -> 11.5 | H6: =G6/$G$10 -> 0.28364246
A7: Чёрный перец | B7: 1 | C7: 0 | D7: г | E7: =B7-C7 -> 1 | F7: =E7/B7*100 -> 100 | G7: =VLOOKUP(A7,'Матрица поставщиков'!A9:E60,5,0) * B7 -> 1.057 | H7: =G7/$G$10 -> 0.026070442
A8: Сахар | B8: 15 | C8: 0 | D8: г | E8: =B8-C8 -> 15 | F8: =E8/B8*100 -> 100 | G8: =VLOOKUP(A8,'Матрица поставщиков'!A10:E61,5,0) * B8 -> 1.035 | H8: =G8/$G$10 -> 0.025527822
A9: Соль | B9: 1 | C9: 0 | D9: г | E9: =B9-C9 -> 1 | F9: =E9/B9*100 -> 100 | G9: =VLOOKUP(A9,'Матрица поставщиков'!A10:E61,5,0) * B9 -> 0.042 | H9: =G9/$G$10 -> 0.0010359116
A10: Итого | B10: =SUM(B3:B9) -> 407 | C10: =SUM(C3:C9) -> 300 | D10: - | E10: =SUM(E4:E9) -> 107 | F10: =SUM(F4:F9) -> 514.28571 | G10: =SUM(G4:G9) -> 40.544 | H10: =SUM(H4:H9) -> 1 | I10: =B10-E10 -> 300
A12: Технология приготовления
A13: Лук нарезать полукольцами. Смешать с со специями и уксусом. Дать настояться в холодильнике
C15: выход | D15: с/с
C16: 100 | D16: =G10/I10*C16 -> 13.514667 | G16: 90гр | H16: 38.7
C17: 1000 | D17: =G10/I10*C17 -> 135.14667 | G17: прайс | H17: 150 | I17: ?
C18: 1 | D18: =G10/I10*C18 -> 0.13514667

Sheet пф Лук - сумах
A1: Наименование ТТК: | B1: п/ф Лук - сумах
A3: Ингредиент | B3: Брутто | C3: Нетто | D3: Ед.изм. | E3: Объём потери | F3: % потери | G3: с/с руб. | H3: с/с % | I3: Выход (г.)
A4: Лук репчатый | B4: 350 | C4: 300 | D4: г | E4: =B4-C4 -> 50 | F4: =E4/B4*100 -> 14.285714 | G4: =VLOOKUP(A4,'Матрица поставщиков'!A1:E52,5,0) * B4 -> 19.95 | H4: =G4/$G$9 -> 0.48602821
A5: Лимонный сок | B5: 30 | C5: 0 | D5: г | E5: =B5-C5 -> 30 | F5: =E5/B5*100 -> 100 | G5: =VLOOKUP(A5,'Матрица поставщиков'!A2:E53,5,0) * B5 -> 8.52 | H5: =G5/$G$9 -> 0.20756694
A6: Сумах | B6: 10 | C6: 0 | D6: г | E6: =B6-C6 -> 10 | F6: =E6/B6*100 -> 100 | G6: =VLOOKUP(A6,'Матрица поставщиков'!A7:E58,5,0) * B6 -> 11.5 | H6: =G6/$G$9 -> 0.28016664
A7: Сахар | B7: 15 | C7: 0 | D7: г | E7: =B7-C7 -> 15 | F7: =E7/B7*100 -> 100 | G7: =VLOOKUP(A7,'Матрица поставщиков'!A10:E61,5,0) * B7 -> 1.035 | H7: =G7/$G$9 -> 0.025214997
A8: Соль | B8: 1 | C8: 0 | D8: г | E8: =B8-C8 -> 1 | F8: =E8/B8*100 -> 100 | G8: =VLOOKUP(A8,'Матрица поставщиков'!A10:E61,5,0) * B8 -> 0.042 | H8: =G8/$G$9 -> 0.0010232173
A9: Итого | B9: =SUM(B3:B8) -> 406 | C9: =SUM(C3:C8) -> 300 | D9: - | E9: =SUM(E4:E8) -> 106 | F9: =SUM(F4:F8) -> 414.28571 | G9: =SUM(G4:G8) -> 41.047 | H9: =SUM(H4:H8) -> 1 | I9: =B9-E9 -> 300
A11: Технология приготовления
A12: Лук нарезать перьями. Смешать с со специями и уксусом. Дать настояться в холодильнике
C14: выход | D14: с/с
C15: 100 | D15: =G9/I9*C15 -> 13.682333 | G15: 90гр | H15: 38.7
C16: 1000 | D16: =G9/I9*C16 -> 136.82333 | G16: прайс | H16: 150 | I16: ?
C17: 1 | D17: =G9/I9*C17 -> 0.13682333

Sheet пф Фарш Primebeef Классик марин
A1: Наименование ТТК: | B1: п/ф Фарш Primebeef Классик говяжий охлажденный
A3: Ингредиент | B3: Брутто | C3: Нетто | D3: Ед.изм. | E3: Объём потери | F3: % потери | G3: с/с руб. | H3: с/с % | I3: Выход (г.)
A4: Фарш Primebeef Классик говяжий охлажденный | B4: 2000 | C4: 1950 | D4: г | E4: =B4-C4 -> 50 | F4: =E4/B4*100 -> 2.5 | G4: =VLOOKUP(A4,'Матрица поставщиков'!A1:E52,5,0) * B4 -> 1679 | H4: =G4/$G$11 -> 0.99460908
A5: Лук гранулированный | B5: 2 | C5: 0 | D5: г | E5: =B5-C5 -> 2 | F5: =E5/B5*100 -> 100 | G5: =VLOOKUP(A5,'Матрица поставщиков'!A3:E545,5,0) * B5 -> 2.2958333 | H5: =G5/$G$11 -> 0.0013600099
A6: Зира (кумин) | B6: 2 | C6: 0 | D6: г | E6: =B6-C6 -> 2 | F6: =E6/B6*100 -> 100 | G6: =VLOOKUP(A6,'Матрица поставщиков'!A4:E55,5,0) * B6 -> 1.8066667 | H6: =G6/$G$11 -> 0.0010702365
A7: Паприка | B7: 2 | C7: 0 | D7: г | E7: =B7-C7 -> 2 | F7: =E7/B7*100 -> 100 | G7: =VLOOKUP(A7,'Матрица поставщиков'!A6:E57,5,0) * B7 -> 1.34 | H7: =G7/$G$11 -> 0.00079379164
A8: Сухой чеснок | B8: 1 | C8: 0 | D8: г | E8: =B8-C8 -> 1 | F8: =E8/B8*100 -> 100 | G8: =VLOOKUP(A8,'Матрица поставщиков'!A7:E58,5,0) * B8 -> 1.3409091 | H8: =G8/$G$11 -> 0.00079433017
A9: Чёрный перец | B9: 1 | C9: 0 | D9: г | E9: =B9-C9 -> 1 | F9: =E9/B9*100 -> 100 | G9: =VLOOKUP(A9,'Матрица поставщиков'!A9:E60,5,0) * B9 -> 1.057 | H9: =G9/$G$11 -> 0.00062614759
A10: Соль | B10: 30 | C10: 0 | D10: г | E10: =B10-C10 -> 30 | F10: =E10/B10*100 -> 100 | G10: =VLOOKUP(A10,'Матрица поставщиков'!A10:E61,5,0) * B10 -> 1.26 | H10: =G10/$G$11 -> 0.0007464011
A11: Итого | B11: =SUM(B3:B10) -> 2038 | C11: =SUM(C3:C10) -> 1950 | D11: - | E11: =SUM(E4:E10) -> 88 | F11: =SUM(F4:F10) -> 602.5 | G11: =SUM(G4:G10) -> 1688.1004 | H11: =SUM(H4:H10) -> 1 | I11: =B11-E11 -> 1950
A13: Технология приготовления
A14: Приготовление: смешать в большой миске: говяжий фарш, специи все. Вымешивать фарш не менее 5–7 минут — до тех пор, пока он не станет липким и эластичным. Это важно: так кебабы не развалятся при жарке!!! Охладить фарш в холодильнике (дать помариноваться) не менее 60 минут — это улучшит структуру и облегчит формовку.
C16: выход | D16: с/с
C17: 165 | D17: =G11/I11*C17 -> 142.83927
C18: 1000 | D18: =G11/I11*C18 -> 865.69252
C19: 1 | D19: =G11/I11*C19 -> 0.86569252

Sheet пф Фарш Primebeef Классик жарен
A1: Наименование ТТК: | B1: п/ф Фарш Primebeef Классик говяжий охлажденный
A3: Ингредиент | B3: Брутто | C3: Нетто | D3: Ед.изм. | E3: Объём потери | F3: % потери | G3: с/с руб. | H3: с/с % | I3: Выход (г.)
A4: п/ф Фарш Primebeef Классик маринованный | B4: 1950 | C4: 1170 | D4: г | E4: =B4-C4 -> 780 | F4: =E4/B4*100 -> 40 | G4: ='пф Фарш Primebeef Классик марин'!D19 * B4 -> 1688.1004 | H4: =G4/$G$6 -> 0.98911916
A5: Курдюк | B5: 30 | C5: 0 | D5: г | E5: =B5-C5 -> 30 | F5: =E5/B5*100 -> 100 | G5: =VLOOKUP(A5,'Матрица поставщиков'!A11:E602,5,0) * B5 -> 18.57 | H5: =G5/$G$6 -> 0.010880836
A6: Итого | B6: =SUM(B3:B5) -> 1980 | C6: =SUM(C3:C5) -> 1170 | D6: - | E6: =SUM(E4:E5) -> 810 | F6: =SUM(F4:F5) -> 140 | G6: =SUM(G4:G5) -> 1706.6704 | H6: =SUM(H4:H5) -> 1 | I6: =B6-E6 -> 1170
A8: Технология приготовления
A9: Жарка: Сформируйте кебабы в форме для кебаба, взяв 150 грамм готового фарша. Жарьте на гриле 250° градусов по 3 минуты, с каждой стороны.
C11: выход | D11: с/с
C12: 100 | D12: =G6/I6*C12 -> 145.86927
C13: 1000 | D13: =G6/I6*C13 -> 1458.6927
C14: 1 | D14: =G6/I6*C14 -> 1.4586927

Sheet пф Фри
A1: Наименование ТТК: | B1: фри
A3: Ингредиент | B3: Брутто | C3: Нетто | D3: Ед.изм. | E3: вес потери | F3: % потери | G3: с/с руб. | H3: с/с % | I3: Выход (мл.) | K3: выход | L3: с/с
A4: Стейкхаус Фри | B4: 1000 | C4: 800 | D4: г. | E4: =B4-C4 -> 200 | F4: =E4/B4*100 -> 20 | G4: =VLOOKUP(A4,'Матрица поставщиков'!A1:E520,5,False) * B4 -> 254.4 | H4: =G4/G7 -> 0.99834457 | K4: 100 | L4: =G7/I7*K4 -> 31.85273
A5: Масло фритюрное | B5: 0.1 | C5: 0.1 | D5: г. | E5: =B5-C5 -> 0 | F5: =E5/B5*100 -> 0 | G5: =(VLOOKUP(A5,'Матрица поставщиков'!A1:E53,5,False) * B5)/10 -> 0.00184 | H5: =G5/G7 -> 7.2207312e-06 | K5: 1 | L5: =G7/I7*K5 -> 0.3185273
A6: Соль | B6: 10 | C6: 10 | D6: г. | E6: =B6-C6 -> 0 | F6: =E6/B6*100 -> 0 | G6: =VLOOKUP(A6,'Матрица поставщиков'!A1:E57,5,False) * B6 -> 0.42 | H6: =G6/G7 -> 0.0016482104
A7: Итого | B7: =B4 -> 1000 | C7: =C4 -> 800 | D7: - | E7: =B7-C7 -> 200 | F7: =E7/B7*100 -> 20 | G7: =SUM(G4:G6) -> 254.82184 | H7: =SUM(H4:H6) -> 1 | I7: =B7-E7 -> 800
A9: Технология приготовления
A10: Жарить во фритюре 3 мин. 15 сек. Добавить соль кивком руки. 1 кивок на 150гр

Sheet пф Фри в панировке
A1: Наименование ТТК: | B1: фри
A3: Ингредиент | B3: Брутто | C3: Нетто | D3: Ед.изм. | E3: вес потери | F3: % потери | G3: с/с руб. | H3: с/с % | I3: Выход (мл.) | K3: выход | L3: с/с
A4: Фри в панировке | B4: 1000 | C4: 665 | D4: г. | E4: =B4-C4 -> 335 | F4: =E4/B4*100 -> 33.5 | G4: =VLOOKUP(A4,'Матрица поставщиков'!A1:E520,5,False) * B4 -> 199.6 | H4: =G4/G7 -> 0.99789103 | K4: 100 | L4: =G7/I7*K4 -> 30.078472
A5: Масло фритюрное | B5: 0.1 | C5: 0.1 | D5: г. | E5: =B5-C5 -> 0 | F5: =E5/B5*100 -> 0 | G5: =(VLOOKUP(A5,'Матрица поставщиков'!A1:E53,5,False) * B5)/10 -> 0.00184 | H5: =G5/G7 -> 9.1989955e-06 | K5: 1 | L5: =G7/I7*K5 -> 0.30078472
A6: Соль | B6: 10 | C6: 10 | D6: г. | E6: =B6-C6 -> 0 | F6: =E6/B6*100 -> 0 | G6: =VLOOKUP(A6,'Матрица поставщиков'!A1:E57,5,False) * B6 -> 0.42 | H6: =G6/G7 -> 0.0020997707
A7: Итого | B7: =B4 -> 1000 | C7: =C4 -> 665 | D7: - | E7: =B7-C7 -> 335 | F7: =E7/B7*100 -> 33.5 | G7: =SUM(G4:G6) -> 200.02184 | H7: =SUM(H4:H6) -> 1 | I7: =B7-E7 -> 665
A9: Технология приготовления
A10: Жарить во фритюре 3 мин. 15 сек. Добавить соль кивком руки. 1 кивок на 150гр

Sheet пф искандер соус
A1: Наименование ТТК: | B1: п/ф искандер соус
A3: Ингредиент | B3: Брутто | C3: Нетто | D3: Ед.изм. | E3: вес потери | F3: % потери | G3: с/с руб. | H3: с/с % | I3: Выход (мл.)
A4: Масло растительное | B4: 300 | C4: =B4 -> 300 | D4: г | E4: =B4-C4 -> 0 | F4: =E4/B4*100 -> 0 | G4: =VLOOKUP(A4,'Матрица поставщиков'!A2:E53,5,False) * B4 -> 36.54 | H4: =G4/G11 -> 0.1010453
A5: Томатная паста | B5: 2400 | C5: 200 | D5: г | E5: =B5-C5 -> 2200 | F5: =E5/B5*100 -> 91.666667 | G5: =VLOOKUP(A5,'Матрица поставщиков'!A1:E53,5,False) * B5 -> 247.2 | H5: =G5/G11 -> 0.68359051
A6: Тимьян / Чабрец | B6: 70 | C6: =B6 -> 70 | D6: г | E6: =B6-C6 -> 0 | F6: =E6/B6*100 -> 0 | G6: =VLOOKUP(A6,'Матрица поставщиков'!A1:E57,5,False) * B6 -> 57.96 | H6: =G6/G11 -> 0.16027875
A7: Сахар | B7: 240 | C7: 50 | D7: г | E7: =B7-C7 -> 190 | F7: =E7/B7*100 -> 79.166667 | G7: =VLOOKUP(A7,'Матрица поставщиков'!A1:E56,5,False) * B7 -> 16.56 | H7: =G7/G11 -> 0.045793927
A8: Соль | B8: 80 | C8: 10 | D8: г | E8: =B8-C8 -> 70 | F8: =E8/B8*100 -> 87.5 | G8: =VLOOKUP(A8,'Матрица поставщиков'!A1:E55,5,False) * B8 -> 3.36 | H8: =G8/G11 -> 0.0092915215 | K8: выход | L8: с/с | M8: цена | N8: cost
A9: Вода | B9: 7500 | C9: 3310 | D9: мл | E9: =B9-C9 -> 4190 | F9: =E9/B9*100 -> 55.866667 | G9: =VLOOKUP(A9,'Матрица поставщиков'!A2:E56,5,False) * B9 -> 0 | H9: =G9/G11 -> 0 | K9: 50 | L9: =G11/I11*K9 -> 1.8081 | M9: 50 | N9: =L9/M9 -> 0.036162
A10: Сухой чеснок | B10: 4 | C10: 0 | D10: г | E10: =B10-C10 -> 4 | F10: =E10/B10*100 -> 100 | G10: =VLOOKUP(A10,'Матрица поставщиков'!A3:E57,5,False) * B10 -> 5.3636364 | H10: =G10/G11 -> 0.014832245
A11: Итого | B11: =SUM(B4:B10) -> 10594 | C11: =SUM(C4:C10) -> 3940 | D11: - | E11: =B11-C11 -> 6654 | F11: =E11/B11*100 -> 62.809137 | G11: =SUM(G4:G9) -> 361.62 | H11: =SUM(H4:H9) -> 1 | I11: 10000 | K11: 1 | L11: =G11/I11*K11 -> 0.036162 | M11: 1 | N11: =L11/M11 -> 0.036162
A13: Технология приготовления
A14: 1. Разогреть 2.5л воды в гастроемкости на индукционной плите на 2квт до легкого кипения, добавив смесь соли и сахара, помешивая до растворения их. Отставить в сторону на пробковую подставку. 2. Добавить в кастрюлю масло и томатную пасту нужных граммовок. 3. Начать пробивать погружным блендером viatto пасту с маслом до однородной смеси. 4. Ставим кастрюлю на плиту на 1.8квт, продолжаем пробивать водя ножкой блендера по дну кастрюли по кругу, не забываю про центр, там может сильнее пригорать 5мин. Добавляем тимьян с чесноком, пробиваем 1 мин. Добавляем 2.5л нагретой воды, пробиваем 2 мин. Добавляем 5л воды, пробиваем 2 минуты. Устанавливаем мощность 2квт, доводим до кипения. После закипания устанавливаем 500вт на 10 мин и закрываем крышкой. 7. Перелить соус в гастроёмкость 8. Наклеить маркировку

Sheet пф говядина маринованная
A1: Наименование ТТК: | B1: п/ф мясо маринованное
A3: Ингредиент | B3: Брутто | C3: Нетто | D3: Ед.изм. | E3: Объём потери | F3: % потери | G3: с/с руб. | H3: с/с % | I3: Выход (г.) | K3: выход | L3: с/с
A4: Говядина - лопатка | B4: 1000 | C4: 800 | D4: г | E4: =B4-C4 -> 200 | F4: =E4/B4*100 -> 20 | G4: =VLOOKUP(A4,'Матрица поставщиков'!A1:E53,5,0) * B4 -> #N/A | H4: =G4/$G$17 -> #N/A | K4: 100 | L4: =G17/I17*K4 -> #N/A
A5: Лук | B5: 170 | C5: 140 | D5: г | E5: =B5-C5 -> 30 | F5: =E5/B5*100 -> 17.647059 | G5: =VLOOKUP(A5,'Матрица поставщиков'!A1:E52,5,0) * B5 -> #N/A | H5: =G5/$G$17 -> #N/A | K5: 1000 | L5: =G17/I17*K5 -> #N/A
A6: Чеснок | B6: 17 | C6: 15 | D6: мл | E6: =B6-C6 -> 2 | F6: =E6/B6*100 -> 11.764706 | G6: =VLOOKUP(A6,'Матрица поставщиков'!A1:E55,5,0) * B6 -> 3.672 | H6: =G6/$G$17 -> #N/A
A7: Йогурт турецкий | B7: 70 | C7: 50 | D7: мл | E7: =B7-C7 -> 20 | F7: =E7/B7*100 -> 28.571429 | G7: =VLOOKUP(A7,'Матрица поставщиков'!A1:E57,5,False) * B7 -> 20.23 | H7: =G7/$G$17 -> #N/A
A8: Оливковое масло | B8: 50 | C8: 50 | D8: г | E8: =B8-C8 -> 0 | F8: =E8/B8*100 -> 0 | G8: =VLOOKUP(A8,'Матрица поставщиков'!A1:E59,5,False) * B8 -> #N/A | H8: =G8/$G$17 -> #N/A
A9: Лимонный сок | B9: 25 | C9: 20 | D9: мл | E9: =B9-C9 -> 5 | F9: =E9/B9*100 -> 20 | G9: =VLOOKUP(A9,'Матрица поставщиков'!A1:E60,5,False) * B9 -> 7.1 | H9: =G9/$G$17 -> #N/A
A10: Томатная паста | B10: 12 | C10: 10 | D10: г | E10: =B10-C10 -> 2 | F10: =E10/B10*100 -> 16.666667 | G10: =VLOOKUP(A10,'Матрица поставщиков'!A1:E53,5,0) * B10 -> 1.236 | H10: =G10/$G$17 -> #N/A
A11: Соль | B11: 20 | C11: 20 | D11: г | E11: =B11-C11 -> 0 | F11: =E11/B11*100 -> 0 | G11: =VLOOKUP(A11,'Матрица поставщиков'!A1:E57,5,False) * B11 -> 0.84 | H11: =G11/$G$17 -> #N/A
A12: Чёрный перец | B12: 2 | C12: 2 | D12: г | E12: =B12-C12 -> 0 | F12: =E12/B12*100 -> 0 | G12: =VLOOKUP(A12,'Матрица поставщиков'!A1:E60,5,False) * B12 -> 2.114 | H12: =G12/$G$17 -> #N/A
A13: Паприка | B13: 3 | C13: 3 | D13: г | E13: =B13-C13 -> 0 | F13: =E13/B13*100 -> 0 | G13: =VLOOKUP(A13,'Матрица поставщиков'!A1:E61,5,False) * B13 -> 2.01 | H13: =G13/$G$17 -> #N/A
A14: Зира (кумин) | B14: 2 | C14: 2 | D14: мл | E14: =B14-C14 -> 0 | F14: =E14/B14*100 -> 0 | G14: =VLOOKUP(A14,'Матрица поставщиков'!A1:E62,5,False) * B14 -> 1.8066667 | H14: =G14/$G$17 -> #N/A
A15: Сумах | B15: 2 | C15: 2 | E15: =B15-C15 -> 0 | F15: =E15/B15*100 -> 0 | G15: =VLOOKUP(A15,'Матрица поставщиков'!A1:E62,5,False) * B15 -> 2.3 | H15: =G15/$G$17 -> #N/A
A16: Кориандр молотый | B16: 1 | C16: 1 | E16: =B16-C16 -> 0 | F16: =E16/B16*100 -> 0 | G16: =VLOOKUP(A16,'Матрица поставщиков'!A1:E64,5,False) * B16 -> 0.68 | H16: =G16/$G$17 -> #N/A
A17: Итого | B17: =SUM(B3:B16) -> 1374 | C17: =SUM(C3:C16) -> 1115 | D17: - | E17: =SUM(E3:E16) -> 259 | F17: =SUM(F3:F16) -> 114.64986 | G17: =SUM(G3:G16) -> #N/A | H17: =SUM(H3:H16) -> #N/A | I17: =B17-E17 -> 1115
A19: Технология приготовления
A20: 1. Нарезать говядину тонкими слайсами (0.2–0.5 см) поперёк волокон в виде прямоугольников 2. Смешать все ингредиенты маринада до однородности 3. Выложить мясо в квадратную форму для выпекания, расположив слайсы в одном направлении разреза волоков 4. Замариновать мясо и выдержать 12-16 часов в холодильнике

Sheet пф курица готовая
A1: Наименование ТТК: | B1: п/ф мясо жареннное
A3: Ингредиент | B3: Брутто | C3: Нетто | D3: Ед.изм. | E3: Объём потери | F3: % потери | G3: с/с руб. | H3: с/с % | I3: Выход (г.) | K3: выход | L3: с/с
A4: п/ф курица маринованная | B4: 1000 | C4: 750 | D4: г | E4: =B4-C4 -> 250 | F4: =E4/B4*100 -> 25 | G4: ='пф курица маринованная'!G10/'пф курица маринованная'!I10*B4 -> 384.42338 | H4: =G4/$G$6 -> 0.99684163 | K4: 100 | L4: =G6/I6*K4 -> 51.418851
A5: масло растительное | B5: 10 | C5: 0 | D5: мл | E5: =B5-C5 -> 10 | F5: =E5/B5*100 -> 100 | G5: ='Матрица поставщиков'!E10*B5 -> 1.218 | H5: =G5/$G$6 -> 0.0031583747 | K5: 1000 | L5: =G6/I6*K5 -> 514.18851
A6: Итого | B6: =SUM(B4:B5) -> 1010 | C6: =SUM(C4) -> 750 | D6: - | E6: =sum(E4:E5) -> 260 | F6: - | G6: =sum(G4:G5) -> 385.64138 | H6: =sum(H4:H5) -> 1 | I6: =B6-E6 -> 750
A8: Технология приготовления
A9: 1. Смазать растительным маслом предварительно нагретый гриль до 200 2. Выложить куски мяса равномерно распределив их по площади жарочной поверхности 3. Обжарить до золотистой корочки 5 минут с каждой стороны, контролировать, если пригорает убавить температуру. 4. Проверить готовность, разрезая мясо попололам шпателем или щипцами 5. Выложить готовое мясо в тару для хранения готовго мяса

Sheet пф говядина готовая
A1: Наименование ТТК: | B1: п/ф мясо жареннное
A3: Ингредиент | B3: Брутто | C3: Нетто | D3: Ед.изм. | E3: Объём потери | F3: % потери | G3: с/с руб. | H3: с/с % | I3: Выход (г.) | K3: выход | L3: с/с
A4: п/ф говядина маринованная | B4: 1000 | C4: 800 | D4: г | E4: =B4-C4 -> 200 | F4: =E4/B4*100 -> 20 | G4: ='пф говядина маринованная'!G17/'пф говядина маринованная'!I17*B4 -> #N/A | H4: =G4/$G$6 -> #N/A | K4: 100 | L4: =G6/I6*K4 -> #N/A
A5: масло растительное | B5: 20 | C5: 20 | D5: мл | E5: =B5-C5 -> 0 | F5: =E5/B5*100 -> 0 | G5: ='Матрица поставщиков'!E10*B5 -> 2.436 | H5: =G5/$G$6 -> #N/A | K5: 1000 | L5: =G6/I6*K5 -> #N/A
A6: Итого | B6: =SUM(B4:B5) -> 1020 | C6: =SUM(C4) -> 800 | D6: - | E6: =sum(E4:E5) -> 200 | F6: - | G6: =sum(G4:G5) -> #N/A | H6: =sum(H4:H5) -> #N/A | I6: =B6-E6 -> 820
A8: Технология приготовления
A9: 1. Запекать при 90 °C 2.5–3 часа под фольгой (протомить) 2. Остудить до 45 °C 3. Нарезать поперёк слоёв и выложить в тепловой мармид

Sheet пф Сырный дип
A1: Наименование ТТК: | B1: п/ф Сырный дип
A3: Ингредиент | B3: Брутто | C3: Нетто | D3: Ед.изм. | E3: Объём потери | F3: % потери | G3: с/с руб. | H3: с/с % | I3: Выход (г.) | K3: выход | L3: с/с
A4: Сливки 22% | B4: 200 | C4: 200 | D4: г | E4: =B4-C4 -> 0 | F4: =E4/B4*100 -> 0 | G4: =VLOOKUP(A4,'Матрица поставщиков'!A1:E530,5,0) * B4 -> 66.8 | H4: =G4/$G$13 -> 0.22551873 | K4: 100 | L4: =G13/I13*K4 -> 65.823556
A5: Чеддер для соуса плавленый | B5: 250 | C5: 250 | D5: г | E5: =B5-C5 -> 0 | F5: =E5/B5*100 -> 0 | G5: =VLOOKUP(A5,'Матрица поставщиков'!A1:E545,5,0) * B5 -> 150 | H5: =G5/$G$13 -> 0.50640433 | K5: 1 | L5: =G13/I13*K5 -> 0.65823556
A6: Моцарелла | B6: 100 | C6: 100 | D6: г | E6: =B6-C6 -> 0 | F6: =E6/B6*100 -> 0 | G6: =VLOOKUP(A6,'Матрица поставщиков'!A2:E550,5,0) * B6 -> 77.8 | H6: =G6/$G$13 -> 0.26265504 | K6: 40 | L6: =G13/I13*K6 -> 26.329422
A7: Паприка | B7: 1 | C7: 1 | D7: г | E7: =B7-C7 -> 0 | F7: =E7/B7*100 -> 0 | G7: =VLOOKUP(A7,'Матрица поставщиков'!A2:E200,5,0) * B7 -> 0.67 | H7: =G7/$G$13 -> 0.0022619393
A8: Чеснок (сушёный) | B8: 1 | C8: 1 | D8: г | E8: =B8-C8 -> 0 | F8: =E8/B8*100 -> 0 | G8: =VLOOKUP(A8,'Матрица поставщиков'!A1:E55,5,0) * B8 -> 0.894 | H8: =G8/$G$13 -> 0.0030181698
A9: Соль | B9: 1 | C9: 1 | D9: г | E9: =B9-C9 -> 0 | F9: =E9/B9*100 -> 0 | G9: =VLOOKUP(A9,'Матрица поставщиков'!A1:E56,5,0) * B9 -> 0.042 | H9: =G9/$G$13 -> 0.00014179321
A10: Зира (кумин) | B10: 1 | C10: 1 | D10: г | E10: =B10-C10 -> 0 | F10: =E10/B10*100 -> 0 | G10: =VLOOKUP(A10,'Матрица поставщиков'!A2:E57,5,0) * B10 -> 0.90333333 | H10: =G10/$G$13 -> 0.0030496794
A11: копченая паприка 1 | B11: 1 | C11: 1 | D11: г | E11: =B11-C11 -> 0 | F11: =E11/B11*100 -> 0 | G11: =VLOOKUP(A11,'Матрица поставщиков'!A3:E58,5,0) * B11 -> 0.7 | H11: =G11/$G$13 -> 0.0023632202
A12: Цитрат натрия | B12: 0.5 | C12: 0.5 | D12: г | E12: =B12-C12 -> 0 | F12: =E12/B12*100 -> 0 | G12: =VLOOKUP(A12,'Матрица поставщиков'!A4:E590,5,0) * B12 -> 0.1925 | H12: =G12/$G$13 -> 0.00064988555
A13: Итого | B13: =SUM(B4:B9) -> 553 | C13: =SUM(C4:C9) -> 553 | D13: - | E13: =B13-C13 -> 0 | F13: =E13/B13*100 -> 0 | G13: =sum(G4:G9) -> 296.206 | H13: =sum(H4:H9) -> 1 | I13: 450
A15: Технология приготовления
A16: 1. Подготовить смесь специй 2. Добавляем смесь специй и сливки в сотейник или кастрюлю. 3. Разогреваем на 1000 Вт до закипания 4. После закипания ставим 60 градусов 5. Добавляем моцареллу, перемешываем до её расворния и однородной массы. 6. Добавляем плавленный чеддер, перемешиваем до растворения на 100 градусов 7. Готово. Даем настояться 30-40 мин. 8. Расфасовать в соусники 80мл по 50 гр.
B20: 1 гр | C20: =G13/I13 -> 0.65823556
B21: 50 | C21: =B21*C20 -> 32.911778

Sheet пф соус для суджука
A1: Наименование ТТК: | B1: п/ф соус для суджука
A3: Ингредиент | B3: Брутто | C3: Нетто | D3: Ед.изм. | E3: Объём потери | F3: % потери | G3: с/с руб. | H3: с/с % | I3: Выход (г.) | K3: выход | L3: с/с
A4: Томатная паста | B4: 120 | C4: 120 | D4: г | E4: =B4-C4 -> 0 | F4: =E4/B4*100 -> 0 | G4: =VLOOKUP(A4,'Матрица поставщиков'!A1:E530,5,0) * B4 -> 12.36 | H4: =G4/$G$14 -> 0.3867909 | K4: 100 | L4: =G14/I14*K4 -> 14.525114
A5: Вода | B5: 100 | C5: 100 | D5: г | E5: =B5-C5 -> 0 | F5: =E5/B5*100 -> 0 | G5: =VLOOKUP(A5,'Матрица поставщиков'!A1:E545,5,0) * B5 -> 0 | H5: =G5/$G$14 -> 0 | K5: 1 | L5: =G14/I14*K5 -> 0.14525114
A6: Паприка | B6: 3 | C6: 0 | D6: г | E6: =B6-C6 -> 3 | F6: =E6/B6*100 -> 100 | G6: =VLOOKUP(A6,'Матрица поставщиков'!A2:E200,5,0) * B6 -> 2.01 | H6: =G6/$G$14 -> 0.062900462
A7: Чеснок (сушёный) | B7: 3 | C7: 0 | D7: г | E7: =B7-C7 -> 3 | F7: =E7/B7*100 -> 100 | G7: =VLOOKUP(A7,'Матрица поставщиков'!A1:E55,5,0) * B7 -> 2.682 | H7: =G7/$G$14 -> 0.083929871
A8: Чёрный перец | B8: 1 | C8: 0 | D8: г | E8: =B8-C8 -> 1 | F8: =E8/B8*100 -> 100 | G8: =VLOOKUP(A8,'Матрица поставщиков'!A1:E56,5,0) * B8 -> 1.057 | H8: =G8/$G$14 -> 0.033077507
A9: Зира (кумин) | B9: 0.5 | C9: 0 | D9: г | E9: =B9-C9 -> 0.5 | F9: =E9/B9*100 -> 100 | G9: =VLOOKUP(A9,'Матрица поставщиков'!A2:E57,5,0) * B9 -> 0.45166667 | H9: =G9/$G$14 -> 0.014134349
A10: Сахар | B10: 5 | C10: 0 | D10: г | E10: =B10-C10 -> 5 | F10: =E10/B10*100 -> 100 | G10: =VLOOKUP(A10,'Матрица поставщиков'!A3:E58,5,0) * B10 -> 0.345 | H10: =G10/$G$14 -> 0.010796348
A11: Орегано | B11: 1 | C11: 0 | D11: г | E11: =B11-C11 -> 1 | F11: =E11/B11*100 -> 100 | G11: =VLOOKUP(A11,'Матрица поставщиков'!A4:E590,5,0) * B11 -> 1.36 | H11: =G11/$G$14 -> 0.042559517
A12: Лук гранулированный | B12: 5 | C12: 0 | D12: г | E12: =B12-C12 -> 5 | F12: =E12/B12*100 -> 100 | G12: =VLOOKUP(A12,'Матрица поставщиков'!A5:E591,5,0) * B12 -> 5.7395833 | H12: =G12/$G$14 -> 0.17961316
A13: Исот | B13: 5 | C13: 0 | D13: г | E13: =B13-C13 -> 5 | F13: =E13/B13*100 -> 100 | G13: =VLOOKUP(A13,'Матрица поставщиков'!A6:E592,5,0) * B13 -> 5.95 | H13: =G13/$G$14 -> 0.18619789
A14: Итого | B14: =SUM(B4:B8) -> 227 | C14: =SUM(C4:C8) -> 220 | D14: - | E14: =B14-C14 -> 7 | F14: =E14/B14*100 -> 3.0837004 | G14: =SUM(G4:G13) -> 31.95525 | H14: =SUM(H4:H13) -> 1 | I14: =B14-E14 -> 220
A16: Технология приготовления
B21: 1 гр | C21: =G14/I14 -> 0.14525114
B22: 50 | C22: =B22*C21 -> 7.2625568

Sheet пф обмазка балыка
A1: Наименование ТТК: | B1: п/ф обмазка балыка
A3: Ингредиент | B3: Брутто | C3: Нетто | D3: Ед.изм. | E3: Объём потери | F3: % потери | G3: с/с руб. | H3: с/с % | I3: Выход (г.) | K3: выход | L3: с/с
A4: Соевый соус | B4: 300 | C4: 300 | D4: г | E4: =B4-C4 -> 0 | F4: =E4/B4*100 -> 0 | G4: =VLOOKUP(A4,'Матрица поставщиков'!A1:E530,5,0) * B4 -> 33.3 | H4: =G4/$G$8 -> 0.30242024 | K4: 100 | L4: =G8/I8*K4 -> 19.317838
A5: п/ф соус Нар | B5: 200 | C5: 200 | D5: г | E5: =B5-C5 -> 0 | F5: =E5/B5*100 -> 0 | G5: ='пф соус Нар'!C13*B5 -> 58.321678 | H5: =G5/$G$8 -> 0.52965934 | K5: 1 | L5: =G8/I8*K5 -> 0.19317838
A6: Масло оливковое | B6: 50 | C6: 50 | D6: г | E6: =B6-C6 -> 0 | F6: =E6/B6*100 -> 0 | G6: =VLOOKUP(A6,'Матрица поставщиков'!A2:E200,5,0) * B6 -> 12.81 | H6: =G6/$G$8 -> 0.11633643
A7: Лимонный сок | B7: 20 | C7: 20 | D7: г | E7: =B7-C7 -> 0 | F7: =E7/B7*100 -> 0 | G7: =VLOOKUP(A7,'Матрица поставщиков'!A1:E55,5,0) * B7 -> 5.68 | H7: =G7/$G$8 -> 0.051583993
A8: Итого | B8: =SUM(B4:B7) -> 570 | C8: =SUM(C4:C7) -> 570 | D8: - | E8: =B8-C8 -> 0 | F8: =E8/B8*100 -> 0 | G8: =SUM(G4:G7) -> 110.11168 | H8: =SUM(H4:H7) -> 1 | I8: =B8-E8 -> 570
A10: Технология приготовления
B15: 1 гр | C15: =G8/I8 -> 0.19317838
B16: 50 | C16: =B16*C15 -> 9.6589192

Sheet пф айсберг
A1: Наименование ТТК: | B1: п/ф айсберг
A3: Ингредиент | B3: Брутто | C3: Нетто | D3: Ед.изм. | E3: Объём потери | F3: % потери | G3: с/с руб. | H3: с/с % | I3: Выход (г.) | K3: выход | L3: с/с
A4: Айсберг | B4: 410 | C4: 330 | D4: г | E4: =B4-C4 -> 80 | F4: =E4/B4*100 -> 19.512195 | G4: =VLOOKUP(A4,'Матрица поставщиков'!A1:E530,5,0) * B4 -> 97.99 | H4: =G4/$G$5 -> 1 | K4: 100 | L4: =G5/I5*K4 -> 29.693939
A5: Итого | B5: =SUM(B4) -> 410 | C5: =SUM(C4) -> 330 | D5: - | E5: =B5-C5 -> 80 | F5: =E5/B5*100 -> 19.512195 | G5: =SUM(G4) -> 97.99 | H5: =SUM(H4) -> 1 | I5: =B5-E5 -> 330
A7: Технология приготовления
A8: Айсберг: вырезать кочерыжку, нашинковать. Морковь очистить и натереть на терке. Смешать
B12: 1 гр | C12: =G5/I5 -> 0.29693939
B13: 50 | C13: =B13*C12 -> 14.84697

Sheet пф скумбрия
A1: Наименование ТТК: | B1: п/ф скумбрия
A3: Ингредиент | B3: Брутто | C3: Нетто | D3: Ед.изм. | E3: Объём потери | F3: % потери | G3: с/с руб. | H3: с/с % | I3: Выход (г.) | K3: выход | L3: с/с
A4: Скумбрия | B4: 100 | C4: 50 | D4: г | E4: =B4-C4 -> 50 | F4: =E4/B4*100 -> 50 | G4: =VLOOKUP(A4,'Матрица поставщиков'!A1:E530,5,0) * B4 -> 55 | H4: =G4/$G$7 -> 0.98904854 | K4: 100 | L4: =G7/I7*K4 -> 101.10727
A5: Масло растительное | B5: 5 | C5: 5 | D5: г | E5: =B5-C5 -> 0 | F5: =E5/B5*100 -> 0 | G5: =VLOOKUP(A5,'Матрица поставщиков'!A1:E545,5,0) * B5 -> 0.609 | H5: =G5/$G$7 -> 0.010951465 | K5: 1 | L5: =G7/I7*K5 -> 1.0110727
A6: Соль | B6: 2 | C6: 2 | D6: г | E6: =B6-C6 -> 0 | F6: =E6/B6*100 -> 0 | G6: =VLOOKUP(A6,'Матрица поставщиков'!A2:E546,5,0) * B6 -> 0.084 | H6: =G6/$G$7 -> 0.0015105469
A7: Итого | B7: =SUM(B4:B5) -> 105 | C7: =SUM(C4:C5) -> 55 | D7: - | E7: =B7-C7 -> 50 | F7: =E7/B7*100 -> 47.619048 | G7: =SUM(G4:G5) -> 55.609 | H7: =SUM(H4:H5) -> 1 | I7: =B7-E7 -> 55
A9: Технология приготовления
A10: Филировать рыбу, добавить масло и соль
B14: 1 гр | C14: =G7/I7 -> 1.0110727
B15: 50 | C15: =B15*C14 -> 50.553636

Sheet пф перец сладкий
A1: Наименование ТТК: | B1: п/ф перец сладкий
A3: Ингредиент | B3: Брутто | C3: Нетто | D3: Ед.изм. | E3: Объём потери | F3: % потери | G3: с/с руб. | H3: с/с % | I3: Выход (г.) | K3: выход | L3: с/с
A4: Перец красный сладкий | B4: 100 | C4: 88 | D4: г | E4: =B4-C4 -> 12 | F4: =E4/B4*100 -> 12 | G4: =VLOOKUP(A4,'Матрица поставщиков'!A1:E530,5,0) * B4 -> 20.5 | H4: =G4/$G$5 -> 1 | K4: 100 | L4: =G5/I5*K4 -> 23.295455
A5: Итого | B5: =SUM(B4) -> 100 | C5: =SUM(C4) -> 88 | D5: - | E5: =B5-C5 -> 12 | F5: =E5/B5*100 -> 12 | G5: =SUM(G4) -> 20.5 | H5: =SUM(H4) -> 1 | I5: =B5-E5 -> 88
A7: Технология приготовления
A8: Вдавить внутрь хвостик, разломить на две части, удалить хвостик, семена, перегородки. Промыть водой
B12: 1 гр | C12: =G5/I5 -> 0.23295455
B13: 50 | C13: =B13*C12 -> 11.647727

Sheet пф соус Нар
A1: Наименование ТТК: | B1: п/ф Соус Нар
A3: Ингредиент | B3: Брутто | C3: Нетто | D3: Ед.изм. | E3: Объём потери | F3: % потери | G3: с/с руб. | H3: с/с % | I3: Выход (г.) | K3: выход | L3: с/с
A4: Наршараб | B4: 500 | C4: 500 | D4: г | E4: =B4-C4 -> 0 | F4: =E4/B4*100 -> 0 | G4: =VLOOKUP(A4,'Матрица поставщиков'!A1:E530,5,0) * B4 -> 115.38462 | H4: =G4/$G$6 -> 0.71942446 | K4: 100 | L4: =G6/I6*K4 -> 29.160839
A5: Соус гриль | B5: 50 | C5: 50 | D5: г | E5: =B5-C5 -> 0 | F5: =E5/B5*100 -> 0 | G5: =VLOOKUP(A5,'Матрица поставщиков'!A1:E545,5,0) * B5 -> 45 | H5: =G5/$G$6 -> 0.28057554 | K5: 1 | L5: =G6/I6*K5 -> 0.29160839
A6: Итого | B6: =SUM(B4:B5) -> 550 | C6: =SUM(C4:C5) -> 550 | D6: - | E6: =B6-C6 -> 0 | F6: =E6/B6*100 -> 0 | G6: =sum(G4:G5) -> 160.38462 | H6: =sum(H4:H5) -> 1 | I6: =C6 -> 550
A8: Технология приготовления
A9: Смешать до однородной консистенции.
B13: 1 гр | C13: =G6/I6 -> 0.29160839
B14: 50 | C14: =B14*C13 -> 14.58042

Sheet пф искандер соус по-Хатайски
A1: Наименование ТТК: | B1: п/ф искандер соус по-Хатайски
A3: Ингредиент | B3: Брутто | C3: Нетто | D3: Ед.изм. | E3: Объём потери | F3: % потери | G3: с/с руб. | H3: с/с % | I3: Выход (мл)
A4: Сливочное масло | B4: 15 | C4: 15 | D4: г | E4: =B4-C4 -> 0 | F4: =E4/B4*100 -> 0 | G4: =VLOOKUP(A4,'Матрица поставщиков'!A1:E43,5,False) * B4 -> 14.966667 | H4: =G4/$G$19 -> #REF!
A5: Томатная паста | B5: 40 | C5: 40 | D5: г | E5: =B5-C5 -> 0 | F5: =E5/B5*100 -> 0 | G5: =VLOOKUP(A5,'Матрица поставщиков'!A1:E43,5,False) * B5 -> 4.12 | H5: =G5/$G$19 -> #REF!
A6: п/ф луковый сок | B6: 40 | C6: 40 | D6: мл | E6: =B6-C6 -> 0 | F6: =E6/B6*100 -> 0 | G6: ='п/ф луковый сок'!G5/'п/ф луковый сок'!I5 *B6 -> #REF! | H6: =G6/$G$19 -> #REF!
A7: Тимьян / Чабрец | B7: 2 | C7: 2 | D7: г | E7: =B7-C7 -> 0 | F7: =E7/B7*100 -> 0 | G7: =VLOOKUP(A7,'Матрица поставщиков'!A1:E43,5,False) * B7 -> 1.656 | H7: =G7/$G$19 -> #REF!
A8: Красный молотый перец | B8: 2 | C8: 2 | D8: г | E8: =B8-C8 -> 0 | F8: =E8/B8*100 -> 0 | G8: =VLOOKUP(A8,'Матрица поставщиков'!A1:E43,5,False) * B8 -> 3.3369863 | H8: =G8/$G$19 -> #REF!
A9: Сушёная мята | B9: 2 | C9: 2 | D9: г | E9: =B9-C9 -> 0 | F9: =E9/B9*100 -> 0 | G9: =VLOOKUP(A9,'Матрица поставщиков'!A1:E43,5,False) * B9 -> 3.7666667 | H9: =G9/$G$19 -> #REF!
A10: Чёрный перец | B10: 2 | C10: 2 | D10: г | E10: =B10-C10 -> 0 | F10: =E10/B10*100 -> 0 | G10: =VLOOKUP(A10,'Матрица поставщиков'!A1:E43,5,False) * B10 -> 2.114 | H10: =G10/$G$19 -> #REF!
A11: Масло растительное | B11: 45 | C11: 45 | D11: г | E11: =B11-C11 -> 0 | F11: =E11/B11*100 -> 0 | G11: =VLOOKUP(A11,'Матрица поставщиков'!A1:E43,5,False) * B11 -> 5.481 | H11: =G11/$G$19 -> #REF!
A12: Тмин | B12: 2 | C12: 2 | D12: г | E12: =B12-C12 -> 0 | F12: =E12/B12*100 -> 0 | G12: =VLOOKUP(A12,'Матрица поставщиков'!A1:E43,5,False) * B12 -> 2.4326531 | H12: =G12/$G$19 -> #REF!
A13: Кориандр | B13: 2 | C13: 2 | D13: г | E13: =B13-C13 -> 0 | F13: =E13/B13*100 -> 0 | G13: =VLOOKUP(A13,'Матрица поставщиков'!A1:E43,5,False) * B13 -> 2.4875 | H13: =G13/$G$19 -> #REF!
A14: Лимон | B14: 10 | C14: 10 | D14: г | E14: =B14-C14 -> 0 | F14: =E14/B14*100 -> 0 | G14: =VLOOKUP(A14,'Матрица поставщиков'!A1:E43,5,False) * B14 -> 2.59 | H14: =G14/$G$19 -> #REF!
A15: Корица | B15: 0.5 | C15: 0.5 | D15: г | E15: =B15-C15 -> 0 | F15: =E15/B15*100 -> 0 | G15: =VLOOKUP(A15,'Матрица поставщиков'!A1:E43,5,False) * B15 -> 0.67 | H15: =G15/$G$19 -> #REF!
A16: Сахар | B16: 5 | C16: 5 | D16: г | E16: =B16-C16 -> 0 | F16: =E16/B16*100 -> 0 | G16: =VLOOKUP(A16,'Матрица поставщиков'!A1:E43,5,False) * B16 -> 0.345 | H16: =G16/$G$19 -> #REF!
A17: Соль | B17: 5 | C17: 5 | D17: г | E17: =B17-C17 -> 0 | F17: =E17/B17*100 -> 0 | G17: =VLOOKUP(A17,'Матрица поставщиков'!A1:E43,5,False) * B17 -> 0.21 | H17: =G17/$G$19 -> #REF!
A18: Вода | B18: 500 | C18: 500 | D18: мл | E18: 50 | F18: =E18/B18*100 -> 10 | G18: 0 | H18: =G18/$G$19 -> #REF!
A19: Итого | B19: =SUM(B4:B18) -> 672.5 | C19: =SUM(C4:C18) -> 672.5 | D19: - | E19: =SUM(E4:E18) -> 50 | F19: - | G19: =SUM(G4:G18) -> #REF! | H19: =G19/$G$19 -> #REF! | I19: =B19-E19 -> 622.5
A21: Технология приготовления
A22: 1. Разогрейть растительное масло в сотейнике на среднем огне. 2. Добавить томатную пасту и обжарить 2 минуты. Масло должно впитаться в томатную пасту. Паста должна получить рыхлую структуру. 3. Влить кипяток, добавить луковый сок, ломтик лимона 4. Довести соус до кипения на среднем огне. 5. Добавить все специи. 6. Уменьшить огонь до слабого и варить соус 10–15 минут до лёгкого загустения. 7. Добавить сливочное масло и перемешать до полного растворения. *Подавать горячим (чем чаще греете, тем больше воды выпаривается и гуще становится)
